Workbook
Name Active_Engine_Ref: 'CHART DATA'!$M$2
Name Age_Range: 'CHART DATA'!$A$2:INDEX('CHART DATA'!$A$2:$A$102,Horizon_Rows)
Name AgeContrib_Range: 'CHART DATA'!$N$2:INDEX('CHART DATA'!$N$2:$N$102,Horizon_Rows)
Name AgeMilestone_Range: 'CHART DATA'!$H$2:INDEX('CHART DATA'!$H$2:$H$102,Horizon_Rows)
Name Bracket_Round_MFS: 'CONSTANTS & REFERENCES'!$B$17
Name Bracket_Round_Standard: 'CONSTANTS & REFERENCES'!$B$16
Name Contribution_Range: 'CHART DATA'!$O$2:INDEX('CHART DATA'!$O$2:$O$102,Horizon_Rows)
Name DisposablePay_Range: 'CHART DATA'!$F$2:INDEX('CHART DATA'!$F$2:$F$102,Horizon_Rows)
Name FedTax_Range: 'CHART DATA'!$S$2:INDEX('CHART DATA'!$S$2:$S$102,Horizon_Rows)
Name Growth_Range: 'CHART DATA'!$P$2:INDEX('CHART DATA'!$P$2:$P$102,Horizon_Rows)
Name GrowthMultiple_Range: 'PERIODIC ENGINE'!$L$2:INDEX('PERIODIC ENGINE'!$L$2:$L$102,Horizon_Rows)
Name Head_Household_STD_Deduction: #REF!
Name Horizon_Rows: 'CHART DATA'!$AZ$2
Name Horizon_Years: 'CHART DATA'!$AY$2
Name Inp_Age_Retire: #REF!
Name Inp_Age_Start: #REF!
Name Inp_Rate_Inf: #REF!
Name Inp_Wage_Base: #REF!
Name Inp_Wage_Merit: #REF!
Name IRA_Base: #REF!
Name IRA_Catch_Base: #REF!
Name IRA_Catch_Step: #REF!
Name IRA_Step: #REF!
Name Joint_Spouse_STD_Deduction: #REF!
Name Limit_OASDI: #REF!
Name Med_Threshold: #REF!
Name NominalBal_Range: 'CHART DATA'!$B$2:INDEX('CHART DATA'!$B$2:$B$102,Horizon_Rows)
Name NominalMilestone_Range: 'CHART DATA'!$I$2:INDEX('CHART DATA'!$I$2:$I$102,Horizon_Rows)
Name Payroll_Range: 'CHART DATA'!$U$2:INDEX('CHART DATA'!$U$2:$U$102,Horizon_Rows)
Name ProjYear_Range: 'CHART DATA'!$E$2:INDEX('CHART DATA'!$E$2:$E$102,Horizon_Rows)
Name ProjYearTax_Range: 'CHART DATA'!$R$2:INDEX('CHART DATA'!$R$2:$R$102,Horizon_Rows)
Name Rate_Med: #REF!
Name Rate_OASDI: #REF!
Name RealBal_Range: 'CHART DATA'!$C$2:INDEX('CHART DATA'!$C$2:$C$102,Horizon_Rows)
Name Single_Separately_STD_Deduction: #REF!
Name StateTax_Range: 'CHART DATA'!$T$2:INDEX('CHART DATA'!$T$2:$T$102,Horizon_Rows)
Name TakeHome_Range: 'CHART DATA'!$V$2:INDEX('CHART DATA'!$V$2:$V$102,Horizon_Rows)
Name Tax_Step: #REF!
Name TerminalValueByYear_Range: 'PERIODIC ENGINE'!$Q$2:INDEX('PERIODIC ENGINE'!$Q$2:$Q$102,Horizon_Rows)
Name Threshold1M_Range: 'CHART DATA'!$K$2:INDEX('CHART DATA'!$K$2:$K$102,Horizon_Rows)
Name Threshold2M_Range: 'CHART DATA'!$L$2:INDEX('CHART DATA'!$L$2:$L$102,Horizon_Rows)
Name Threshold500k_Range: 'CHART DATA'!$J$2:INDEX('CHART DATA'!$J$2:$J$102,Horizon_Rows)

Sheet README
A1: IRA RETIREMENT MODEL
A2: Instructions, methodology, assumptions, and limitations
A4: PURPOSE
A5: This workbook projects an IRA balance from a starting age through retirement using transparent annual time-value-of-money formulas.
A7: HOW TO USE THE MODEL
A8: 1. Open INPUTS and answer the highlighted questions.
A9: 2. Select whether contributions occur at the beginning or end of each year.
A10: 3. Review the year-by-year roll-forward on ENGINE.
A11: 4. Review retirement results and the nominal-versus-real chart on OUTPUT.
A12: 5. Actuary Mode stores career assumptions for a future salary module; it does not currently change IRA accumulation.
A14: WORKBOOK STRUCTURE
A15: Sheet | B15: Purpose | C15: User action
A16: INPUTS | B16: Conversational assumptions | C16: Edit the highlighted cells
A17: ENGINE | B17: Annual accumulation schedule | C17: Review formulas and audit trail
A18: OUTPUT | B18: Review retirement results | C18: Review retirement results
A19: MILESTONES | B19: First-year threshold analysis for $500k, $1m, and $2m balances | C19: Review
A20: CONSTANTS & REFERENCES | B20: Research notes and future official-source inputs | C20: Review / update
A21: EXAM FM CONCEPTS
A22: Concept | B22: Formula demonstrated | C22: Purpose
A23: Compound accumulation | B23: Beginning Balance × (1 + annual return) | C23: Annual interest accumulation
A24: Growing contributions | B24: Initial Contribution × (1 + growth)^(t − delay − 1) | C24: Contributions made over time
A25: Real balance | B25: Nominal Ending Balance ÷ Inflation Index | C25: Inflation-adjusted retirement value
A26: Future-value cross-check | B26: FV for starting balance + sum of each contribution's FV | C26: Independent validation of the roll-forward
A28: ASSUMPTIONS & LIMITATIONS
A29: Returns, inflation, and contribution growth are flat effective annual assumptions, not forecasts.
A30: The model includes a simplified 2026 federal income-tax module, Social Security and Medicare payroll taxes, and an optional illustrative flat state income tax. It does not model credits, itemized deductions, local taxes, or employer benefits.
A31: Illustrative IRA contribution limits are indexed within the model. Roth eligibility, MAGI phase-outs, earned-income limits, and future official IRS limits are not modeled. | C31: n
A32: Educational project only; not tax, legal, actuarial, or investment advice.
A33: Tax interface note: the filing status can change after a user-selected number of projection years. State tax is intentionally simplified and applies a flat rate to federal taxable income.
A37: PERIODIC CONTRIBUTION MODEL
A38: The annual effective investment return is converted using (1 + annual return)^(1 / selected periods per year) - 1. Users do not enter a separate periodic return.
A39: The annual modeled Roth limit remains indexed once per projection year and is divided evenly across the selected contribution periods.
A40: Advanced mode uses 252 trading days divided by the selected valid interval. IRA and C-CPI-U indexing remain annual in both standard and advanced modes.

Sheet INPUTS
B2: Let’s build your IRA projection.
B3: Answer the highlighted questions and the model will project your account over time.
B5: Let’s start with your IRA
B6: What's your starting age? | C6: 22 | D6: years
B7: At what age do you plan to retire? | C7: 65 | D7: years
B8: What's your current IRA balance? | C8: 0 | D8: nominal dollars
B9: How often will you contribute to your IRA? | C9: Annual | D9: =IF($C$39="On","Ignored while advanced trading-day contributions are On","Annual, Semiannual, Quarterly, Monthly, Biweekly, or Weekly") -> Annual, Semiannual, Quarterly, Monthly, Biweekly, or Weekly
B10: What annual investment return should we assume? | C10: 0.1 | D10: nominal effective annual rate
B11: What annual inflation rate should we assume? | C11: 0.06 | D11: flat effective annual rate
B12: When during the year will you contribute? | C12: Beginning | D12: Beginning or End
B13: How many years will you wait before contributing? | C13: 0 | D13: full years skipped before the first contribution
B14: Now let’s add your tax and career assumptions
B15: What annual merit raise should we assume? | C15: 0.03 | D15: effective annual rate
B16: What's your starting salary? | C16: 70000 | D16: annual salary
B17: Cap your salary growth? | C17: No | D17: Yes or No
B18: What's the maximum salary you'd like to model? | C18: 275000 | D18: Salary will never exceed this amount | E18: =IF($C$17="Yes","Active","Ignored while cap is No") -> Ignored while cap is No
B19: What federal filing status should we use? | C19: Single | D19: Single, Married Filing Jointly, Married Filing Separately, or Head of Household
B20: Include an illustrative flat state income tax? | C20: No | D20: Simplified state-tax option only
B21: What illustrative flat state income tax rate should we assume? | C21: 0 | D21: Applied to federal taxable income
B22: Illustrative flat state income tax does not model individual state tax codes, credits, deductions, local taxes, or special rules.
B25: Optional & Advanced Inputs
B26: Now let’s add your actuarial career assumptions
B27: Actuary Mode on? | C27: Yes | D27: Yes or No | E27: Controls exam and credential bonuses
B28: Credential Status | C28: ASA / ACAS | D28: Determines which career bonuses still apply | E28: =IF($C$27="Yes","Active","Ignored while Actuary Mode is No") -> Active
B29: If you're already ASA/ACAS or FSA/FCAS, we assume your entered starting salary already reflects those bonuses (we won't add them again).
B30: How many exams do you have left to pass? | C30: 3 | D30: exams remaining (caps cumulative exam bonus) | E30: =IF($C$27<>"Yes","Ignored while Actuary Mode is No",IF($C$28="FSA / FCAS","Already reflected in starting salary","Active")) -> Active
B31: What's the salary raise for each exam passed? | C31: 3000 | D31: per exam pass | E31: =IF($C$27<>"Yes","Ignored while Actuary Mode is No",IF($C$28="FSA / FCAS","Already reflected in starting salary","Active")) -> Active
B32: What's the salary raise when you earn Associate status? | C32: 15000 | D32: one-time increase | E32: =IF($C$27<>"Yes","Ignored while Actuary Mode is No",IF(OR($C$28="ASA / ACAS",$C$28="FSA / FCAS"),"Already reflected in starting salary","Active")) -> Already reflected in starting salary
B33: How many years until Associate status? | C33: 5 | D33: years from today | E33: =IF($C$27<>"Yes","Ignored while Actuary Mode is No",IF(OR($C$28="ASA / ACAS",$C$28="FSA / FCAS"),"Already reflected in starting salary","Active")) -> Already reflected in starting salary
B34: What's the salary raise when you earn Fellowship status? | C34: 15000 | D34: one-time increase | E34: =IF($C$27<>"Yes","Ignored while Actuary Mode is No",IF($C$28="FSA / FCAS","Already reflected in starting salary","Active")) -> Active
B35: How many years until Fellowship? | C35: 4 | D35: years from today | E35: =IF($C$27<>"Yes","Ignored while Actuary Mode is No",IF($C$28="FSA / FCAS","Already reflected in starting salary","Active")) -> Active
B36: How many years until you finish passing exams? | C36: 4 | D36: years (pace = exams remaining ÷ this) | E36: =IF($C$27<>"Yes","Ignored while Actuary Mode is No",IF($C$28="FSA / FCAS","Already reflected in starting salary","Active")) -> Active
B37: Exams Per Year (derived pace) | C37: =IF(C36=0,"—",C30/C36) -> 0.75 | D37: exams remaining ÷ years to finish | E37: =IF($C$27<>"Yes","Ignored while Actuary Mode is No",IF($C$28="FSA / FCAS","Already reflected in starting salary","Calculated")) -> Calculated
B38: Advanced periodic contribution mode
B39: Enable advanced trading-day contributions? | C39: Off | D39: Off uses the frequency selected above; On uses a trading-day interval
B40: Contribute every how many trading days? | C40: 18 | D40: Choose an interval that divides 252 evenly
B41: Trading-Day Contributions per Year | C41: =IF(C39="On",252/C40,"") | D41: 252 trading days ÷ selected interval
B42: Contribution per Trading-Day Period | C42: =IF(C39="On",IFERROR(ENGINE!J2/C41,0),"") | D42: Statutory Roth limit (Year 0) divided by trading-day contributions. This is the limit only, not the delayed actual contribution.
B43: Do you expect your filing status to change? | C43: Yes | D43: Choose Yes to activate the transition inputs
B44: What filing status should we use after the change? | C44: Married Filing Jointly | D44: Applied beginning in the selected projection year
B45: How many years until your filing status changes? | C45: 5 | D45: 0 means the new status applies in Year 0
B47: MODEL NOTES
B48: Contribution delay: 0 contributes in Year 0; x skips x full years and starts in Year x.
B49: Actuary Mode drives the salary path used by the tax and take-home-pay module; it does not change the Roth accumulation mechanics.

Sheet OUTPUT - SUMMARY
A1: IRA Projection Summary
A2: High-level retirement and disposable-income outcomes from the current model assumptions.
A4: Key Results
A6: Final nominal Roth balance | B6: {=LOOKUP(2,1/('CHART DATA'!B2:B102<>""),'CHART DATA'!B2:B102)} -> 11101633
A7: Final real Roth balance | B7: {=LOOKUP(2,1/('CHART DATA'!C2:C102<>""),'CHART DATA'!C2:C102)} -> 906222.15
A8: Total contributions | B8: {=LOOKUP(2,1/('PERIODIC ENGINE'!K2:K102<>""),'PERIODIC ENGINE'!K2:K102)} -> 1630400
A9: Total investment growth | B9: =B6-INPUTS!C8-B8 -> 9471233.3
A10: Money multiplier | B10: =IFERROR(B6/(B8+INPUTS!C8),0) -> 6.809147
A11: Final disposable take-home pay | B11: {=LOOKUP(2,1/(ENGINE!AI2:AI102<>""),ENGINE!AI2:AI102)-LOOKUP(2,1/(ENGINE!D2:D102<>""),ENGINE!D2:D102)} -> 194530.73
A12: The money multiplier above is just an average across all your contributions. The chart below shows why that average hides a wide range.
A13: First contribution's growth multiple | B13: {=INDEX('PERIODIC ENGINE'!L2:L102,MATCH(TRUE,INDEX(ENGINE!D2:D102>0,0),0))} -> 66.264076
A14: Final contribution's growth multiple | B14: {=INDEX('PERIODIC ENGINE'!L2:L102,Horizon_Rows)} -> 1.1
A15: First contribution's terminal value | B15: {=INDEX('PERIODIC ENGINE'!Q2:Q102,MATCH(TRUE,INDEX(ENGINE!D2:D102>0,0),0))} -> 496980.57
A16: Final contribution's terminal value | B16: {=INDEX('PERIODIC ENGINE'!Q2:Q102,Horizon_Rows)} -> 115390
A17: Starting balance's terminal value | B17: =INPUTS!$C$8*(1+'PERIODIC ENGINE'!$S$5)^(Horizon_Rows*'PERIODIC ENGINE'!$S$3) -> 0
A18: Cross-check: seed + all contributions' terminal values vs. actual ending balance | B18: {=ROUND((B17+SUM('PERIODIC ENGINE'!$Q$2:$Q$102))-INDEX('PERIODIC ENGINE'!$J$2:$J$102,Horizon_Rows),2)} -> 0
A19: ="Your dollars didn't grow equally: "&TEXT(B13,"0.0")&"x for your earliest contribution vs. "&TEXT(B14,"0.0")&"x for your last, because early money compounds longer. Your first year's contributions grew into "&TEXT(B15,"$#,##0")&", and your final year's grew into "&TEXT(B16,"$#,##0")&". The charts show the full curve." -> Your dollars didn't grow equally: 66.3x for your earliest contribution vs. 1.1x for your last, because early money compounds longer. Your first year's contributions grew into $496,981, and your final year's grew into $115,390. The charts show the full curve.
A22: Lifetime Tax Summary
A24: Cumulative taxes paid | B24: =SUM(ENGINE!AH2:AH102) -> 911070.78
A25: Cumulative Social Security (OASDI) tax paid | B25: =SUM(ENGINE!AE2:AE102) -> 501452.51
A26: Cumulative gross income earned | B26: =SUM(ENGINE!Y2:Y102) -> 8087943.7
A27: Cumulative effective tax rate | B27: =IFERROR(B24/B26,0) -> 0.11264554
A28: Cumulative effective take-home rate | B28: =1-B27 -> 0.88735446

Sheet OUTPUT - RETIREMENT
A1: IRA Retirement Detail
A2: Annual accumulation, contribution, investment-growth, and inflation-adjusted balances.
A4: Retirement Results
A6: Final nominal balance | B6: ='OUTPUT - SUMMARY'!B6 -> 11101633
A7: Final real balance | B7: ='OUTPUT - SUMMARY'!B7 -> 906222.15
A8: Total contributions | B8: ='OUTPUT - SUMMARY'!B8 -> 1630400
A9: Total investment growth | B9: ='OUTPUT - SUMMARY'!B9 -> 9471233.3
A12: Projection Year | B12: Age | C12: Annual Contribution | D12: Annual Investment Growth | E12: Ending Nominal Balance | F12: Ending Real Balance | G12: Cumulative Contributions | H12: Cumulative Investment Growth | I12: Terminal Value of Contributions
A13: =IF(ENGINE!A2="","",ENGINE!A2) -> 0 | B13: =IF(A13="","",ENGINE!B2) -> 22 | C13: =IF(A13="","",ENGINE!D2) -> 7500 | D13: =IF(A13="","",INDEX('PERIODIC ENGINE'!$I$2:$I$102,MATCH(A13,'PERIODIC ENGINE'!$A$2:$A$102,0))) -> 750 | E13: =IF(A13="","",'CHART DATA'!B2) -> 8250 | F13: =IF(A13="","",'CHART DATA'!C2) -> 8250 | G13: =IF(A13="","",INDEX('PERIODIC ENGINE'!$K$2:$K$102,MATCH(A13,'PERIODIC ENGINE'!$A$2:$A$102,0))) -> 7500 | H13: =IF(A13="","",E13-INPUTS!$C$8-G13) -> 750 | I13: {=IF(A13="","",IFERROR(INDEX(TerminalValueByYear_Range,ROW()-ROW($I$13)+1),""))} -> 496980.57
A14: =IF(ENGINE!A3="","",ENGINE!A3) -> 1 | B14: =IF(A14="","",ENGINE!B3) -> 23 | C14: =IF(A14="","",ENGINE!D3) -> 7500 | D14: =IF(A14="","",INDEX('PERIODIC ENGINE'!$I$2:$I$102,MATCH(A14,'PERIODIC ENGINE'!$A$2:$A$102,0))) -> 1575 | E14: =IF(A14="","",'CHART DATA'!B3) -> 17325 | F14: =IF(A14="","",'CHART DATA'!C3) -> 16344.34 | G14: =IF(A14="","",INDEX('PERIODIC ENGINE'!$K$2:$K$102,MATCH(A14,'PERIODIC ENGINE'!$A$2:$A$102,0))) -> 15000 | H14: =IF(A14="","",E14-INPUTS!$C$8-G14) -> 2325 | I14: {=IF(A14="","",IFERROR(INDEX(TerminalValueByYear_Range,ROW()-ROW($I$13)+1),""))} -> 451800.52
A15: =IF(ENGINE!A4="","",ENGINE!A4) -> 2 | B15: =IF(A15="","",ENGINE!B4) -> 24 | C15: =IF(A15="","",ENGINE!D4) -> 8000 | D15: =IF(A15="","",INDEX('PERIODIC ENGINE'!$I$2:$I$102,MATCH(A15,'PERIODIC ENGINE'!$A$2:$A$102,0))) -> 2532.5 | E15: =IF(A15="","",'CHART DATA'!B4) -> 27857.5 | F15: =IF(A15="","",'CHART DATA'!C4) -> 24793.076 | G15: =IF(A15="","",INDEX('PERIODIC ENGINE'!$K$2:$K$102,MATCH(A15,'PERIODIC ENGINE'!$A$2:$A$102,0))) -> 23000 | H15: =IF(A15="","",E15-INPUTS!$C$8-G15) -> 4857.5 | I15: {=IF(A15="","",IFERROR(INDEX(TerminalValueByYear_Range,ROW()-ROW($I$13)+1),""))} -> 438109.59
A16: =IF(ENGINE!A5="","",ENGINE!A5) -> 3 | B16: =IF(A16="","",ENGINE!B5) -> 25 | C16: =IF(A16="","",ENGINE!D5) -> 8500 | D16: =IF(A16="","",INDEX('PERIODIC ENGINE'!$I$2:$I$102,MATCH(A16,'PERIODIC ENGINE'!$A$2:$A$102,0))) -> 3635.75 | E16: =IF(A16="","",'CHART DATA'!B5) -> 39993.25 | F16: =IF(A16="","",'CHART DATA'!C5) -> 33579.104 | G16: =IF(A16="","",INDEX('PERIODIC ENGINE'!$K$2:$K$102,MATCH(A16,'PERIODIC ENGINE'!$A$2:$A$102,0))) -> 31500 | H16: =IF(A16="","",E16-INPUTS!$C$8-G16) -> 8493.25 | I16: {=IF(A16="","",IFERROR(INDEX(TerminalValueByYear_Range,ROW()-ROW($I$13)+1),""))} -> 423174.04
A17: =IF(ENGINE!A6="","",ENGINE!A6) -> 4 | B17: =IF(A17="","",ENGINE!B6) -> 26 | C17: =IF(A17="","",ENGINE!D6) -> 9000 | D17: =IF(A17="","",INDEX('PERIODIC ENGINE'!$I$2:$I$102,MATCH(A17,'PERIODIC ENGINE'!$A$2:$A$102,0))) -> 4899.325 | E17: =IF(A17="","",'CHART DATA'!B6) -> 53892.575 | F17: =IF(A17="","",'CHART DATA'!C6) -> 42687.967 | G17: =IF(A17="","",INDEX('PERIODIC ENGINE'!$K$2:$K$102,MATCH(A17,'PERIODIC ENGINE'!$A$2:$A$102,0))) -> 40500 | H17: =IF(A17="","",E17-INPUTS!$C$8-G17) -> 13392.575 | I17: {=IF(A17="","",IFERROR(INDEX(TerminalValueByYear_Range,ROW()-ROW($I$13)+1),""))} -> 407333.3
A18: =IF(ENGINE!A7="","",ENGINE!A7) -> 5 | B18: =IF(A18="","",ENGINE!B7) -> 27 | C18: =IF(A18="","",ENGINE!D7) -> 10000 | D18: =IF(A18="","",INDEX('PERIODIC ENGINE'!$I$2:$I$102,MATCH(A18,'PERIODIC ENGINE'!$A$2:$A$102,0))) -> 6389.2575 | E18: =IF(A18="","",'CHART DATA'!B7) -> 70281.833 | F18: =IF(A18="","",'CHART DATA'!C7) -> 52518.674 | G18: =IF(A18="","",INDEX('PERIODIC ENGINE'!$K$2:$K$102,MATCH(A18,'PERIODIC ENGINE'!$A$2:$A$102,0))) -> 50500 | H18: =IF(A18="","",E18-INPUTS!$C$8-G18) -> 19781.833 | I18: {=IF(A18="","",IFERROR(INDEX(TerminalValueByYear_Range,ROW()-ROW($I$13)+1),""))} -> 411447.78
A19: =IF(ENGINE!A8="","",ENGINE!A8) -> 6 | B19: =IF(A19="","",ENGINE!B8) -> 28 | C19: =IF(A19="","",ENGINE!D8) -> 10500 | D19: =IF(A19="","",INDEX('PERIODIC ENGINE'!$I$2:$I$102,MATCH(A19,'PERIODIC ENGINE'!$A$2:$A$102,0))) -> 8078.1833 | E19: =IF(A19="","",'CHART DATA'!B8) -> 88860.016 | F19: =IF(A19="","",'CHART DATA'!C8) -> 62642.805 | G19: =IF(A19="","",INDEX('PERIODIC ENGINE'!$K$2:$K$102,MATCH(A19,'PERIODIC ENGINE'!$A$2:$A$102,0))) -> 61000 | H19: =IF(A19="","",E19-INPUTS!$C$8-G19) -> 27860.016 | I19: {=IF(A19="","",IFERROR(INDEX(TerminalValueByYear_Range,ROW()-ROW($I$13)+1),""))} -> 392745.61
A20: =IF(ENGINE!A9="","",ENGINE!A9) -> 7 | B20: =IF(A20="","",ENGINE!B9) -> 29 | C20: =IF(A20="","",ENGINE!D9) -> 11000 | D20: =IF(A20="","",INDEX('PERIODIC ENGINE'!$I$2:$I$102,MATCH(A20,'PERIODIC ENGINE'!$A$2:$A$102,0))) -> 9986.0016 | E20: =IF(A20="","",'CHART DATA'!B9) -> 109846.02 | F20: =IF(A20="","",'CHART DATA'!C9) -> 73053.875 | G20: =IF(A20="","",INDEX('PERIODIC ENGINE'!$K$2:$K$102,MATCH(A20,'PERIODIC ENGINE'!$A$2:$A$102,0))) -> 72000 | H20: =IF(A20="","",E20-INPUTS!$C$8-G20) -> 37846.017 | I20: {=IF(A20="","",IFERROR(INDEX(TerminalValueByYear_Range,ROW()-ROW($I$13)+1),""))} -> 374043.43
A21: =IF(ENGINE!A10="","",ENGINE!A10) -> 8 | B21: =IF(A21="","",ENGINE!B10) -> 30 | C21: =IF(A21="","",ENGINE!D10) -> 11500 | D21: =IF(A21="","",INDEX('PERIODIC ENGINE'!$I$2:$I$102,MATCH(A21,'PERIODIC ENGINE'!$A$2:$A$102,0))) -> 12134.602 | E21: =IF(A21="","",'CHART DATA'!B10) -> 133480.62 | F21: =IF(A21="","",'CHART DATA'!C10) -> 83747.392 | G21: =IF(A21="","",INDEX('PERIODIC ENGINE'!$K$2:$K$102,MATCH(A21,'PERIODIC ENGINE'!$A$2:$A$102,0))) -> 83500 | H21: =IF(A21="","",E21-INPUTS!$C$8-G21) -> 49980.619 | I21: {=IF(A21="","",IFERROR(INDEX(TerminalValueByYear_Range,ROW()-ROW($I$13)+1),""))} -> 355495.83
A22: =IF(ENGINE!A11="","",ENGINE!A11) -> 9 | B22: =IF(A22="","",ENGINE!B11) -> 31 | C22: =IF(A22="","",ENGINE!D11) -> 12500 | D22: =IF(A22="","",INDEX('PERIODIC ENGINE'!$I$2:$I$102,MATCH(A22,'PERIODIC ENGINE'!$A$2:$A$102,0))) -> 14598.062 | E22: =IF(A22="","",'CHART DATA'!B11) -> 160578.68 | F22: =IF(A22="","",'CHART DATA'!C11) -> 95046.275 | G22: =IF(A22="","",INDEX('PERIODIC ENGINE'!$K$2:$K$102,MATCH(A22,'PERIODIC ENGINE'!$A$2:$A$102,0))) -> 96000 | H22: =IF(A22="","",E22-INPUTS!$C$8-G22) -> 64578.681 | I22: {=IF(A22="","",IFERROR(INDEX(TerminalValueByYear_Range,ROW()-ROW($I$13)+1),""))} -> 351280.46
A23: =IF(ENGINE!A12="","",ENGINE!A12) -> 10 | B23: =IF(A23="","",ENGINE!B12) -> 32 | C23: =IF(A23="","",ENGINE!D12) -> 13000 | D23: =IF(A23="","",INDEX('PERIODIC ENGINE'!$I$2:$I$102,MATCH(A23,'PERIODIC ENGINE'!$A$2:$A$102,0))) -> 17357.868 | E23: =IF(A23="","",'CHART DATA'!B12) -> 190936.55 | F23: =IF(A23="","",'CHART DATA'!C12) -> 106617.97 | G23: =IF(A23="","",INDEX('PERIODIC ENGINE'!$K$2:$K$102,MATCH(A23,'PERIODIC ENGINE'!$A$2:$A$102,0))) -> 109000 | H23: =IF(A23="","",E23-INPUTS!$C$8-G23) -> 81936.549 | I23: {=IF(A23="","",IFERROR(INDEX(TerminalValueByYear_Range,ROW()-ROW($I$13)+1),""))} -> 332119.71
A24: =IF(ENGINE!A13="","",ENGINE!A13) -> 11 | B24: =IF(A24="","",ENGINE!B13) -> 33 | C24: =IF(A24="","",ENGINE!D13) -> 14000 | D24: =IF(A24="","",INDEX('PERIODIC ENGINE'!$I$2:$I$102,MATCH(A24,'PERIODIC ENGINE'!$A$2:$A$102,0))) -> 20493.655 | E24: =IF(A24="","",'CHART DATA'!B13) -> 225430.2 | F24: =IF(A24="","",'CHART DATA'!C13) -> 118753.82 | G24: =IF(A24="","",INDEX('PERIODIC ENGINE'!$K$2:$K$102,MATCH(A24,'PERIODIC ENGINE'!$A$2:$A$102,0))) -> 123000 | H24: =IF(A24="","",E24-INPUTS!$C$8-G24) -> 102430.2 | I24: {=IF(A24="","",IFERROR(INDEX(TerminalValueByYear_Range,ROW()-ROW($I$13)+1),""))} -> 325152.16
... A113: =IF(ENGINE!A102="","",ENGINE!A102) | B113: =IF(A113="","",ENGINE!B102) | C113: =IF(A113="","",ENGINE!D102) | D113: =IF(A113="","",INDEX('PERIODIC ENGINE'!$I$2:$I$102,MATCH(A113,'PERIODIC ENGINE'!$A$2:$A$102,0))) | E113: =IF(A113="","",'CHART DATA'!B102) | F113: =IF(A113="","",'CHART DATA'!C102) | G113: =IF(A113="","",INDEX('PERIODIC ENGINE'!$K$2:$K$102,MATCH(A113,'PERIODIC ENGINE'!$A$2:$A$102,0))) | H113: =IF(A113="","",E113-INPUTS!$C$8-G113) | I113: {=IF(A113="","",IFERROR(INDEX(TerminalValueByYear_Range,ROW()-ROW($I$13)+1),""))}

Sheet OUTPUT - CASH FLOW
A1: Annual Cash Flow Detail
A2: Salary, federal and state income taxes, payroll taxes, Roth contributions, and disposable take-home pay.
A4: Annual Cash Flow Schedule
A6: Projection Year | B6: Age | C6: Gross Salary | D6: Federal Income Tax | E6: Flat State Income Tax | F6: Payroll Taxes | G6: Total Taxes | H6: Take-Home Pay After Taxes | I6: IRA Contribution | J6: Disposable Take-Home Pay
A7: =IF(ENGINE!A2="","",ENGINE!A2) -> 0 | B7: =IF(ENGINE!A2="","",ENGINE!B2) -> 22 | C7: =IF(ENGINE!A2="","",ENGINE!Y2) -> 70000 | D7: =IF(ENGINE!A2="","",ENGINE!AC2) -> 6570 | E7: =IF(ENGINE!A2="","",ENGINE!AD2) -> 0 | F7: =IF(ENGINE!A2="","",ENGINE!AG2) -> 5355 | G7: =IF(ENGINE!A2="","",ENGINE!AH2) -> 11925 | H7: =IF(ENGINE!A2="","",ENGINE!AI2) -> 58075 | I7: =IF(ENGINE!A2="","",ENGINE!D2) -> 7500 | J7: =IF(ENGINE!A2="","",ENGINE!AI2-ENGINE!D2) -> 50575
A8: =IF(ENGINE!A3="","",ENGINE!A3) -> 1 | B8: =IF(ENGINE!A3="","",ENGINE!B3) -> 23 | C8: =IF(ENGINE!A3="","",ENGINE!Y3) -> 74350 | D8: =IF(ENGINE!A3="","",ENGINE!AC3) -> 7057 | E8: =IF(ENGINE!A3="","",ENGINE!AD3) -> 0 | F8: =IF(ENGINE!A3="","",ENGINE!AG3) -> 5687.775 | G8: =IF(ENGINE!A3="","",ENGINE!AH3) -> 12744.775 | H8: =IF(ENGINE!A3="","",ENGINE!AI3) -> 61605.225 | I8: =IF(ENGINE!A3="","",ENGINE!D3) -> 7500 | J8: =IF(ENGINE!A3="","",ENGINE!AI3-ENGINE!D3) -> 54105.225
A9: =IF(ENGINE!A4="","",ENGINE!A4) -> 2 | B9: =IF(ENGINE!A4="","",ENGINE!B4) -> 24 | C9: =IF(ENGINE!A4="","",ENGINE!Y4) -> 78830.5 | D9: =IF(ENGINE!A4="","",ENGINE!AC4) -> 7545.71 | E9: =IF(ENGINE!A4="","",ENGINE!AD4) -> 0 | F9: =IF(ENGINE!A4="","",ENGINE!AG4) -> 6030.5333 | G9: =IF(ENGINE!A4="","",ENGINE!AH4) -> 13576.243 | H9: =IF(ENGINE!A4="","",ENGINE!AI4) -> 65254.257 | I9: =IF(ENGINE!A4="","",ENGINE!D4) -> 8000 | J9: =IF(ENGINE!A4="","",ENGINE!AI4-ENGINE!D4) -> 57254.257
A10: =IF(ENGINE!A5="","",ENGINE!A5) -> 3 | B10: =IF(ENGINE!A5="","",ENGINE!B5) -> 25 | C10: =IF(ENGINE!A5="","",ENGINE!Y5) -> 83445.415 | D10: =IF(ENGINE!A5="","",ENGINE!AC5) -> 8020.9913 | E10: =IF(ENGINE!A5="","",ENGINE!AD5) -> 0 | F10: =IF(ENGINE!A5="","",ENGINE!AG5) -> 6383.5742 | G10: =IF(ENGINE!A5="","",ENGINE!AH5) -> 14404.566 | H10: =IF(ENGINE!A5="","",ENGINE!AI5) -> 69040.849 | I10: =IF(ENGINE!A5="","",ENGINE!D5) -> 8500 | J10: =IF(ENGINE!A5="","",ENGINE!AI5-ENGINE!D5) -> 60540.849
A11: =IF(ENGINE!A6="","",ENGINE!A6) -> 4 | B11: =IF(ENGINE!A6="","",ENGINE!B6) -> 26 | C11: =IF(ENGINE!A6="","",ENGINE!Y6) -> 103198.78 | D11: =IF(ENGINE!A6="","",ENGINE!AC6) -> 11810.731 | E11: =IF(ENGINE!A6="","",ENGINE!AD6) -> 0 | F11: =IF(ENGINE!A6="","",ENGINE!AG6) -> 7894.7065 | G11: =IF(ENGINE!A6="","",ENGINE!AH6) -> 19705.438 | H11: =IF(ENGINE!A6="","",ENGINE!AI6) -> 83493.34 | I11: =IF(ENGINE!A6="","",ENGINE!D6) -> 9000 | J11: =IF(ENGINE!A6="","",ENGINE!AI6-ENGINE!D6) -> 74493.34
A12: =IF(ENGINE!A7="","",ENGINE!A7) -> 5 | B12: =IF(ENGINE!A7="","",ENGINE!B7) -> 27 | C12: =IF(ENGINE!A7="","",ENGINE!Y7) -> 106294.74 | D12: =IF(ENGINE!A7="","",ENGINE!AC7) -> 7088.3689 | E12: =IF(ENGINE!A7="","",ENGINE!AD7) -> 0 | F12: =IF(ENGINE!A7="","",ENGINE!AG7) -> 8131.5477 | G12: =IF(ENGINE!A7="","",ENGINE!AH7) -> 15219.917 | H12: =IF(ENGINE!A7="","",ENGINE!AI7) -> 91074.824 | I12: =IF(ENGINE!A7="","",ENGINE!D7) -> 10000 | J12: =IF(ENGINE!A7="","",ENGINE!AI7-ENGINE!D7) -> 81074.824
A13: =IF(ENGINE!A8="","",ENGINE!A8) -> 6 | B13: =IF(ENGINE!A8="","",ENGINE!B8) -> 28 | C13: =IF(ENGINE!A8="","",ENGINE!Y8) -> 109483.58 | D13: =IF(ENGINE!A8="","",ENGINE!AC8) -> 7160.03 | E13: =IF(ENGINE!A8="","",ENGINE!AD8) -> 0 | F13: =IF(ENGINE!A8="","",ENGINE!AG8) -> 8375.4941 | G13: =IF(ENGINE!A8="","",ENGINE!AH8) -> 15535.524 | H13: =IF(ENGINE!A8="","",ENGINE!AI8) -> 93948.059 | I13: =IF(ENGINE!A8="","",ENGINE!D8) -> 10500 | J13: =IF(ENGINE!A8="","",ENGINE!AI8-ENGINE!D8) -> 83448.059
A14: =IF(ENGINE!A9="","",ENGINE!A9) -> 7 | B14: =IF(ENGINE!A9="","",ENGINE!B9) -> 29 | C14: =IF(ENGINE!A9="","",ENGINE!Y9) -> 112768.09 | D14: =IF(ENGINE!A9="","",ENGINE!AC9) -> 7235.1709 | E14: =IF(ENGINE!A9="","",ENGINE!AD9) -> 0 | F14: =IF(ENGINE!A9="","",ENGINE!AG9) -> 8626.7589 | G14: =IF(ENGINE!A9="","",ENGINE!AH9) -> 15861.93 | H14: =IF(ENGINE!A9="","",ENGINE!AI9) -> 96906.161 | I14: =IF(ENGINE!A9="","",ENGINE!D9) -> 11000 | J14: =IF(ENGINE!A9="","",ENGINE!AI9-ENGINE!D9) -> 85906.161
A15: =IF(ENGINE!A10="","",ENGINE!A10) -> 8 | B15: =IF(ENGINE!A10="","",ENGINE!B10) -> 30 | C15: =IF(ENGINE!A10="","",ENGINE!Y10) -> 116151.13 | D15: =IF(ENGINE!A10="","",ENGINE!AC10) -> 7297.136 | E15: =IF(ENGINE!A10="","",ENGINE!AD10) -> 0 | F15: =IF(ENGINE!A10="","",ENGINE!AG10) -> 8885.5617 | G15: =IF(ENGINE!A10="","",ENGINE!AH10) -> 16182.698 | H15: =IF(ENGINE!A10="","",ENGINE!AI10) -> 99968.436 | I15: =IF(ENGINE!A10="","",ENGINE!D10) -> 11500 | J15: =IF(ENGINE!A10="","",ENGINE!AI10-ENGINE!D10) -> 88468.436
A16: =IF(ENGINE!A11="","",ENGINE!A11) -> 9 | B16: =IF(ENGINE!A11="","",ENGINE!B11) -> 31 | C16: =IF(ENGINE!A11="","",ENGINE!Y11) -> 119635.67 | D16: =IF(ENGINE!A11="","",ENGINE!AC11) -> 7356.2801 | E16: =IF(ENGINE!A11="","",ENGINE!AD11) -> 0 | F16: =IF(ENGINE!A11="","",ENGINE!AG11) -> 9152.1285 | G16: =IF(ENGINE!A11="","",ENGINE!AH11) -> 16508.409 | H16: =IF(ENGINE!A11="","",ENGINE!AI11) -> 103127.26 | I16: =IF(ENGINE!A11="","",ENGINE!D11) -> 12500 | J16: =IF(ENGINE!A11="","",ENGINE!AI11-ENGINE!D11) -> 90627.259
A17: =IF(ENGINE!A12="","",ENGINE!A12) -> 10 | B17: =IF(ENGINE!A12="","",ENGINE!B12) -> 32 | C17: =IF(ENGINE!A12="","",ENGINE!Y12) -> 123224.74 | D17: =IF(ENGINE!A12="","",ENGINE!AC12) -> 7407.9685 | E17: =IF(ENGINE!A12="","",ENGINE!AD12) -> 0 | F17: =IF(ENGINE!A12="","",ENGINE!AG12) -> 9426.6924 | G17: =IF(ENGINE!A12="","",ENGINE!AH12) -> 16834.661 | H17: =IF(ENGINE!A12="","",ENGINE!AI12) -> 106390.08 | I17: =IF(ENGINE!A12="","",ENGINE!D12) -> 13000 | J17: =IF(ENGINE!A12="","",ENGINE!AI12-ENGINE!D12) -> 93390.076
A18: =IF(ENGINE!A13="","",ENGINE!A13) -> 11 | B18: =IF(ENGINE!A13="","",ENGINE!B13) -> 33 | C18: =IF(ENGINE!A13="","",ENGINE!Y13) -> 126921.48 | D18: =IF(ENGINE!A13="","",ENGINE!AC13) -> 7451.5775 | E18: =IF(ENGINE!A13="","",ENGINE!AD13) -> 0 | F18: =IF(ENGINE!A13="","",ENGINE!AG13) -> 9709.4932 | G18: =IF(ENGINE!A13="","",ENGINE!AH13) -> 17161.071 | H18: =IF(ENGINE!A13="","",ENGINE!AI13) -> 109760.41 | I18: =IF(ENGINE!A13="","",ENGINE!D13) -> 14000 | J18: =IF(ENGINE!A13="","",ENGINE!AI13-ENGINE!D13) -> 95760.409
... A24: =IF(ENGINE!A19="","",ENGINE!A19) -> 17 | B24: =IF(ENGINE!A19="","",ENGINE!B19) -> 39 | C24: =IF(ENGINE!A19="","",ENGINE!Y19) -> 151550.88 | D24: =IF(ENGINE!A19="","",ENGINE!AC19) -> 7517.1061 | E24: =IF(ENGINE!A19="","",ENGINE!AD19) -> 0 | F24: =IF(ENGINE!A19="","",ENGINE!AG19) -> 11593.643 | G24: =IF(ENGINE!A19="","",ENGINE!AH19) -> 19110.749 | H24: =IF(ENGINE!A19="","",ENGINE!AI19) -> 132440.14 | I24: =IF(ENGINE!A19="","",ENGINE!D19) -> 20000 | J24: =IF(ENGINE!A19="","",ENGINE!AI19-ENGINE!D19) -> 112440.14
A25: =IF(ENGINE!A20="","",ENGINE!A20) -> 18 | B25: =IF(ENGINE!A20="","",ENGINE!B20) -> 40 | C25: =IF(ENGINE!A20="","",ENGINE!Y20) -> 156097.41 | D25: =IF(ENGINE!A20="","",ENGINE!AC20) -> 7486.6892 | E25: =IF(ENGINE!A20="","",ENGINE!AD20) -> 0 | F25: =IF(ENGINE!A20="","",ENGINE!AG20) -> 11941.452 | G25: =IF(ENGINE!A20="","",ENGINE!AH20) -> 19428.141 | H25: =IF(ENGINE!A20="","",ENGINE!AI20) -> 136669.27 | I25: =IF(ENGINE!A20="","",ENGINE!D20) -> 21000 | J25: =IF(ENGINE!A20="","",ENGINE!AI20-ENGINE!D20) -> 115669.27 | L25: Cumulative Tax Summary
A26: =IF(ENGINE!A21="","",ENGINE!A21) -> 19 | B26: =IF(ENGINE!A21="","",ENGINE!B21) -> 41 | C26: =IF(ENGINE!A21="","",ENGINE!Y21) -> 160780.33 | D26: =IF(ENGINE!A21="","",ENGINE!AC21) -> 7439.6399 | E26: =IF(ENGINE!A21="","",ENGINE!AD21) -> 0 | F26: =IF(ENGINE!A21="","",ENGINE!AG21) -> 12299.695 | G26: =IF(ENGINE!A21="","",ENGINE!AH21) -> 19739.335 | H26: =IF(ENGINE!A21="","",ENGINE!AI21) -> 141041 | I26: =IF(ENGINE!A21="","",ENGINE!D21) -> 22500 | J26: =IF(ENGINE!A21="","",ENGINE!AI21-ENGINE!D21) -> 118541
A27: =IF(ENGINE!A22="","",ENGINE!A22) -> 20 | B27: =IF(ENGINE!A22="","",ENGINE!B22) -> 42 | C27: =IF(ENGINE!A22="","",ENGINE!Y22) -> 165603.74 | D27: =IF(ENGINE!A22="","",ENGINE!AC22) -> 7381.4491 | E27: =IF(ENGINE!A22="","",ENGINE!AD22) -> 0 | F27: =IF(ENGINE!A22="","",ENGINE!AG22) -> 12668.686 | G27: =IF(ENGINE!A22="","",ENGINE!AH22) -> 20050.135 | H27: =IF(ENGINE!A22="","",ENGINE!AI22) -> 145553.61 | I27: =IF(ENGINE!A22="","",ENGINE!D22) -> 24000 | J27: =IF(ENGINE!A22="","",ENGINE!AI22-ENGINE!D22) -> 121553.61 | L27: Federal income tax | M27: =SUM(ENGINE!AC2:AC102) -> 288998.75
A28: =IF(ENGINE!A23="","",ENGINE!A23) -> 21 | B28: =IF(ENGINE!A23="","",ENGINE!B23) -> 43 | C28: =IF(ENGINE!A23="","",ENGINE!Y23) -> 170571.85 | D28: =IF(ENGINE!A23="","",ENGINE!AC23) -> 7332.1855 | E28: =IF(ENGINE!A23="","",ENGINE!AD23) -> 0 | F28: =IF(ENGINE!A23="","",ENGINE!AG23) -> 13048.747 | G28: =IF(ENGINE!A23="","",ENGINE!AH23) -> 20380.932 | H28: =IF(ENGINE!A23="","",ENGINE!AI23) -> 150190.92 | I28: =IF(ENGINE!A23="","",ENGINE!D23) -> 25000 | J28: =IF(ENGINE!A23="","",ENGINE!AI23-ENGINE!D23) -> 125190.92 | L28: Flat state income tax | M28: =SUM(ENGINE!AD2:AD102) -> 0
A29: =IF(ENGINE!A24="","",ENGINE!A24) -> 22 | B29: =IF(ENGINE!A24="","",ENGINE!B24) -> 44 | C29: =IF(ENGINE!A24="","",ENGINE!Y24) -> 175689.01 | D29: =IF(ENGINE!A24="","",ENGINE!AC24) -> 7318.9011 | E29: =IF(ENGINE!A24="","",ENGINE!AD24) -> 0 | F29: =IF(ENGINE!A24="","",ENGINE!AG24) -> 13440.209 | G29: =IF(ENGINE!A24="","",ENGINE!AH24) -> 20759.11 | H29: =IF(ENGINE!A24="","",ENGINE!AI24) -> 154929.9 | I29: =IF(ENGINE!A24="","",ENGINE!D24) -> 27000 | J29: =IF(ENGINE!A24="","",ENGINE!AI24-ENGINE!D24) -> 127929.9 | L29: Payroll taxes | M29: =SUM(ENGINE!AG2:AG102) -> 622072.03
A30: =IF(ENGINE!A25="","",ENGINE!A25) -> 23 | B30: =IF(ENGINE!A25="","",ENGINE!B25) -> 45 | C30: =IF(ENGINE!A25="","",ENGINE!Y25) -> 180959.68 | D30: =IF(ENGINE!A25="","",ENGINE!AC25) -> 7290.9681 | E30: =IF(ENGINE!A25="","",ENGINE!AD25) -> 0 | F30: =IF(ENGINE!A25="","",ENGINE!AG25) -> 13843.416 | G30: =IF(ENGINE!A25="","",ENGINE!AH25) -> 21134.384 | H30: =IF(ENGINE!A25="","",ENGINE!AI25) -> 159825.3 | I30: =IF(ENGINE!A25="","",ENGINE!D25) -> 28500 | J30: =IF(ENGINE!A25="","",ENGINE!AI25-ENGINE!D25) -> 131325.3 | L30: Total taxes paid | M30: =SUM(ENGINE!AH2:AH102) -> 911070.78
A31: =IF(ENGINE!A26="","",ENGINE!A26) -> 24 | B31: =IF(ENGINE!A26="","",ENGINE!B26) -> 46 | C31: =IF(ENGINE!A26="","",ENGINE!Y26) -> 186388.47 | D31: =IF(ENGINE!A26="","",ENGINE!AC26) -> 7248.8471 | E31: =IF(ENGINE!A26="","",ENGINE!AD26) -> 0 | F31: =IF(ENGINE!A26="","",ENGINE!AG26) -> 14258.718 | G31: =IF(ENGINE!A26="","",ENGINE!AH26) -> 21507.565 | H31: =IF(ENGINE!A26="","",ENGINE!AI26) -> 164880.91 | I31: =IF(ENGINE!A26="","",ENGINE!D26) -> 30000 | J31: =IF(ENGINE!A26="","",ENGINE!AI26-ENGINE!D26) -> 134880.91 | L31: Total gross income earned | M31: =SUM(ENGINE!Y2:Y102) -> 8087943.7
A32: =IF(ENGINE!A27="","",ENGINE!A27) -> 25 | B32: =IF(ENGINE!A27="","",ENGINE!B27) -> 47 | C32: =IF(ENGINE!A27="","",ENGINE!Y27) -> 191980.13 | D32: =IF(ENGINE!A27="","",ENGINE!AC27) -> 7193.0125 | E32: =IF(ENGINE!A27="","",ENGINE!AD27) -> 0 | F32: =IF(ENGINE!A27="","",ENGINE!AG27) -> 14686.48 | G32: =IF(ENGINE!A27="","",ENGINE!AH27) -> 21879.492 | H32: =IF(ENGINE!A27="","",ENGINE!AI27) -> 170100.63 | I32: =IF(ENGINE!A27="","",ENGINE!D27) -> 32000 | J32: =IF(ENGINE!A27="","",ENGINE!AI27-ENGINE!D27) -> 138100.63 | L32: Cumulative Total Tax Rate | M32: =IFERROR(M30/M31,0) -> 0.11264554
A33: =IF(ENGINE!A28="","",ENGINE!A28) -> 26 | B33: =IF(ENGINE!A28="","",ENGINE!B28) -> 48 | C33: =IF(ENGINE!A28="","",ENGINE!Y28) -> 197739.53 | D33: =IF(ENGINE!A28="","",ENGINE!AC28) -> 7118.9529 | E33: =IF(ENGINE!A28="","",ENGINE!AD28) -> 0 | F33: =IF(ENGINE!A28="","",ENGINE!AG28) -> 15127.074 | G33: =IF(ENGINE!A28="","",ENGINE!AH28) -> 22246.027 | H33: =IF(ENGINE!A28="","",ENGINE!AI28) -> 175493.5 | I33: =IF(ENGINE!A28="","",ENGINE!D28) -> 34000 | J33: =IF(ENGINE!A28="","",ENGINE!AI28-ENGINE!D28) -> 141493.5 | L33: Cumulative effective take-home rate | M33: =1-M32 -> 0.88735446
A34: =IF(ENGINE!A29="","",ENGINE!A29) -> 27 | B34: =IF(ENGINE!A29="","",ENGINE!B29) -> 49 | C34: =IF(ENGINE!A29="","",ENGINE!Y29) -> 203671.72 | D34: =IF(ENGINE!A29="","",ENGINE!AC29) -> 7027.1715 | E34: =IF(ENGINE!A29="","",ENGINE!AD29) -> 0 | F34: =IF(ENGINE!A29="","",ENGINE!AG29) -> 15580.886 | G34: =IF(ENGINE!A29="","",ENGINE!AH29) -> 22608.058 | H34: =IF(ENGINE!A29="","",ENGINE!AI29) -> 181063.66 | I34: =IF(ENGINE!A29="","",ENGINE!D29) -> 36000 | J34: =IF(ENGINE!A29="","",ENGINE!AI29-ENGINE!D29) -> 145063.66
A35: =IF(ENGINE!A30="","",ENGINE!A30) -> 28 | B35: =IF(ENGINE!A30="","",ENGINE!B30) -> 50 | C35: =IF(ENGINE!A30="","",ENGINE!Y30) -> 209781.87 | D35: =IF(ENGINE!A30="","",ENGINE!AC30) -> 6918.1867 | E35: =IF(ENGINE!A30="","",ENGINE!AD30) -> 0 | F35: =IF(ENGINE!A30="","",ENGINE!AG30) -> 16048.313 | G35: =IF(ENGINE!A30="","",ENGINE!AH30) -> 22966.499 | H35: =IF(ENGINE!A30="","",ENGINE!AI30) -> 186815.37 | I35: =IF(ENGINE!A30="","",ENGINE!D30) -> 43600 | J35: =IF(ENGINE!A30="","",ENGINE!AI30-ENGINE!D30) -> 143215.37
A36: =IF(ENGINE!A31="","",ENGINE!A31) -> 29 | B36: =IF(ENGINE!A31="","",ENGINE!B31) -> 51 | C36: =IF(ENGINE!A31="","",ENGINE!Y31) -> 216075.32 | D36: =IF(ENGINE!A31="","",ENGINE!AC31) -> 6787.5323 | E36: =IF(ENGINE!A31="","",ENGINE!AD31) -> 0 | F36: =IF(ENGINE!A31="","",ENGINE!AG31) -> 16529.762 | G36: =IF(ENGINE!A31="","",ENGINE!AH31) -> 23317.294 | H36: =IF(ENGINE!A31="","",ENGINE!AI31) -> 192758.03 | I36: =IF(ENGINE!A31="","",ENGINE!D31) -> 46400 | J36: =IF(ENGINE!A31="","",ENGINE!AI31-ENGINE!D31) -> 146358.03
A37: =IF(ENGINE!A32="","",ENGINE!A32) -> 30 | B37: =IF(ENGINE!A32="","",ENGINE!B32) -> 52 | C37: =IF(ENGINE!A32="","",ENGINE!Y32) -> 222557.58 | D37: =IF(ENGINE!A32="","",ENGINE!AC32) -> 6635.7582 | E37: =IF(ENGINE!A32="","",ENGINE!AD32) -> 0 | F37: =IF(ENGINE!A32="","",ENGINE!AG32) -> 17025.655 | G37: =IF(ENGINE!A32="","",ENGINE!AH32) -> 23661.413 | H37: =IF(ENGINE!A32="","",ENGINE!AI32) -> 198896.17 | I37: =IF(ENGINE!A32="","",ENGINE!D32) -> 49300 | J37: =IF(ENGINE!A32="","",ENGINE!AI32-ENGINE!D32) -> 149596.17
A38: =IF(ENGINE!A33="","",ENGINE!A33) -> 31 | B38: =IF(ENGINE!A33="","",ENGINE!B33) -> 53 | C38: =IF(ENGINE!A33="","",ENGINE!Y33) -> 229234.31 | D38: =IF(ENGINE!A33="","",ENGINE!AC33) -> 6458.431 | E38: =IF(ENGINE!A33="","",ENGINE!AD33) -> 0 | F38: =IF(ENGINE!A33="","",ENGINE!AG33) -> 17536.425 | G38: =IF(ENGINE!A33="","",ENGINE!AH33) -> 23994.856 | H38: =IF(ENGINE!A33="","",ENGINE!AI33) -> 205239.45 | I38: =IF(ENGINE!A33="","",ENGINE!D33) -> 52100 | J38: =IF(ENGINE!A33="","",ENGINE!AI33-ENGINE!D33) -> 153139.45
A39: =IF(ENGINE!A34="","",ENGINE!A34) -> 32 | B39: =IF(ENGINE!A34="","",ENGINE!B34) -> 54 | C39: =IF(ENGINE!A34="","",ENGINE!Y34) -> 236111.34 | D39: =IF(ENGINE!A34="","",ENGINE!AC34) -> 6256.1339 | E39: =IF(ENGINE!A34="","",ENGINE!AD34) -> 0 | F39: =IF(ENGINE!A34="","",ENGINE!AG34) -> 18062.517 | G39: =IF(ENGINE!A34="","",ENGINE!AH34) -> 24318.651 | H39: =IF(ENGINE!A34="","",ENGINE!AI34) -> 211792.69 | I39: =IF(ENGINE!A34="","",ENGINE!D34) -> 55000 | J39: =IF(ENGINE!A34="","",ENGINE!AI34-ENGINE!D34) -> 156792.69
A40: =IF(ENGINE!A35="","",ENGINE!A35) -> 33 | B40: =IF(ENGINE!A35="","",ENGINE!B35) -> 55 | C40: =IF(ENGINE!A35="","",ENGINE!Y35) -> 243194.68 | D40: =IF(ENGINE!A35="","",ENGINE!AC35) -> 6024.4679 | E40: =IF(ENGINE!A35="","",ENGINE!AD35) -> 0 | F40: =IF(ENGINE!A35="","",ENGINE!AG35) -> 18604.393 | G40: =IF(ENGINE!A35="","",ENGINE!AH35) -> 24628.861 | H40: =IF(ENGINE!A35="","",ENGINE!AI35) -> 218565.82 | I40: =IF(ENGINE!A35="","",ENGINE!D35) -> 58500 | J40: =IF(ENGINE!A35="","",ENGINE!AI35-ENGINE!D35) -> 160065.82
A41: =IF(ENGINE!A36="","",ENGINE!A36) -> 34 | B41: =IF(ENGINE!A36="","",ENGINE!B36) -> 56 | C41: =IF(ENGINE!A36="","",ENGINE!Y36) -> 250490.52 | D41: =IF(ENGINE!A36="","",ENGINE!AC36) -> 5764.052 | E41: =IF(ENGINE!A36="","",ENGINE!AD36) -> 0 | F41: =IF(ENGINE!A36="","",ENGINE!AG36) -> 19166.939 | G41: =IF(ENGINE!A36="","",ENGINE!AH36) -> 24930.991 | H41: =IF(ENGINE!A36="","",ENGINE!AI36) -> 225559.53 | I41: =IF(ENGINE!A36="","",ENGINE!D36) -> 61900 | J41: =IF(ENGINE!A36="","",ENGINE!AI36-ENGINE!D36) -> 163659.53
A42: =IF(ENGINE!A37="","",ENGINE!A37) -> 35 | B42: =IF(ENGINE!A37="","",ENGINE!B37) -> 57 | C42: =IF(ENGINE!A37="","",ENGINE!Y37) -> 258005.24 | D42: =IF(ENGINE!A37="","",ENGINE!AC37) -> 5470.5235 | E42: =IF(ENGINE!A37="","",ENGINE!AD37) -> 0 | F42: =IF(ENGINE!A37="","",ENGINE!AG37) -> 19809.448 | G42: =IF(ENGINE!A37="","",ENGINE!AH37) -> 25279.971 | H42: =IF(ENGINE!A37="","",ENGINE!AI37) -> 232725.26 | I42: =IF(ENGINE!A37="","",ENGINE!D37) -> 65900 | J42: =IF(ENGINE!A37="","",ENGINE!AI37-ENGINE!D37) -> 166825.26
A43: =IF(ENGINE!A38="","",ENGINE!A38) -> 36 | B43: =IF(ENGINE!A38="","",ENGINE!B38) -> 58 | C43: =IF(ENGINE!A38="","",ENGINE!Y38) -> 265745.39 | D43: =IF(ENGINE!A38="","",ENGINE!AC38) -> 5149.5392 | E43: =IF(ENGINE!A38="","",ENGINE!AD38) -> 0 | F43: =IF(ENGINE!A38="","",ENGINE!AG38) -> 20471.231 | G43: =IF(ENGINE!A38="","",ENGINE!AH38) -> 25620.77 | H43: =IF(ENGINE!A38="","",ENGINE!AI38) -> 240124.62 | I43: =IF(ENGINE!A38="","",ENGINE!D38) -> 69900 | J43: =IF(ENGINE!A38="","",ENGINE!AI38-ENGINE!D38) -> 170224.62
A44: =IF(ENGINE!A39="","",ENGINE!A39) -> 37 | B44: =IF(ENGINE!A39="","",ENGINE!B39) -> 59 | C44: =IF(ENGINE!A39="","",ENGINE!Y39) -> 273717.75 | D44: =IF(ENGINE!A39="","",ENGINE!AC39) -> 4786.7754 | E44: =IF(ENGINE!A39="","",ENGINE!AD39) -> 0 | F44: =IF(ENGINE!A39="","",ENGINE!AG39) -> 21152.868 | G44: =IF(ENGINE!A39="","",ENGINE!AH39) -> 25939.643 | H44: =IF(ENGINE!A39="","",ENGINE!AI39) -> 247778.11 | I44: =IF(ENGINE!A39="","",ENGINE!D39) -> 73900 | J44: =IF(ENGINE!A39="","",ENGINE!AI39-ENGINE!D39) -> 173878.11
A45: =IF(ENGINE!A40="","",ENGINE!A40) -> 38 | B45: =IF(ENGINE!A40="","",ENGINE!B40) -> 60 | C45: =IF(ENGINE!A40="","",ENGINE!Y40) -> 281929.29 | D45: =IF(ENGINE!A40="","",ENGINE!AC40) -> 4387.9287 | E45: =IF(ENGINE!A40="","",ENGINE!AD40) -> 0 | F45: =IF(ENGINE!A40="","",ENGINE!AG40) -> 21854.954 | G45: =IF(ENGINE!A40="","",ENGINE!AH40) -> 26242.883 | H45: =IF(ENGINE!A40="","",ENGINE!AI40) -> 255686.4 | I45: =IF(ENGINE!A40="","",ENGINE!D40) -> 78500 | J45: =IF(ENGINE!A40="","",ENGINE!AI40-ENGINE!D40) -> 177186.4
... A107: =IF(ENGINE!A102="","",ENGINE!A102) | B107: =IF(ENGINE!A102="","",ENGINE!B102) | C107: =IF(ENGINE!A102="","",ENGINE!Y102) | D107: =IF(ENGINE!A102="","",ENGINE!AC102) | E107: =IF(ENGINE!A102="","",ENGINE!AD102) | F107: =IF(ENGINE!A102="","",ENGINE!AG102) | G107: =IF(ENGINE!A102="","",ENGINE!AH102) | H107: =IF(ENGINE!A102="","",ENGINE!AI102) | I107: =IF(ENGINE!A102="","",ENGINE!D102) | J107: =IF(ENGINE!A102="","",ENGINE!AI102-ENGINE!D102)

Sheet MILESTONES
A1: Retirement Balance Milestones
A2: How long until you cross each balance threshold
A4: Milestone | B4: Threshold | C4: Years to Milestone | D4: Age | E4: Nominal Balance | F4: Real Balance | G4: Cumulative Contributions | H4: Cumulative Investment Growth | J4: First Projection Year (Helper)
A5: First $500,000 | B5: 500000 | C5: =IF($J5="Not reached","Not reached",$J5) -> 17 | D5: =IF($J5="Not reached","Not reached",INDEX(ENGINE!$B$2:$B$102,MATCH($J5,ENGINE!$A$2:$A$102,0))) -> 39 | E5: =IF($J5="Not reached","Not reached",INDEX(ENGINE!$L$2:$L$102,MATCH($J5,ENGINE!$A$2:$A$102,0))) -> 543339.83 | F5: =IF($J5="Not reached","Not reached",INDEX(ENGINE!$N$2:$N$102,MATCH($J5,ENGINE!$A$2:$A$102,0))) -> 201777.08 | G5: =IF($J5="Not reached","Not reached",INDEX(ENGINE!$O$2:$O$102,MATCH($J5,ENGINE!$A$2:$A$102,0))) -> 226500 | H5: =IF($J5="Not reached","Not reached",INDEX(ENGINE!$P$2:$P$102,MATCH($J5,ENGINE!$A$2:$A$102,0))) -> 316839.83 | J5: {=IFERROR(INDEX(ENGINE!$A$2:$A$102,_xlfn.AGGREGATE(15,6,(ROW(ENGINE!$L$2:$L$102)-ROW(ENGINE!$L$2)+1)/((ENGINE!$L$2:$L$102>=$B5)*(ENGINE!$A$2:$A$102<>"")),1)),"Not reached")} -> 17
A6: First $1,000,000 | B6: 1000000 | C6: =IF($J6="Not reached","Not reached",$J6) -> 22 | D6: =IF($J6="Not reached","Not reached",INDEX(ENGINE!$B$2:$B$102,MATCH($J6,ENGINE!$A$2:$A$102,0))) -> 44 | E6: =IF($J6="Not reached","Not reached",INDEX(ENGINE!$L$2:$L$102,MATCH($J6,ENGINE!$A$2:$A$102,0))) -> 1033711.2 | F6: =IF($J6="Not reached","Not reached",INDEX(ENGINE!$N$2:$N$102,MATCH($J6,ENGINE!$A$2:$A$102,0))) -> 286860.12 | G6: =IF($J6="Not reached","Not reached",INDEX(ENGINE!$O$2:$O$102,MATCH($J6,ENGINE!$A$2:$A$102,0))) -> 346000 | H6: =IF($J6="Not reached","Not reached",INDEX(ENGINE!$P$2:$P$102,MATCH($J6,ENGINE!$A$2:$A$102,0))) -> 687711.19 | J6: {=IFERROR(INDEX(ENGINE!$A$2:$A$102,_xlfn.AGGREGATE(15,6,(ROW(ENGINE!$L$2:$L$102)-ROW(ENGINE!$L$2)+1)/((ENGINE!$L$2:$L$102>=$B6)*(ENGINE!$A$2:$A$102<>"")),1)),"Not reached")} -> 22
A7: First $2,000,000 | B7: 2000000 | C7: =IF($J7="Not reached","Not reached",$J7) -> 28 | D7: =IF($J7="Not reached","Not reached",INDEX(ENGINE!$B$2:$B$102,MATCH($J7,ENGINE!$A$2:$A$102,0))) -> 50 | E7: =IF($J7="Not reached","Not reached",INDEX(ENGINE!$L$2:$L$102,MATCH($J7,ENGINE!$A$2:$A$102,0))) -> 2113712.4 | F7: =IF($J7="Not reached","Not reached",INDEX(ENGINE!$N$2:$N$102,MATCH($J7,ENGINE!$A$2:$A$102,0))) -> 413505.86 | G7: =IF($J7="Not reached","Not reached",INDEX(ENGINE!$O$2:$O$102,MATCH($J7,ENGINE!$A$2:$A$102,0))) -> 550100 | H7: =IF($J7="Not reached","Not reached",INDEX(ENGINE!$P$2:$P$102,MATCH($J7,ENGINE!$A$2:$A$102,0))) -> 1563612.4 | J7: {=IFERROR(INDEX(ENGINE!$A$2:$A$102,_xlfn.AGGREGATE(15,6,(ROW(ENGINE!$L$2:$L$102)-ROW(ENGINE!$L$2)+1)/((ENGINE!$L$2:$L$102>=$B7)*(ENGINE!$A$2:$A$102<>"")),1)),"Not reached")} -> 28
A8: First $5,000,000 | B8: 5000000 | C8: =IF($J8="Not reached","Not reached",$J8) -> 36 | D8: =IF($J8="Not reached","Not reached",INDEX(ENGINE!$B$2:$B$102,MATCH($J8,ENGINE!$A$2:$A$102,0))) -> 58 | E8: =IF($J8="Not reached","Not reached",INDEX(ENGINE!$L$2:$L$102,MATCH($J8,ENGINE!$A$2:$A$102,0))) -> 5232008.7 | F8: =IF($J8="Not reached","Not reached",INDEX(ENGINE!$N$2:$N$102,MATCH($J8,ENGINE!$A$2:$A$102,0))) -> 642180.78 | G8: =IF($J8="Not reached","Not reached",INDEX(ENGINE!$O$2:$O$102,MATCH($J8,ENGINE!$A$2:$A$102,0))) -> 1009100 | H8: =IF($J8="Not reached","Not reached",INDEX(ENGINE!$P$2:$P$102,MATCH($J8,ENGINE!$A$2:$A$102,0))) -> 4222908.7 | J8: {=IFERROR(INDEX(ENGINE!$A$2:$A$102,_xlfn.AGGREGATE(15,6,(ROW(ENGINE!$L$2:$L$102)-ROW(ENGINE!$L$2)+1)/((ENGINE!$L$2:$L$102>=$B8)*(ENGINE!$A$2:$A$102<>"")),1)),"Not reached")} -> 36
A10: Each milestone uses the first projection year in which the modeled value is greater than or equal to the selected threshold.
A13: Career & Cash-Flow Milestones
A15: Metric | B15: Threshold | C15: Years to Milestone | D15: Age | E15: Value at Milestone | F15: Roth Contribution | G15: Disposable Take-Home Pay | H15: Cumulative Total Tax Rate | J15: First Projection Year (Helper)
A16: Gross Salary | B16: 100000 | C16: =IF($J16="Not reached","Not reached",$J16) -> 4 | D16: =IF($J16="Not reached","Not reached",INDEX(ENGINE!$B$2:$B$102,MATCH($J16,ENGINE!$A$2:$A$102,0))) -> 26 | E16: =IF($J16="Not reached","Not reached",INDEX(ENGINE!$Y$2:$Y$102,MATCH($J16,ENGINE!$A$2:$A$102,0))) -> 103198.78 | F16: =IF($J16="Not reached","Not reached",INDEX(ENGINE!$D$2:$D$102,MATCH($J16,ENGINE!$A$2:$A$102,0))) -> 9000 | G16: =IF($J16="Not reached","Not reached",INDEX(ENGINE!$AI$2:$AI$102,MATCH($J16,ENGINE!$A$2:$A$102,0))-INDEX(ENGINE!$D$2:$D$102,MATCH($J16,ENGINE!$A$2:$A$102,0))) -> 74493.34 | H16: =IF($J16="Not reached","Not reached",IFERROR(SUMIFS(ENGINE!$AH$2:$AH$102,ENGINE!$A$2:$A$102,"<="&$J16)/SUMIFS(ENGINE!$Y$2:$Y$102,ENGINE!$A$2:$A$102,"<="&$J16),0)) -> 0.17655359 | J16: {=IFERROR(INDEX(ENGINE!$A$2:$A$102,_xlfn.AGGREGATE(15,6,(ROW(ENGINE!$A$2:$A$102)-ROW(ENGINE!$A$2)+1)/((ENGINE!$Y$2:$Y$102>=$B16)*(ENGINE!$A$2:$A$102<>"")),1)),"Not reached")} -> 4
A17: Gross Salary | B17: 250000 | C17: =IF($J17="Not reached","Not reached",$J17) -> 34 | D17: =IF($J17="Not reached","Not reached",INDEX(ENGINE!$B$2:$B$102,MATCH($J17,ENGINE!$A$2:$A$102,0))) -> 56 | E17: =IF($J17="Not reached","Not reached",INDEX(ENGINE!$Y$2:$Y$102,MATCH($J17,ENGINE!$A$2:$A$102,0))) -> 250490.52 | F17: =IF($J17="Not reached","Not reached",INDEX(ENGINE!$D$2:$D$102,MATCH($J17,ENGINE!$A$2:$A$102,0))) -> 61900 | G17: =IF($J17="Not reached","Not reached",INDEX(ENGINE!$AI$2:$AI$102,MATCH($J17,ENGINE!$A$2:$A$102,0))-INDEX(ENGINE!$D$2:$D$102,MATCH($J17,ENGINE!$A$2:$A$102,0))) -> 163659.53 | H17: =IF($J17="Not reached","Not reached",IFERROR(SUMIFS(ENGINE!$AH$2:$AH$102,ENGINE!$A$2:$A$102,"<="&$J17)/SUMIFS(ENGINE!$Y$2:$Y$102,ENGINE!$A$2:$A$102,"<="&$J17),0)) -> 0.12311337 | J17: {=IFERROR(INDEX(ENGINE!$A$2:$A$102,_xlfn.AGGREGATE(15,6,(ROW(ENGINE!$A$2:$A$102)-ROW(ENGINE!$A$2)+1)/((ENGINE!$Y$2:$Y$102>=$B17)*(ENGINE!$A$2:$A$102<>"")),1)),"Not reached")} -> 34
A18: Disposable Take-Home Pay | B18: 100000 | C18: =IF($J18="Not reached","Not reached",$J18) -> 13 | D18: =IF($J18="Not reached","Not reached",INDEX(ENGINE!$B$2:$B$102,MATCH($J18,ENGINE!$A$2:$A$102,0))) -> 35 | E18: =IF($J18="Not reached","Not reached",INDEX(ENGINE!$AI$2:$AI$102,MATCH($J18,ENGINE!$A$2:$A$102,0))-INDEX(ENGINE!$D$2:$D$102,MATCH($J18,ENGINE!$A$2:$A$102,0))) -> 101331.08 | F18: =IF($J18="Not reached","Not reached",INDEX(ENGINE!$D$2:$D$102,MATCH($J18,ENGINE!$A$2:$A$102,0))) -> 15500 | G18: =IF($J18="Not reached","Not reached",$E18) -> 101331.08 | H18: =IF($J18="Not reached","Not reached",IFERROR(SUMIFS(ENGINE!$AH$2:$AH$102,ENGINE!$A$2:$A$102,"<="&$J18)/SUMIFS(ENGINE!$Y$2:$Y$102,ENGINE!$A$2:$A$102,"<="&$J18),0)) -> 0.14833373 | J18: {=IFERROR(INDEX(ENGINE!$A$2:$A$102,_xlfn.AGGREGATE(15,6,(ROW(ENGINE!$A$2:$A$102)-ROW(ENGINE!$A$2)+1)/(((ENGINE!$AI$2:$AI$102-ENGINE!$D$2:$D$102)>=$B18)*(ENGINE!$A$2:$A$102<>"")),1)),"Not reached")} -> 13
A19: Disposable Take-Home Pay | B19: 250000 | C19: =IF($J19="Not reached","Not reached",$J19) -> Not reached | D19: =IF($J19="Not reached","Not reached",INDEX(ENGINE!$B$2:$B$102,MATCH($J19,ENGINE!$A$2:$A$102,0))) -> Not reached | E19: =IF($J19="Not reached","Not reached",INDEX(ENGINE!$AI$2:$AI$102,MATCH($J19,ENGINE!$A$2:$A$102,0))-INDEX(ENGINE!$D$2:$D$102,MATCH($J19,ENGINE!$A$2:$A$102,0))) -> Not reached | F19: =IF($J19="Not reached","Not reached",INDEX(ENGINE!$D$2:$D$102,MATCH($J19,ENGINE!$A$2:$A$102,0))) -> Not reached | G19: =IF($J19="Not reached","Not reached",$E19) -> Not reached | H19: =IF($J19="Not reached","Not reached",IFERROR(SUMIFS(ENGINE!$AH$2:$AH$102,ENGINE!$A$2:$A$102,"<="&$J19)/SUMIFS(ENGINE!$Y$2:$Y$102,ENGINE!$A$2:$A$102,"<="&$J19),0)) -> Not reached | J19: {=IFERROR(INDEX(ENGINE!$A$2:$A$102,_xlfn.AGGREGATE(15,6,(ROW(ENGINE!$A$2:$A$102)-ROW(ENGINE!$A$2)+1)/(((ENGINE!$AI$2:$AI$102-ENGINE!$D$2:$D$102)>=$B19)*(ENGINE!$A$2:$A$102<>"")),1)),"Not reached")} -> Not reached

Sheet WHAT-IF SCENARIOS
A1: WHAT-IF SCENARIOS
A2: Isolated shadow calculations for exploring alternate assumptions. None of these inputs affect ENGINE, PERIODIC ENGINE, or any existing chart or output.
A4: 1. REQUIRED RETURN SOLVER
A5: This section is fully isolated from the rest of the model. It does not read or change your main return-rate assumption, and running Goal Seek here will never affect any chart or output elsewhere in the workbook.
A6: Target retirement balance ($) | B6: 2000000 | C6: What you want your balance to reach by retirement
A7: Target in nominal or real (today's) dollars? | B7: Nominal | C7: Real = today's purchasing power; Nominal = actual future dollars
A8: Solver Return Rate (%), isolated: does not affect the rest of the model | B8: 0.1 | C8: Goal Seek changes THIS cell only. It defaults to your main return rate.
A10: Shadow Terminal Balance (at Solver Rate) | B10: =SUM('PERIODIC ENGINE'!$U$2:$U$102)+INPUTS!$C$8*(1+B8)^(Horizon_Rows*'PERIODIC ENGINE'!$S$3) -> 11101633 | C10: Total balance the shadow schedule reaches at the Solver Rate
A11: Nominal Target (converted from Real if needed) | B11: =IF(B7="Real",B6*(1+INPUTS!$C$11)^Horizon_Years,B6) -> 2000000 | C11: What Shadow Terminal Balance must equal, in future dollars
A12: Difference (Shadow − Target) | B12: =B10-B11 -> 9101633.3 | C12: ~$0 after Goal Seek converges; nonzero before it's run
A13: Required Annual Return (Solver Return Rate, once solved) | B13: =B8 -> 0.1 | C13: This is the answer, once Goal Seek has been run
A15: HOW TO SOLVE
A16: Data, then What-If Analysis, then Goal Seek. Set cell: B10. To value: type the number currently shown in B11 (or 0 if using the Difference cell as "Set cell" instead; see below). By changing cell: B8. Click OK.
A17: Tip: for a cleaner solve, you can instead set "Set cell" to B12 (Difference) and "To value" to 0. It's mathematically identical, but lets you watch the gap close to exactly zero.
A20: 2. RETURN-RATE SCENARIOS (BEAR / BASE / BULL)
A21: Bear and Bull are relative to your actual base-case return rate, not fixed values, so they stay meaningful no matter what your real assumption is.
A22: Bear/Bull spread (± percentage points) | B22: 3 | C22: Applied above and below your base return rate
A24: Scenario | B24: Return Rate | C24: Final Nominal Balance | D24: Final Real Balance
A25: Bear (Base − Spread, floored at 0%) | B25: =MAX(0,INPUTS!$C$10-$B$22/100) -> 0.07 | C25: =SUM('PERIODIC ENGINE'!$W$2:$W$102)+INPUTS!$C$8*(1+B25)^(Horizon_Rows*'PERIODIC ENGINE'!$S$3) -> 5498285.3 | D25: =C25/(1+INPUTS!$C$11)^Horizon_Years -> 448822.96
A26: Base (live from main model) | B26: =INPUTS!$C$10 -> 0.1 | C26: =SUM('PERIODIC ENGINE'!$Q$2:$Q$102)+INPUTS!$C$8*(1+B26)^(Horizon_Rows*'PERIODIC ENGINE'!$S$3) -> 11101633 | D26: =C26/(1+INPUTS!$C$11)^Horizon_Years -> 906222.15
A27: Bull (Base + Spread) | B27: =INPUTS!$C$10+$B$22/100 -> 0.13 | C27: =SUM('PERIODIC ENGINE'!$Y$2:$Y$102)+INPUTS!$C$8*(1+B27)^(Horizon_Rows*'PERIODIC ENGINE'!$S$3) -> 24513236 | D27: =C27/(1+INPUTS!$C$11)^Horizon_Years -> 2001006.2
A30: 3. INFLATION SWING
A31: Same relative-offset principle: Low/High inflation move with your actual base inflation assumption, not fixed values. Nominal balance never changes here; only its real-dollar conversion does.
A32: Inflation swing (± percentage points) | B32: 1.5 | C32: Applied above and below your base inflation rate
A34: Inflation Scenario | B34: Rate | C34: Real Balance at Retirement
A35: Low (Base − Swing, floored at 0%) | B35: =MAX(0,INPUTS!$C$11-$B$32/100) -> 0.045 | C35: =$C$26/(1+B35)^Horizon_Years -> 1672578
A36: Base (live from main model) | B36: =INPUTS!$C$11 -> 0.06 | C36: =$C$26/(1+B36)^Horizon_Years -> 906222.15
A37: High (Base + Swing) | B37: =INPUTS!$C$11+$B$32/100 -> 0.075 | C37: =$C$26/(1+B37)^Horizon_Years -> 495248.21
A40: 4. CONTRIBUTION GAP / CAREER BREAK
A41: Gap start year (Projection Year, 0 = first modeled year) | B41: 0
A42: Gap length (years) | B42: 0
A44: Scenario | B44: Final Nominal Balance | C44: Difference vs. Base Case
A45: No gap (base case) | B45: =$C$26 -> 11101633 | C45: N/A
A46: With gap | B46: =SUM('PERIODIC ENGINE'!$AA$2:$AA$102)+INPUTS!$C$8*(1+INPUTS!$C$10)^(Horizon_Rows*'PERIODIC ENGINE'!$S$3) -> 11101633 | C46: =B46-B45 -> 0
A48: 5. EARLY STOP CONTRIBUTING
A49: Stop contributing after age (last contribution happens at this age) | B49: 45 | C49: Contributions stop for good after this age; balance keeps compounding to retirement
A51: Scenario | B51: Final Nominal Balance | C51: Difference vs. Base Case
A52: Contribute full career (base case) | B52: =$C$26 -> 11101633 | C52: N/A
A53: Stop early | B53: =SUM('PERIODIC ENGINE'!$AC$2:$AC$102)+INPUTS!$C$8*(1+INPUTS!$C$10)^(Horizon_Rows*'PERIODIC ENGINE'!$S$3) -> 7860628.3 | C53: =B53-B52 -> -3241005

Sheet CONSTANTS & REFERENCES
A1: CONSTANTS & REFERENCES: 2026 BASE YEAR | F1: Model-linked constants remain in fixed cells; research-only sections are labeled below.
A2: 2026 FEDERAL INCOME TAX BRACKETS & STANDARD DEDUCTIONS
A3: Single / Married Filing Separately | F3: Married Filing Jointly / Qualifying Surviving Spouse | K3: Head of Household
A4: Marginal rate | B4: Taxable income from | C4: Taxable income to | D4: Full-bracket tax | F4: Marginal rate | G4: Taxable income from | H4: Taxable income to | I4: Full-bracket tax | K4: Marginal rate | L4: Taxable income from | M4: Taxable income to | N4: Full-bracket tax
A5: 0.1 | B5: 0 | C5: 12400 | D5: =A5*(C5-B5) -> 1240 | F5: 0.1 | G5: 0 | H5: 24800 | I5: =F5*(H5) -> 2480 | K5: 0.1 | L5: 0 | M5: 17700 | N5: =K5*(M5) -> 1770
A6: 0.12 | B6: =C5+1 -> 12401 | C6: 50400 | D6: =A6*(C6-B6+1) -> 4560 | F6: 0.12 | G6: =H5+1 -> 24801 | H6: 100800 | I6: =F6*(H6-G6) -> 9119.88 | K6: 0.12 | L6: =M5+1 -> 17701 | M6: 67450 | N6: =K6*(M6-L6) -> 5969.88
A7: 0.22 | B7: =C6+1 -> 50401 | C7: 105700 | D7: =A7*(C7-B7+1) -> 12166 | F7: 0.22 | G7: =H6+1 -> 100801 | H7: 211400 | I7: =F7*(H7-G7) -> 24331.78 | K7: 0.22 | L7: =M6+1 -> 67451 | M7: 105700 | N7: =K7*(M7-L7) -> 8414.78
A8: 0.24 | B8: =C7+1 -> 105701 | C8: 201775 | D8: =A8*(C8-B8+1) -> 23058 | F8: 0.24 | G8: =H7+1 -> 211401 | H8: 403550 | I8: =F8*(H8-G8) -> 46115.76 | K8: 0.24 | L8: =M7+1 -> 105701 | M8: 201700 | N8: =K8*(M8-L8) -> 23039.76
A9: 0.32 | B9: =C8+1 -> 201776 | C9: 256225 | D9: =A9*(C9-B9+1) -> 17424 | F9: 0.32 | G9: =H8+1 -> 403551 | H9: 512450 | I9: =F9*(H9-G9) -> 34847.68 | K9: 0.32 | L9: =M8+1 -> 201701 | M9: 256200 | N9: =K9*(M9-L9) -> 17439.68
A10: 0.35 | B10: =C9+1 -> 256226 | C10: 646600 | D10: =A10*(C10-B10+1) -> 136631.25 | F10: 0.35 | G10: =H9+1 -> 512451 | H10: 768600 | I10: =F10*(H10-G10) -> 89652.15 | K10: 0.35 | L10: =M9+1 -> 256201 | M10: 640600 | N10: =K10*(M10-L10) -> 134539.65
A11: 0.37 | B11: =C10 -> 646600 | F11: 0.37 | G11: =H10 -> 768600 | K11: 0.37 | L11: =M10 -> 640600
A12: 2026 standard deduction | F12: 2026 standard deduction | K12: 2026 standard deduction
A13: Single / Separately | B13: 16100 | C13: Single_Separately_STD_Deduction | F13: Jointly / Spouse | G13: 32200 | K13: Head of Household | L13: 24150
A15: Supporting indexing and rounding constants | B15: Value | C15: Notes
A16: Bracket rounding increment (Single / Joint / HoH) | B16: 50 | C16: Bracket_Round_Standard: statutory rounding for Single, Married Filing Jointly, and Head of Household (IRC §1(f)(6)/(7))
A17: Bracket rounding increment (Married Filing Separately) | B17: 25 | C17: Bracket_Round_MFS: MFS brackets round to the nearest $25, not $50, per IRC §1(f)(7)/(8)
A18: Standard deduction rounding increment | B18: 50 | C18: Supporting reference for deduction rounding
A20: 2026 PAYROLL TAX RATES & THRESHOLDS
A21: Tax component | B21: Employee rate | C21: Wage base / threshold | D21: Model note
A22: OASDI | B22: 0.062 | C22: 184500 | D22: Gross Income (capped)
A23: Note: This model escalates the OASDI wage base using CPI as a simplified illustrative proxy (see 'Modeled OASDI Wage Base' column on ENGINE); row 21 is the 2026 base year value only. This is NOT how the SSA actually indexes the wage base: the real annual adjustment is tied to the National Average Wage Index (AWI), not CPI. Treat the modeled figures as a rough approximation, not an official forecast.
A24: Medicare | B24: 0.0145 | C24: No Limit | D24: All Gross Income
A25: Additional Medicare Tax (Single) | B25: 0.009 | C25: 200000 | D25: GI over threshold (Single)
A26: Additional Medicare Tax (Joint) | B26: 0.009 | C26: 250000 | D26: GI over threshold (Jointly)
A27: Additional Medicare Tax (Married Filing Separately) | B27: 0.009 | C27: 125000 | D27: GI over threshold (Married Filing Separately)
A28: Additional Medicare Tax (Head of Household) | B28: 0.009 | C28: 200000 | D28: GI over threshold (Head of Household)
A29: 2026 IRA LIMITS & ROUNDING CONSTANTS
A30: Reference item | B30: 2026 value | C30: Purpose
A31: Regular IRA contribution limit | B31: 7500 | C31: 2026 published regular IRA limit, per IRS Notice 2025-67
A32: Age-50+ catch-up limit | B32: 1100 | C32: 2026 age-50+ catch-up amount
A33: Regular limit rounding increment | B33: 500 | C33: Regular IRA limit statutory rounding increment
A34: Catch-up rounding increment | B34: 100 | C34: Catch-up statutory rounding increment
A35: RESEARCH NOTES: NOT CONNECTED TO CURRENT ENGINE
A36: 2026 FEDERAL TAX HEADLINE REFERENCES
A37: Single 10% bracket upper bound | B37: 12400 | C37: 10% applies to taxable income from $0 through $12,400.
A38: Single standard deduction | B38: 16100 | C38: Taxable income generally starts after deductions.
A39: Approx. gross income before 12% begins | B39: =B37+B38 -> 28500 | C39: Illustrative gross threshold = bracket ceiling + standard deduction.
A41: 2026 IRA MAGI RESEARCH: NOT MODELED | D41: Roth reduction mechanics
A42: Filing status | B42: Lower bound | C42: Upper bound | D42: Phase-out percentage | E42: Phase-out fraction: (MAGI - Lower) / (Upper - Lower)
A43: Single / Head of Household | B43: 153000 | C43: 168000 | D43: Preliminary limit | E43: Max contribution × (1 - phase-out percentage)
A44: Married Filing Jointly | B44: 242000 | C44: 252000 | D44: Rounding | E44: Round UP to next $10
A45: Married Filing Separately* | B45: 0 | C45: 10000 | D45: Minimum positive limit | E45: $200 if result is above $0 but below $200
A47: IRA CONTRIBUTION-LIMIT INDEXING RESEARCH | D47: MODEL POLICY & IMPLEMENTATION NOTES
A48: Statutory regular-limit base | B48: 5000 | C48: IRC §219 base amount; inflation comparison uses calendar year 2007. | D48: Historical/current years | E48: Use IRS-published tables as authoritative inputs.
A49: Regular-limit rounding step | B49: =B33 -> 500 | C49: After indexing, any amount not divisible by $500 is rounded DOWN. | D49: Future projection years | E49: Estimate with assumed inflation, clearly label as projected.
A50: Minimum indexed multiplier for current limit | B50: =B31/B48 -> 1.5 | C50: $7,500 / $5,000 = 1.500 minimum multiplier. | D50: Tax brackets | E50: Do not compound the prior-year rounded bracket for statutory reproduction.
A51: Minimum indexed multiplier for next $8,000 limit | B51: =(B31+B49)/B48 -> 1.6 | C51: $8,000 / $5,000 = 1.600 minimum multiplier. | D51: IRA limits | E51: Apply indexed statutory base, then required $500/$100 rounding.
A52: 2026 inferred unrounded regular-limit band | B52: $7,500 ≤ indexed amount < $8,000 | C52: Exact intermediate amount is not stated in IRS Notice 2025-67.
A53: Example: unrounded $7,560 | B53: =_xlfn.FLOOR.MATH(7560,500) -> 7500 | C53: Becomes $7,500.
A54: Example: unrounded $7,999 | B54: =_xlfn.FLOOR.MATH(7999,500) -> 7500 | C54: Still becomes $7,500.
A55: Example: unrounded $8,000 | B55: =_xlfn.FLOOR.MATH(8000,500) -> 8000 | C55: Becomes $8,000 immediately.
A56: Excel statutory rounding formula | B56: =FLOOR.MATH(Unrounded_Indexed_Limit,500) | C56: Do not use normal ROUND or round to nearest.
A58: SOURCE LOG & MODEL SCOPE
A59: Source Document | B59: Year | C59: Source URL | D59: Research Note
A60: IRS Notice 2025-67 | B60: 2026 | C60: https://www.irs.gov/pub/irs-drop/n-25-67.pdf | D60: 2026 federal brackets, standard deductions, and retirement-plan references used by the model. Verify the cited IRS source before changing the tax year.
A61: Internal model assumptions | B61: User-controlled | C61: N/A | D61: The current engine applies the 2026 federal bracket tables, standard deductions, payroll assumptions, and user-controlled illustrative flat state tax. MAGI and tax credits are not modeled.

Sheet ENGINE
A1: Year | B1: Age | C1: Beginning Balance | D1: Actual Contribution Applied | E1: Contribution Method | F1: Illustrative Unrounded Regular IRA Index | G1: Modeled Regular IRA Limit | H1: Illustrative Unrounded Catch-Up Index | I1: Modeled Catch-Up Limit | J1: Total Maximum Modeled Contribution | K1: Investment Growth | L1: Ending Balance | M1: Inflation Index | N1: Ending Balance (Real $) | O1: Cumulative Contributions | P1: Cumulative Investment Growth | S1: Age | T1: Nominal IRA Balance | U1: Real IRA Balance | V1: FV of Contribution at Retirement | W1: Illustrative IRA Indexing Assumptions | Y1: Gross Salary | Z1: Cumulative Exams Modeled (Capped) | AA1: Modeled Standard Deduction | AB1: Federal Taxable Income | AC1: Federal Income Tax | AD1: Illustrative Flat State Income Tax | AE1: Social Security Tax | AF1: Medicare Tax | AG1: Total Payroll Taxes | AH1: Total Taxes | AI1: Take-Home Income | AJ1: Tax Calculation Check | AK1: Filing Status Used | AL1: Cumulative C-CPI Index | AM1: Unrounded Standard Deduction | AN1: Modeled Standard Deduction | AO1: Unrounded Tax Threshold 1 | AP1: Modeled Tax Threshold 1 | AQ1: Unrounded Tax Threshold 2 | AR1: Modeled Tax Threshold 2 | AS1: Unrounded Tax Threshold 3 | AT1: Modeled Tax Threshold 3 | AU1: Unrounded Tax Threshold 4 | AV1: Modeled Tax Threshold 4 | AW1: Unrounded Tax Threshold 5 | AX1: Modeled Tax Threshold 5 | AY1: Unrounded Tax Threshold 6 | AZ1: Modeled Tax Threshold 6 | BA1: Tax Assumption Status | BB1: Unrounded OASDI Wage Base | BC1: Modeled OASDI Wage Base
A2: 0 | B2: =INPUTS!$C$6 -> 22 | C2: =INPUTS!$C$8 -> 0 | D2: =IF(A2="","",IF(A2<INPUTS!$C$13,0,J2)) -> 7500 | E2: =IF(A2="","",IF(D2=0,"—",IF(Y2<IF(AK2="Married Filing Jointly",'CONSTANTS & REFERENCES'!$B$44,IF(AK2="Married Filing Separately",'CONSTANTS & REFERENCES'!$B$45,'CONSTANTS & REFERENCES'!$B$43)),"Direct","Backdoor"))) -> Direct | F2: =IF(A2="","",$X$2*(1+$X$3)^A2) -> 7500 | G2: =IF(F2="","",_xlfn.FLOOR.MATH(F2,500)) -> 7500 | H2: =IF(A2="","",$X$4*(1+$X$3)^A2) -> 1100 | I2: =IF(H2="","",_xlfn.FLOOR.MATH(H2,100)) -> 1100 | J2: =IF(A2="","",G2+IF(B2>=50,I2,0)) -> 7500 | K2: =IF(A2="","",IF(INPUTS!$C$12="Beginning",(C2+D2)*INPUTS!$C$10,C2*INPUTS!$C$10)) -> 750 | L2: =IF(A2="","",IF(INPUTS!$C$12="Beginning",(C2+D2)*(1+INPUTS!$C$10),C2*(1+INPUTS!$C$10)+D2)) -> 8250 | M2: 1 | N2: =L2/M2 -> 8250 | O2: =IF(A2="","",D2) -> 7500 | P2: =IF(A2="","",L2-INPUTS!$C$8-O2) -> 750 | S2: =B2 -> 22 | T2: =L2 -> 8250 | U2: =N2 -> 8250 | V2: =IF(A2="","",FV(INPUTS!$C$10,INPUTS!$C$7-INPUTS!$C$6-A2+IF(INPUTS!$C$12="Beginning",1,0),0,-D2,0)) -> 496980.57 | W2: Starting Modeled Regular IRA Limit | X2: 7500 | Y2: =IF(A2="","",IF(INPUTS!$C$17="Yes",MIN(INPUTS!$C$16,INPUTS!$C$18),INPUTS!$C$16)) -> 70000 | Z2: =IF(A2="","",IF(AND(INPUTS!$C$27="Yes",INPUTS!$C$28<>"FSA / FCAS",ISNUMBER(INPUTS!$C$37)),MIN(A2*INPUTS!$C$37,INPUTS!$C$30),0)) -> 0 | AA2: =IF(A2="","",AN2) -> 16100 | AB2: =IF(OR(A2="",AA2=""),"",MAX(0,Y2-AA2)) -> 53900 | AC2: =IF(A2="","",MIN(AB2,AP2)*'CONSTANTS & REFERENCES'!$A$5+MAX(MIN(AB2,AR2)-AP2,0)*'CONSTANTS & REFERENCES'!$A$6+MAX(MIN(AB2,AT2)-AR2,0)*'CONSTANTS & REFERENCES'!$A$7+MAX(MIN(AB2,AV2)-AT2,0)*'CONSTANTS & REFERENCES'!$A$8+MAX(MIN(AB2,AX2)-AV2,0)*'CONSTANTS & REFERENCES'!$A$9+MAX(MIN(AB2,AZ2)-AX2,0)*'CONSTANTS & REFERENCES'!$A$10+MAX(AB2-AZ2,0)*'CONSTANTS & REFERENCES'!$A$11) -> 6570 | AD2: =IF(AB2="","",IF(INPUTS!$C$20="Yes",AB2*INPUTS!$C$21,0)) -> 0 | AE2: =IF(Y2="","",MIN(Y2,BC2)*'CONSTANTS & REFERENCES'!$B$22) -> 4340 | AF2: =IF(Y2="","",Y2*'CONSTANTS & REFERENCES'!$B$24+MAX(0,Y2-IF(AK2="Married Filing Jointly",'CONSTANTS & REFERENCES'!$C$26,IF(AK2="Married Filing Separately",'CONSTANTS & REFERENCES'!$C$27,IF(AK2="Head of Household",'CONSTANTS & REFERENCES'!$C$28,'CONSTANTS & REFERENCES'!$C$25))))*'CONSTANTS & REFERENCES'!$B$25) -> 1015 | AG2: =IF(Y2="","",AE2+AF2) -> 5355 | AH2: =IF(OR(AC2="",AG2=""),"",AC2+AD2+AG2) -> 11925 | AI2: =IF(AH2="","",Y2-AH2) -> 58075 | AJ2: =IF(AI2="","",Y2-AH2-AI2) -> 0 | AK2: =IF(A2="","",IF(AND(INPUTS!$C$43="Yes",A2>=INPUTS!$C$45),INPUTS!$C$44,INPUTS!$C$19)) -> Single | AL2: =IF(A2="","",(1+$X$6)^A2) -> 1 | AM2: =IF(A2="","",(IF(OR(AK2="Single",AK2="Married Filing Separately"),'CONSTANTS & REFERENCES'!$B$13,IF(AK2="Married Filing Jointly",'CONSTANTS & REFERENCES'!$G$13,IF(AK2="Head of Household",'CONSTANTS & REFERENCES'!$L$13,""))))*AL2) -> 16100 | AN2: =IF(AM2="","",IF(A2=0,IF(OR(AK2="Single",AK2="Married Filing Separately"),'CONSTANTS & REFERENCES'!$B$13,IF(AK2="Married Filing Jointly",'CONSTANTS & REFERENCES'!$G$13,IF(AK2="Head of Household",'CONSTANTS & REFERENCES'!$L$13,""))),_xlfn.FLOOR.MATH(AM2,IF(AK2="Married Filing Separately",Bracket_Round_MFS,Bracket_Round_Standard)))) -> 16100 | AO2: =IF(A2="","",(IF(OR(AK2="Single",AK2="Married Filing Separately"),'CONSTANTS & REFERENCES'!$C$5,IF(AK2="Married Filing Jointly",'CONSTANTS & REFERENCES'!$H$5,IF(AK2="Head of Household",'CONSTANTS & REFERENCES'!$M$5,""))))*AL2) -> 12400 | AP2: =IF(AO2="","",IF(A2=0,IF(OR(AK2="Single",AK2="Married Filing Separately"),'CONSTANTS & REFERENCES'!$C$5,IF(AK2="Married Filing Jointly",'CONSTANTS & REFERENCES'!$H$5,IF(AK2="Head of Household",'CONSTANTS & REFERENCES'!$M$5,""))),_xlfn.FLOOR.MATH(AO2,IF(AK2="Married Filing Separately",Bracket_Round_MFS,Bracket_Round_Standard)))) -> 12400 | AQ2: =IF(A2="","",(IF(OR(AK2="Single",AK2="Married Filing Separately"),'CONSTANTS & REFERENCES'!$C$6,IF(AK2="Married Filing Jointly",'CONSTANTS & REFERENCES'!$H$6,IF(AK2="Head of Household",'CONSTANTS & REFERENCES'!$M$6,""))))*AL2) -> 50400 | AR2: =IF(AQ2="","",IF(A2=0,IF(OR(AK2="Single",AK2="Married Filing Separately"),'CONSTANTS & REFERENCES'!$C$6,IF(AK2="Married Filing Jointly",'CONSTANTS & REFERENCES'!$H$6,IF(AK2="Head of Household",'CONSTANTS & REFERENCES'!$M$6,""))),_xlfn.FLOOR.MATH(AQ2,IF(AK2="Married Filing Separately",Bracket_Round_MFS,Bracket_Round_Standard)))) -> 50400 | AS2: =IF(A2="","",(IF(OR(AK2="Single",AK2="Married Filing Separately"),'CONSTANTS & REFERENCES'!$C$7,IF(AK2="Married Filing Jointly",'CONSTANTS & REFERENCES'!$H$7,IF(AK2="Head of Household",'CONSTANTS & REFERENCES'!$M$7,""))))*AL2) -> 105700 | AT2: =IF(AS2="","",IF(A2=0,IF(OR(AK2="Single",AK2="Married Filing Separately"),'CONSTANTS & REFERENCES'!$C$7,IF(AK2="Married Filing Jointly",'CONSTANTS & REFERENCES'!$H$7,IF(AK2="Head of Household",'CONSTANTS & REFERENCES'!$M$7,""))),_xlfn.FLOOR.MATH(AS2,IF(AK2="Married Filing Separately",Bracket_Round_MFS,Bracket_Round_Standard)))) -> 105700 | AU2: =IF(A2="","",(IF(OR(AK2="Single",AK2="Married Filing Separately"),'CONSTANTS & REFERENCES'!$C$8,IF(AK2="Married Filing Jointly",'CONSTANTS & REFERENCES'!$H$8,IF(AK2="Head of Household",'CONSTANTS & REFERENCES'!$M$8,""))))*AL2) -> 201775 | AV2: =IF(AU2="","",IF(A2=0,IF(OR(AK2="Single",AK2="Married Filing Separately"),'CONSTANTS & REFERENCES'!$C$8,IF(AK2="Married Filing Jointly",'CONSTANTS & REFERENCES'!$H$8,IF(AK2="Head of Household",'CONSTANTS & REFERENCES'!$M$8,""))),_xlfn.FLOOR.MATH(AU2,IF(AK2="Married Filing Separately",Bracket_Round_MFS,Bracket_Round_Standard)))) -> 201775 | AW2: =IF(A2="","",(IF(OR(AK2="Single",AK2="Married Filing Separately"),'CONSTANTS & REFERENCES'!$C$9,IF(AK2="Married Filing Jointly",'CONSTANTS & REFERENCES'!$H$9,IF(AK2="Head of Household",'CONSTANTS & REFERENCES'!$M$9,""))))*AL2) -> 256225 | AX2: =IF(AW2="","",IF(A2=0,IF(OR(AK2="Single",AK2="Married Filing Separately"),'CONSTANTS & REFERENCES'!$C$9,IF(AK2="Married Filing Jointly",'CONSTANTS & REFERENCES'!$H$9,IF(AK2="Head of Household",'CONSTANTS & REFERENCES'!$M$9,""))),_xlfn.FLOOR.MATH(AW2,IF(AK2="Married Filing Separately",Bracket_Round_MFS,Bracket_Round_Standard)))) -> 256225 | AY2: =IF(A2="","",(IF(OR(AK2="Single",AK2="Married Filing Separately"),'CONSTANTS & REFERENCES'!$C$10,IF(AK2="Married Filing Jointly",'CONSTANTS & REFERENCES'!$H$10,IF(AK2="Head of Household",'CONSTANTS & REFERENCES'!$M$10,""))))*AL2) -> 646600 | AZ2: =IF(AY2="","",IF(A2=0,IF(OR(AK2="Single",AK2="Married Filing Separately"),'CONSTANTS & REFERENCES'!$C$10,IF(AK2="Married Filing Jointly",'CONSTANTS & REFERENCES'!$H$10,IF(AK2="Head of Household",'CONSTANTS & REFERENCES'!$M$10,""))),_xlfn.FLOOR.MATH(AY2,IF(AK2="Married Filing Separately",Bracket_Round_MFS,Bracket_Round_Standard)))) -> 646600 | BA2: =IF(A2="","",IF(A2=0,"Official 2026 base values","Illustrative future tax assumptions under simplified C-CPI-U indexing; not an IRS forecast.")) -> Official 2026 base values | BB2: =IF(A2="","",'CONSTANTS & REFERENCES'!$C$22*AL2) -> 184500 | BC2: =IF(BB2="","",_xlfn.FLOOR.MATH(BB2,100)) -> 184500
A3: =IF(A2<INPUTS!$C$7-INPUTS!$C$6,A2+1,"") -> 1 | B3: =IF(A3="","",INPUTS!$C$6+A3) -> 23 | C3: =IF(A3="","",L2) -> 8250 | D3: =IF(A3="","",IF(A3<INPUTS!$C$13,0,J3)) -> 7500 | E3: =IF(A3="","",IF(D3=0,"—",IF(Y3<IF(AK3="Married Filing Jointly",'CONSTANTS & REFERENCES'!$B$44,IF(AK3="Married Filing Separately",'CONSTANTS & REFERENCES'!$B$45,'CONSTANTS & REFERENCES'!$B$43)),"Direct","Backdoor"))) -> Direct | F3: =IF(A3="","",$X$2*(1+$X$3)^A3) -> 7950 | G3: =IF(F3="","",_xlfn.FLOOR.MATH(F3,500)) -> 7500 | H3: =IF(A3="","",$X$4*(1+$X$3)^A3) -> 1166 | I3: =IF(H3="","",_xlfn.FLOOR.MATH(H3,100)) -> 1100 | J3: =IF(A3="","",G3+IF(B3>=50,I3,0)) -> 7500 | K3: =IF(A3="","",IF(INPUTS!$C$12="Beginning",(C3+D3)*INPUTS!$C$10,C3*INPUTS!$C$10)) -> 1575 | L3: =IF(A3="","",IF(INPUTS!$C$12="Beginning",(C3+D3)*(1+INPUTS!$C$10),C3*(1+INPUTS!$C$10)+D3)) -> 17325 | M3: =IF(A3="","",(1+INPUTS!$C$11)^A3) -> 1.06 | N3: =IF(A3="","",L3/M3) -> 16344.34 | O3: =IF(A3="","",O2+D3) -> 15000 | P3: =IF(A3="","",L3-INPUTS!$C$8-O3) -> 2325 | S3: =IF(B3="","",B3) -> 23 | T3: =IF(L3="","",L3) -> 17325 | U3: =IF(N3="","",N3) -> 16344.34 | V3: =IF(A3="","",FV(INPUTS!$C$10,INPUTS!$C$7-INPUTS!$C$6-A3+IF(INPUTS!$C$12="Beginning",1,0),0,-D3,0)) -> 451800.52 | W3: Assumed Annual Inflation Rate | X3: =INPUTS!$C$11 -> 0.06 | Y3: =IF(A3="","",IF(INPUTS!$C$17="Yes",MIN(Y2*(1+INPUTS!$C$15)+IF(INPUTS!$C$27="Yes",(Z3-Z2)*INPUTS!$C$31+IF(AND(INPUTS!$C$28="Not yet credentialed",A3=INPUTS!$C$33),INPUTS!$C$32,0)+IF(AND(INPUTS!$C$28<>"FSA / FCAS",A3=INPUTS!$C$35),INPUTS!$C$34,0),0),INPUTS!$C$18),Y2*(1+INPUTS!$C$15)+IF(INPUTS!$C$27="Yes",(Z3-Z2)*INPUTS!$C$31+IF(AND(INPUTS!$C$28="Not yet credentialed",A3=INPUTS!$C$33),INPUTS!$C$32,0)+IF(AND(INPUTS!$C$28<>"FSA / FCAS",A3=INPUTS!$C$35),INPUTS!$C$34,0),0))) -> 74350 | Z3: =IF(A3="","",IF(AND(INPUTS!$C$27="Yes",INPUTS!$C$28<>"FSA / FCAS",ISNUMBER(INPUTS!$C$37)),MIN(A3*INPUTS!$C$37,INPUTS!$C$30),0)) -> 0.75 | AA3: =IF(A3="","",AN3) -> 16950 | AB3: =IF(OR(A3="",AA3=""),"",MAX(0,Y3-AA3)) -> 57400 | AC3: =IF(A3="","",MIN(AB3,AP3)*'CONSTANTS & REFERENCES'!$A$5+MAX(MIN(AB3,AR3)-AP3,0)*'CONSTANTS & REFERENCES'!$A$6+MAX(MIN(AB3,AT3)-AR3,0)*'CONSTANTS & REFERENCES'!$A$7+MAX(MIN(AB3,AV3)-AT3,0)*'CONSTANTS & REFERENCES'!$A$8+MAX(MIN(AB3,AX3)-AV3,0)*'CONSTANTS & REFERENCES'!$A$9+MAX(MIN(AB3,AZ3)-AX3,0)*'CONSTANTS & REFERENCES'!$A$10+MAX(AB3-AZ3,0)*'CONSTANTS & REFERENCES'!$A$11) -> 7057 | AD3: =IF(AB3="","",IF(INPUTS!$C$20="Yes",AB3*INPUTS!$C$21,0)) -> 0 | AE3: =IF(Y3="","",MIN(Y3,BC3)*'CONSTANTS & REFERENCES'!$B$22) -> 4609.7 | AF3: =IF(Y3="","",Y3*'CONSTANTS & REFERENCES'!$B$24+MAX(0,Y3-IF(AK3="Married Filing Jointly",'CONSTANTS & REFERENCES'!$C$26,IF(AK3="Married Filing Separately",'CONSTANTS & REFERENCES'!$C$27,IF(AK3="Head of Household",'CONSTANTS & REFERENCES'!$C$28,'CONSTANTS & REFERENCES'!$C$25))))*'CONSTANTS & REFERENCES'!$B$25) -> 1078.075 | AG3: =IF(Y3="","",AE3+AF3) -> 5687.775 | AH3: =IF(OR(AC3="",AG3=""),"",AC3+AD3+AG3) -> 12744.775 | AI3: =IF(AH3="","",Y3-AH3) -> 61605.225 | AJ3: =IF(AI3="","",Y3-AH3-AI3) -> 0 | AK3: =IF(A3="","",IF(AND(INPUTS!$C$43="Yes",A3>=INPUTS!$C$45),INPUTS!$C$44,INPUTS!$C$19)) -> Single | AL3: =IF(A3="","",(1+$X$6)^A3) -> 1.05406 | AM3: =IF(A3="","",(IF(OR(AK3="Single",AK3="Married Filing Separately"),'CONSTANTS & REFERENCES'!$B$13,IF(AK3="Married Filing Jointly",'CONSTANTS & REFERENCES'!$G$13,IF(AK3="Head of Household",'CONSTANTS & REFERENCES'!$L$13,""))))*AL3) -> 16970.366 | AN3: =IF(AM3="","",IF(A3=0,IF(OR(AK3="Single",AK3="Married Filing Separately"),'CONSTANTS & REFERENCES'!$B$13,IF(AK3="Married Filing Jointly",'CONSTANTS & REFERENCES'!$G$13,IF(AK3="Head of Household",'CONSTANTS & REFERENCES'!$L$13,""))),_xlfn.FLOOR.MATH(AM3,IF(AK3="Married Filing Separately",Bracket_Round_MFS,Bracket_Round_Standard)))) -> 16950 | AO3: =IF(A3="","",(IF(OR(AK3="Single",AK3="Married Filing Separately"),'CONSTANTS & REFERENCES'!$C$5,IF(AK3="Married Filing Jointly",'CONSTANTS & REFERENCES'!$H$5,IF(AK3="Head of Household",'CONSTANTS & REFERENCES'!$M$5,""))))*AL3) -> 13070.344 | AP3: =IF(AO3="","",IF(A3=0,IF(OR(AK3="Single",AK3="Married Filing Separately"),'CONSTANTS & REFERENCES'!$C$5,IF(AK3="Married Filing Jointly",'CONSTANTS & REFERENCES'!$H$5,IF(AK3="Head of Household",'CONSTANTS & REFERENCES'!$M$5,""))),_xlfn.FLOOR.MATH(AO3,IF(AK3="Married Filing Separately",Bracket_Round_MFS,Bracket_Round_Standard)))) -> 13050 | AQ3: =IF(A3="","",(IF(OR(AK3="Single",AK3="Married Filing Separately"),'CONSTANTS & REFERENCES'!$C$6,IF(AK3="Married Filing Jointly",'CONSTANTS & REFERENCES'!$H$6,IF(AK3="Head of Household",'CONSTANTS & REFERENCES'!$M$6,""))))*AL3) -> 53124.624 | AR3: =IF(AQ3="","",IF(A3=0,IF(OR(AK3="Single",AK3="Married Filing Separately"),'CONSTANTS & REFERENCES'!$C$6,IF(AK3="Married Filing Jointly",'CONSTANTS & REFERENCES'!$H$6,IF(AK3="Head of Household",'CONSTANTS & REFERENCES'!$M$6,""))),_xlfn.FLOOR.MATH(AQ3,IF(AK3="Married Filing Separately",Bracket_Round_MFS,Bracket_Round_Standard)))) -> 53100 | AS3: =IF(A3="","",(IF(OR(AK3="Single",AK3="Married Filing Separately"),'CONSTANTS & REFERENCES'!$C$7,IF(AK3="Married Filing Jointly",'CONSTANTS & REFERENCES'!$H$7,IF(AK3="Head of Household",'CONSTANTS & REFERENCES'!$M$7,""))))*AL3) -> 111414.14 | AT3: =IF(AS3="","",IF(A3=0,IF(OR(AK3="Single",AK3="Married Filing Separately"),'CONSTANTS & REFERENCES'!$C$7,IF(AK3="Married Filing Jointly",'CONSTANTS & REFERENCES'!$H$7,IF(AK3="Head of Household",'CONSTANTS & REFERENCES'!$M$7,""))),_xlfn.FLOOR.MATH(AS3,IF(AK3="Married Filing Separately",Bracket_Round_MFS,Bracket_Round_Standard)))) -> 111400 | AU3: =IF(A3="","",(IF(OR(AK3="Single",AK3="Married Filing Separately"),'CONSTANTS & REFERENCES'!$C$8,IF(AK3="Married Filing Jointly",'CONSTANTS & REFERENCES'!$H$8,IF(AK3="Head of Household",'CONSTANTS & REFERENCES'!$M$8,""))))*AL3) -> 212682.96 | AV3: =IF(AU3="","",IF(A3=0,IF(OR(AK3="Single",AK3="Married Filing Separately"),'CONSTANTS & REFERENCES'!$C$8,IF(AK3="Married Filing Jointly",'CONSTANTS & REFERENCES'!$H$8,IF(AK3="Head of Household",'CONSTANTS & REFERENCES'!$M$8,""))),_xlfn.FLOOR.MATH(AU3,IF(AK3="Married Filing Separately",Bracket_Round_MFS,Bracket_Round_Standard)))) -> 212650 | AW3: =IF(A3="","",(IF(OR(AK3="Single",AK3="Married Filing Separately"),'CONSTANTS & REFERENCES'!$C$9,IF(AK3="Married Filing Jointly",'CONSTANTS & REFERENCES'!$H$9,IF(AK3="Head of Household",'CONSTANTS & REFERENCES'!$M$9,""))))*AL3) -> 270076.52 | AX3: =IF(AW3="","",IF(A3=0,IF(OR(AK3="Single",AK3="Married Filing Separately"),'CONSTANTS & REFERENCES'!$C$9,IF(AK3="Married Filing Jointly",'CONSTANTS & REFERENCES'!$H$9,IF(AK3="Head of Household",'CONSTANTS & REFERENCES'!$M$9,""))),_xlfn.FLOOR.MATH(AW3,IF(AK3="Married Filing Separately",Bracket_Round_MFS,Bracket_Round_Standard)))) -> 270050 | AY3: =IF(A3="","",(IF(OR(AK3="Single",AK3="Married Filing Separately"),'CONSTANTS & REFERENCES'!$C$10,IF(AK3="Married Filing Jointly",'CONSTANTS & REFERENCES'!$H$10,IF(AK3="Head of Household",'CONSTANTS & REFERENCES'!$M$10,""))))*AL3) -> 681555.2 | AZ3: =IF(AY3="","",IF(A3=0,IF(OR(AK3="Single",AK3="Married Filing Separately"),'CONSTANTS & REFERENCES'!$C$10,IF(AK3="Married Filing Jointly",'CONSTANTS & REFERENCES'!$H$10,IF(AK3="Head of Household",'CONSTANTS & REFERENCES'!$M$10,""))),_xlfn.FLOOR.MATH(AY3,IF(AK3="Married Filing Separately",Bracket_Round_MFS,Bracket_Round_Standard)))) -> 681550 | BA3: =IF(A3="","",IF(A3=0,"Official 2026 base values","Illustrative future tax assumptions under simplified C-CPI-U indexing; not an IRS forecast.")) -> Illustrative future tax assumptions under simplified C-CPI-U indexing; not an IRS forecast. | BB3: =IF(A3="","",'CONSTANTS & REFERENCES'!$C$22*AL3) -> 194474.07 | BC3: =IF(BB3="","",_xlfn.FLOOR.MATH(BB3,100)) -> 194400
A4: =IF(A3<INPUTS!$C$7-INPUTS!$C$6,A3+1,"") -> 2 | B4: =IF(A4="","",INPUTS!$C$6+A4) -> 24 | C4: =IF(A4="","",L3) -> 17325 | D4: =IF(A4="","",IF(A4<INPUTS!$C$13,0,J4)) -> 8000 | E4: =IF(A4="","",IF(D4=0,"—",IF(Y4<IF(AK4="Married Filing Jointly",'CONSTANTS & REFERENCES'!$B$44,IF(AK4="Married Filing Separately",'CONSTANTS & REFERENCES'!$B$45,'CONSTANTS & REFERENCES'!$B$43)),"Direct","Backdoor"))) -> Direct | F4: =IF(A4="","",$X$2*(1+$X$3)^A4) -> 8427 | G4: =IF(F4="","",_xlfn.FLOOR.MATH(F4,500)) -> 8000 | H4: =IF(A4="","",$X$4*(1+$X$3)^A4) -> 1235.96 | I4: =IF(H4="","",_xlfn.FLOOR.MATH(H4,100)) -> 1200 | J4: =IF(A4="","",G4+IF(B4>=50,I4,0)) -> 8000 | K4: =IF(A4="","",IF(INPUTS!$C$12="Beginning",(C4+D4)*INPUTS!$C$10,C4*INPUTS!$C$10)) -> 2532.5 | L4: =IF(A4="","",IF(INPUTS!$C$12="Beginning",(C4+D4)*(1+INPUTS!$C$10),C4*(1+INPUTS!$C$10)+D4)) -> 27857.5 | M4: =IF(A4="","",(1+INPUTS!$C$11)^A4) -> 1.1236 | N4: =IF(A4="","",L4/M4) -> 24793.076 | O4: =IF(A4="","",O3+D4) -> 23000 | P4: =IF(A4="","",L4-INPUTS!$C$8-O4) -> 4857.5 | S4: =IF(B4="","",B4) -> 24 | T4: =IF(L4="","",L4) -> 27857.5 | U4: =IF(N4="","",N4) -> 24793.076 | V4: =IF(A4="","",FV(INPUTS!$C$10,INPUTS!$C$7-INPUTS!$C$6-A4+IF(INPUTS!$C$12="Beginning",1,0),0,-D4,0)) -> 438109.59 | W4: Starting Modeled Catch-Up Limit (2026) | X4: 1100 | Y4: =IF(A4="","",IF(INPUTS!$C$17="Yes",MIN(Y3*(1+INPUTS!$C$15)+IF(INPUTS!$C$27="Yes",(Z4-Z3)*INPUTS!$C$31+IF(AND(INPUTS!$C$28="Not yet credentialed",A4=INPUTS!$C$33),INPUTS!$C$32,0)+IF(AND(INPUTS!$C$28<>"FSA / FCAS",A4=INPUTS!$C$35),INPUTS!$C$34,0),0),INPUTS!$C$18),Y3*(1+INPUTS!$C$15)+IF(INPUTS!$C$27="Yes",(Z4-Z3)*INPUTS!$C$31+IF(AND(INPUTS!$C$28="Not yet credentialed",A4=INPUTS!$C$33),INPUTS!$C$32,0)+IF(AND(INPUTS!$C$28<>"FSA / FCAS",A4=INPUTS!$C$35),INPUTS!$C$34,0),0))) -> 78830.5 | Z4: =IF(A4="","",IF(AND(INPUTS!$C$27="Yes",INPUTS!$C$28<>"FSA / FCAS",ISNUMBER(INPUTS!$C$37)),MIN(A4*INPUTS!$C$37,INPUTS!$C$30),0)) -> 1.5 | AA4: =IF(A4="","",AN4) -> 17850 | AB4: =IF(OR(A4="",AA4=""),"",MAX(0,Y4-AA4)) -> 60980.5 | AC4: =IF(A4="","",MIN(AB4,AP4)*'CONSTANTS & REFERENCES'!$A$5+MAX(MIN(AB4,AR4)-AP4,0)*'CONSTANTS & REFERENCES'!$A$6+MAX(MIN(AB4,AT4)-AR4,0)*'CONSTANTS & REFERENCES'!$A$7+MAX(MIN(AB4,AV4)-AT4,0)*'CONSTANTS & REFERENCES'!$A$8+MAX(MIN(AB4,AX4)-AV4,0)*'CONSTANTS & REFERENCES'!$A$9+MAX(MIN(AB4,AZ4)-AX4,0)*'CONSTANTS & REFERENCES'!$A$10+MAX(AB4-AZ4,0)*'CONSTANTS & REFERENCES'!$A$11) -> 7545.71 | AD4: =IF(AB4="","",IF(INPUTS!$C$20="Yes",AB4*INPUTS!$C$21,0)) -> 0 | AE4: =IF(Y4="","",MIN(Y4,BC4)*'CONSTANTS & REFERENCES'!$B$22) -> 4887.491 | AF4: =IF(Y4="","",Y4*'CONSTANTS & REFERENCES'!$B$24+MAX(0,Y4-IF(AK4="Married Filing Jointly",'CONSTANTS & REFERENCES'!$C$26,IF(AK4="Married Filing Separately",'CONSTANTS & REFERENCES'!$C$27,IF(AK4="Head of Household",'CONSTANTS & REFERENCES'!$C$28,'CONSTANTS & REFERENCES'!$C$25))))*'CONSTANTS & REFERENCES'!$B$25) -> 1143.0422 | AG4: =IF(Y4="","",AE4+AF4) -> 6030.5333 | AH4: =IF(OR(AC4="",AG4=""),"",AC4+AD4+AG4) -> 13576.243 | AI4: =IF(AH4="","",Y4-AH4) -> 65254.257 | AJ4: =IF(AI4="","",Y4-AH4-AI4) -> 0 | AK4: =IF(A4="","",IF(AND(INPUTS!$C$43="Yes",A4>=INPUTS!$C$45),INPUTS!$C$44,INPUTS!$C$19)) -> Single | AL4: =IF(A4="","",(1+$X$6)^A4) -> 1.1110425 | AM4: =IF(A4="","",(IF(OR(AK4="Single",AK4="Married Filing Separately"),'CONSTANTS & REFERENCES'!$B$13,IF(AK4="Married Filing Jointly",'CONSTANTS & REFERENCES'!$G$13,IF(AK4="Head of Household",'CONSTANTS & REFERENCES'!$L$13,""))))*AL4) -> 17887.784 | AN4: =IF(AM4="","",IF(A4=0,IF(OR(AK4="Single",AK4="Married Filing Separately"),'CONSTANTS & REFERENCES'!$B$13,IF(AK4="Married Filing Jointly",'CONSTANTS & REFERENCES'!$G$13,IF(AK4="Head of Household",'CONSTANTS & REFERENCES'!$L$13,""))),_xlfn.FLOOR.MATH(AM4,IF(AK4="Married Filing Separately",Bracket_Round_MFS,Bracket_Round_Standard)))) -> 17850 | AO4: =IF(A4="","",(IF(OR(AK4="Single",AK4="Married Filing Separately"),'CONSTANTS & REFERENCES'!$C$5,IF(AK4="Married Filing Jointly",'CONSTANTS & REFERENCES'!$H$5,IF(AK4="Head of Household",'CONSTANTS & REFERENCES'!$M$5,""))))*AL4) -> 13776.927 | AP4: =IF(AO4="","",IF(A4=0,IF(OR(AK4="Single",AK4="Married Filing Separately"),'CONSTANTS & REFERENCES'!$C$5,IF(AK4="Married Filing Jointly",'CONSTANTS & REFERENCES'!$H$5,IF(AK4="Head of Household",'CONSTANTS & REFERENCES'!$M$5,""))),_xlfn.FLOOR.MATH(AO4,IF(AK4="Married Filing Separately",Bracket_Round_MFS,Bracket_Round_Standard)))) -> 13750 | AQ4: =IF(A4="","",(IF(OR(AK4="Single",AK4="Married Filing Separately"),'CONSTANTS & REFERENCES'!$C$6,IF(AK4="Married Filing Jointly",'CONSTANTS & REFERENCES'!$H$6,IF(AK4="Head of Household",'CONSTANTS & REFERENCES'!$M$6,""))))*AL4) -> 55996.541 | AR4: =IF(AQ4="","",IF(A4=0,IF(OR(AK4="Single",AK4="Married Filing Separately"),'CONSTANTS & REFERENCES'!$C$6,IF(AK4="Married Filing Jointly",'CONSTANTS & REFERENCES'!$H$6,IF(AK4="Head of Household",'CONSTANTS & REFERENCES'!$M$6,""))),_xlfn.FLOOR.MATH(AQ4,IF(AK4="Married Filing Separately",Bracket_Round_MFS,Bracket_Round_Standard)))) -> 55950 | AS4: =IF(A4="","",(IF(OR(AK4="Single",AK4="Married Filing Separately"),'CONSTANTS & REFERENCES'!$C$7,IF(AK4="Married Filing Jointly",'CONSTANTS & REFERENCES'!$H$7,IF(AK4="Head of Household",'CONSTANTS & REFERENCES'!$M$7,""))))*AL4) -> 117437.19 | AT4: =IF(AS4="","",IF(A4=0,IF(OR(AK4="Single",AK4="Married Filing Separately"),'CONSTANTS & REFERENCES'!$C$7,IF(AK4="Married Filing Jointly",'CONSTANTS & REFERENCES'!$H$7,IF(AK4="Head of Household",'CONSTANTS & REFERENCES'!$M$7,""))),_xlfn.FLOOR.MATH(AS4,IF(AK4="Married Filing Separately",Bracket_Round_MFS,Bracket_Round_Standard)))) -> 117400 | AU4: =IF(A4="","",(IF(OR(AK4="Single",AK4="Married Filing Separately"),'CONSTANTS & REFERENCES'!$C$8,IF(AK4="Married Filing Jointly",'CONSTANTS & REFERENCES'!$H$8,IF(AK4="Head of Household",'CONSTANTS & REFERENCES'!$M$8,""))))*AL4) -> 224180.6 | AV4: =IF(AU4="","",IF(A4=0,IF(OR(AK4="Single",AK4="Married Filing Separately"),'CONSTANTS & REFERENCES'!$C$8,IF(AK4="Married Filing Jointly",'CONSTANTS & REFERENCES'!$H$8,IF(AK4="Head of Household",'CONSTANTS & REFERENCES'!$M$8,""))),_xlfn.FLOOR.MATH(AU4,IF(AK4="Married Filing Separately",Bracket_Round_MFS,Bracket_Round_Standard)))) -> 224150 | AW4: =IF(A4="","",(IF(OR(AK4="Single",AK4="Married Filing Separately"),'CONSTANTS & REFERENCES'!$C$9,IF(AK4="Married Filing Jointly",'CONSTANTS & REFERENCES'!$H$9,IF(AK4="Head of Household",'CONSTANTS & REFERENCES'!$M$9,""))))*AL4) -> 284676.86 | AX4: =IF(AW4="","",IF(A4=0,IF(OR(AK4="Single",AK4="Married Filing Separately"),'CONSTANTS & REFERENCES'!$C$9,IF(AK4="Married Filing Jointly",'CONSTANTS & REFERENCES'!$H$9,IF(AK4="Head of Household",'CONSTANTS & REFERENCES'!$M$9,""))),_xlfn.FLOOR.MATH(AW4,IF(AK4="Married Filing Separately",Bracket_Round_MFS,Bracket_Round_Standard)))) -> 284650 | AY4: =IF(A4="","",(IF(OR(AK4="Single",AK4="Married Filing Separately"),'CONSTANTS & REFERENCES'!$C$10,IF(AK4="Married Filing Jointly",'CONSTANTS & REFERENCES'!$H$10,IF(AK4="Head of Household",'CONSTANTS & REFERENCES'!$M$10,""))))*AL4) -> 718400.07 | AZ4: =IF(AY4="","",IF(A4=0,IF(OR(AK4="Single",AK4="Married Filing Separately"),'CONSTANTS & REFERENCES'!$C$10,IF(AK4="Married Filing Jointly",'CONSTANTS & REFERENCES'!$H$10,IF(AK4="Head of Household",'CONSTANTS & REFERENCES'!$M$10,""))),_xlfn.FLOOR.MATH(AY4,IF(AK4="Married Filing Separately",Bracket_Round_MFS,Bracket_Round_Standard)))) -> 718400 | BA4: =IF(A4="","",IF(A4=0,"Official 2026 base values","Illustrative future tax assumptions under simplified C-CPI-U indexing; not an IRS forecast.")) -> Illustrative future tax assumptions under simplified C-CPI-U indexing; not an IRS forecast. | BB4: =IF(A4="","",'CONSTANTS & REFERENCES'!$C$22*AL4) -> 204987.34 | BC4: =IF(BB4="","",_xlfn.FLOOR.MATH(BB4,100)) -> 204900
A5: =IF(A4<INPUTS!$C$7-INPUTS!$C$6,A4+1,"") -> 3 | B5: =IF(A5="","",INPUTS!$C$6+A5) -> 25 | C5: =IF(A5="","",L4) -> 27857.5 | D5: =IF(A5="","",IF(A5<INPUTS!$C$13,0,J5)) -> 8500 | E5: =IF(A5="","",IF(D5=0,"—",IF(Y5<IF(AK5="Married Filing Jointly",'CONSTANTS & REFERENCES'!$B$44,IF(AK5="Married Filing Separately",'CONSTANTS & REFERENCES'!$B$45,'CONSTANTS & REFERENCES'!$B$43)),"Direct","Backdoor"))) -> Direct | F5: =IF(A5="","",$X$2*(1+$X$3)^A5) -> 8932.62 | G5: =IF(F5="","",_xlfn.FLOOR.MATH(F5,500)) -> 8500 | H5: =IF(A5="","",$X$4*(1+$X$3)^A5) -> 1310.1176 | I5: =IF(H5="","",_xlfn.FLOOR.MATH(H5,100)) -> 1300 | J5: =IF(A5="","",G5+IF(B5>=50,I5,0)) -> 8500 | K5: =IF(A5="","",IF(INPUTS!$C$12="Beginning",(C5+D5)*INPUTS!$C$10,C5*INPUTS!$C$10)) -> 3635.75 | L5: =IF(A5="","",IF(INPUTS!$C$12="Beginning",(C5+D5)*(1+INPUTS!$C$10),C5*(1+INPUTS!$C$10)+D5)) -> 39993.25 | M5: =IF(A5="","",(1+INPUTS!$C$11)^A5) -> 1.191016 | N5: =IF(A5="","",L5/M5) -> 33579.104 | O5: =IF(A5="","",O4+D5) -> 31500 | P5: =IF(A5="","",L5-INPUTS!$C$8-O5) -> 8493.25 | S5: =IF(B5="","",B5) -> 25 | T5: =IF(L5="","",L5) -> 39993.25 | U5: =IF(N5="","",N5) -> 33579.104 | V5: =IF(A5="","",FV(INPUTS!$C$10,INPUTS!$C$7-INPUTS!$C$6-A5+IF(INPUTS!$C$12="Beginning",1,0),0,-D5,0)) -> 423174.04 | W5: Historical C-CPI-U Factor | X5: 0.901 | Y5: =IF(A5="","",IF(INPUTS!$C$17="Yes",MIN(Y4*(1+INPUTS!$C$15)+IF(INPUTS!$C$27="Yes",(Z5-Z4)*INPUTS!$C$31+IF(AND(INPUTS!$C$28="Not yet credentialed",A5=INPUTS!$C$33),INPUTS!$C$32,0)+IF(AND(INPUTS!$C$28<>"FSA / FCAS",A5=INPUTS!$C$35),INPUTS!$C$34,0),0),INPUTS!$C$18),Y4*(1+INPUTS!$C$15)+IF(INPUTS!$C$27="Yes",(Z5-Z4)*INPUTS!$C$31+IF(AND(INPUTS!$C$28="Not yet credentialed",A5=INPUTS!$C$33),INPUTS!$C$32,0)+IF(AND(INPUTS!$C$28<>"FSA / FCAS",A5=INPUTS!$C$35),INPUTS!$C$34,0),0))) -> 83445.415 | Z5: =IF(A5="","",IF(AND(INPUTS!$C$27="Yes",INPUTS!$C$28<>"FSA / FCAS",ISNUMBER(INPUTS!$C$37)),MIN(A5*INPUTS!$C$37,INPUTS!$C$30),0)) -> 2.25 | AA5: =IF(A5="","",AN5) -> 18850 | AB5: =IF(OR(A5="",AA5=""),"",MAX(0,Y5-AA5)) -> 64595.415 | AC5: =IF(A5="","",MIN(AB5,AP5)*'CONSTANTS & REFERENCES'!$A$5+MAX(MIN(AB5,AR5)-AP5,0)*'CONSTANTS & REFERENCES'!$A$6+MAX(MIN(AB5,AT5)-AR5,0)*'CONSTANTS & REFERENCES'!$A$7+MAX(MIN(AB5,AV5)-AT5,0)*'CONSTANTS & REFERENCES'!$A$8+MAX(MIN(AB5,AX5)-AV5,0)*'CONSTANTS & REFERENCES'!$A$9+MAX(MIN(AB5,AZ5)-AX5,0)*'CONSTANTS & REFERENCES'!$A$10+MAX(AB5-AZ5,0)*'CONSTANTS & REFERENCES'!$A$11) -> 8020.9913 | AD5: =IF(AB5="","",IF(INPUTS!$C$20="Yes",AB5*INPUTS!$C$21,0)) -> 0 | AE5: =IF(Y5="","",MIN(Y5,BC5)*'CONSTANTS & REFERENCES'!$B$22) -> 5173.6157 | AF5: =IF(Y5="","",Y5*'CONSTANTS & REFERENCES'!$B$24+MAX(0,Y5-IF(AK5="Married Filing Jointly",'CONSTANTS & REFERENCES'!$C$26,IF(AK5="Married Filing Separately",'CONSTANTS & REFERENCES'!$C$27,IF(AK5="Head of Household",'CONSTANTS & REFERENCES'!$C$28,'CONSTANTS & REFERENCES'!$C$25))))*'CONSTANTS & REFERENCES'!$B$25) -> 1209.9585 | AG5: =IF(Y5="","",AE5+AF5) -> 6383.5742 | AH5: =IF(OR(AC5="",AG5=""),"",AC5+AD5+AG5) -> 14404.566 | AI5: =IF(AH5="","",Y5-AH5) -> 69040.849 | AJ5: =IF(AI5="","",Y5-AH5-AI5) -> 0 | AK5: =IF(A5="","",IF(AND(INPUTS!$C$43="Yes",A5>=INPUTS!$C$45),INPUTS!$C$44,INPUTS!$C$19)) -> Single | AL5: =IF(A5="","",(1+$X$6)^A5) -> 1.1711054 | AM5: =IF(A5="","",(IF(OR(AK5="Single",AK5="Married Filing Separately"),'CONSTANTS & REFERENCES'!$B$13,IF(AK5="Married Filing Jointly",'CONSTANTS & REFERENCES'!$G$13,IF(AK5="Head of Household",'CONSTANTS & REFERENCES'!$L$13,""))))*AL5) -> 18854.798 | AN5: =IF(AM5="","",IF(A5=0,IF(OR(AK5="Single",AK5="Married Filing Separately"),'CONSTANTS & REFERENCES'!$B$13,IF(AK5="Married Filing Jointly",'CONSTANTS & REFERENCES'!$G$13,IF(AK5="Head of Household",'CONSTANTS & REFERENCES'!$L$13,""))),_xlfn.FLOOR.MATH(AM5,IF(AK5="Married Filing Separately",Bracket_Round_MFS,Bracket_Round_Standard)))) -> 18850 | AO5: =IF(A5="","",(IF(OR(AK5="Single",AK5="Married Filing Separately"),'CONSTANTS & REFERENCES'!$C$5,IF(AK5="Married Filing Jointly",'CONSTANTS & REFERENCES'!$H$5,IF(AK5="Head of Household",'CONSTANTS & REFERENCES'!$M$5,""))))*AL5) -> 14521.707 | AP5: =IF(AO5="","",IF(A5=0,IF(OR(AK5="Single",AK5="Married Filing Separately"),'CONSTANTS & REFERENCES'!$C$5,IF(AK5="Married Filing Jointly",'CONSTANTS & REFERENCES'!$H$5,IF(AK5="Head of Household",'CONSTANTS & REFERENCES'!$M$5,""))),_xlfn.FLOOR.MATH(AO5,IF(AK5="Married Filing Separately",Bracket_Round_MFS,Bracket_Round_Standard)))) -> 14500 | AQ5: =IF(A5="","",(IF(OR(AK5="Single",AK5="Married Filing Separately"),'CONSTANTS & REFERENCES'!$C$6,IF(AK5="Married Filing Jointly",'CONSTANTS & REFERENCES'!$H$6,IF(AK5="Head of Household",'CONSTANTS & REFERENCES'!$M$6,""))))*AL5) -> 59023.714 | AR5: =IF(AQ5="","",IF(A5=0,IF(OR(AK5="Single",AK5="Married Filing Separately"),'CONSTANTS & REFERENCES'!$C$6,IF(AK5="Married Filing Jointly",'CONSTANTS & REFERENCES'!$H$6,IF(AK5="Head of Household",'CONSTANTS & REFERENCES'!$M$6,""))),_xlfn.FLOOR.MATH(AQ5,IF(AK5="Married Filing Separately",Bracket_Round_MFS,Bracket_Round_Standard)))) -> 59000 | AS5: =IF(A5="","",(IF(OR(AK5="Single",AK5="Married Filing Separately"),'CONSTANTS & REFERENCES'!$C$7,IF(AK5="Married Filing Jointly",'CONSTANTS & REFERENCES'!$H$7,IF(AK5="Head of Household",'CONSTANTS & REFERENCES'!$M$7,""))))*AL5) -> 123785.85 | AT5: =IF(AS5="","",IF(A5=0,IF(OR(AK5="Single",AK5="Married Filing Separately"),'CONSTANTS & REFERENCES'!$C$7,IF(AK5="Married Filing Jointly",'CONSTANTS & REFERENCES'!$H$7,IF(AK5="Head of Household",'CONSTANTS & REFERENCES'!$M$7,""))),_xlfn.FLOOR.MATH(AS5,IF(AK5="Married Filing Separately",Bracket_Round_MFS,Bracket_Round_Standard)))) -> 123750 | AU5: =IF(A5="","",(IF(OR(AK5="Single",AK5="Married Filing Separately"),'CONSTANTS & REFERENCES'!$C$8,IF(AK5="Married Filing Jointly",'CONSTANTS & REFERENCES'!$H$8,IF(AK5="Head of Household",'CONSTANTS & REFERENCES'!$M$8,""))))*AL5) -> 236299.8 | AV5: =IF(AU5="","",IF(A5=0,IF(OR(AK5="Single",AK5="Married Filing Separately"),'CONSTANTS & REFERENCES'!$C$8,IF(AK5="Married Filing Jointly",'CONSTANTS & REFERENCES'!$H$8,IF(AK5="Head of Household",'CONSTANTS & REFERENCES'!$M$8,""))),_xlfn.FLOOR.MATH(AU5,IF(AK5="Married Filing Separately",Bracket_Round_MFS,Bracket_Round_Standard)))) -> 236250 | AW5: =IF(A5="","",(IF(OR(AK5="Single",AK5="Married Filing Separately"),'CONSTANTS & REFERENCES'!$C$9,IF(AK5="Married Filing Jointly",'CONSTANTS & REFERENCES'!$H$9,IF(AK5="Head of Household",'CONSTANTS & REFERENCES'!$M$9,""))))*AL5) -> 300066.49 | AX5: =IF(AW5="","",IF(A5=0,IF(OR(AK5="Single",AK5="Married Filing Separately"),'CONSTANTS & REFERENCES'!$C$9,IF(AK5="Married Filing Jointly",'CONSTANTS & REFERENCES'!$H$9,IF(AK5="Head of Household",'CONSTANTS & REFERENCES'!$M$9,""))),_xlfn.FLOOR.MATH(AW5,IF(AK5="Married Filing Separately",Bracket_Round_MFS,Bracket_Round_Standard)))) -> 300050 | AY5: =IF(A5="","",(IF(OR(AK5="Single",AK5="Married Filing Separately"),'CONSTANTS & REFERENCES'!$C$10,IF(AK5="Married Filing Jointly",'CONSTANTS & REFERENCES'!$H$10,IF(AK5="Head of Household",'CONSTANTS & REFERENCES'!$M$10,""))))*AL5) -> 757236.78 | AZ5: =IF(AY5="","",IF(A5=0,IF(OR(AK5="Single",AK5="Married Filing Separately"),'CONSTANTS & REFERENCES'!$C$10,IF(AK5="Married Filing Jointly",'CONSTANTS & REFERENCES'!$H$10,IF(AK5="Head of Household",'CONSTANTS & REFERENCES'!$M$10,""))),_xlfn.FLOOR.MATH(AY5,IF(AK5="Married Filing Separately",Bracket_Round_MFS,Bracket_Round_Standard)))) -> 757200 | BA5: =IF(A5="","",IF(A5=0,"Official 2026 base values","Illustrative future tax assumptions under simplified C-CPI-U indexing; not an IRS forecast.")) -> Illustrative future tax assumptions under simplified C-CPI-U indexing; not an IRS forecast. | BB5: =IF(A5="","",'CONSTANTS & REFERENCES'!$C$22*AL5) -> 216068.95 | BC5: =IF(BB5="","",_xlfn.FLOOR.MATH(BB5,100)) -> 216000
A6: =IF(A5<INPUTS!$C$7-INPUTS!$C$6,A5+1,"") -> 4 | B6: =IF(A6="","",INPUTS!$C$6+A6) -> 26 | C6: =IF(A6="","",L5) -> 39993.25 | D6: =IF(A6="","",IF(A6<INPUTS!$C$13,0,J6)) -> 9000 | E6: =IF(A6="","",IF(D6=0,"—",IF(Y6<IF(AK6="Married Filing Jointly",'CONSTANTS & REFERENCES'!$B$44,IF(AK6="Married Filing Separately",'CONSTANTS & REFERENCES'!$B$45,'CONSTANTS & REFERENCES'!$B$43)),"Direct","Backdoor"))) -> Direct | F6: =IF(A6="","",$X$2*(1+$X$3)^A6) -> 9468.5772 | G6: =IF(F6="","",_xlfn.FLOOR.MATH(F6,500)) -> 9000 | H6: =IF(A6="","",$X$4*(1+$X$3)^A6) -> 1388.7247 | I6: =IF(H6="","",_xlfn.FLOOR.MATH(H6,100)) -> 1300 | J6: =IF(A6="","",G6+IF(B6>=50,I6,0)) -> 9000 | K6: =IF(A6="","",IF(INPUTS!$C$12="Beginning",(C6+D6)*INPUTS!$C$10,C6*INPUTS!$C$10)) -> 4899.325 | L6: =IF(A6="","",IF(INPUTS!$C$12="Beginning",(C6+D6)*(1+INPUTS!$C$10),C6*(1+INPUTS!$C$10)+D6)) -> 53892.575 | M6: =IF(A6="","",(1+INPUTS!$C$11)^A6) -> 1.262477 | N6: =IF(A6="","",L6/M6) -> 42687.967 | O6: =IF(A6="","",O5+D6) -> 40500 | P6: =IF(A6="","",L6-INPUTS!$C$8-O6) -> 13392.575 | S6: =IF(B6="","",B6) -> 26 | T6: =IF(L6="","",L6) -> 53892.575 | U6: =IF(N6="","",N6) -> 42687.967 | V6: =IF(A6="","",FV(INPUTS!$C$10,INPUTS!$C$7-INPUTS!$C$6-A6+IF(INPUTS!$C$12="Beginning",1,0),0,-D6,0)) -> 407333.3 | W6: Modeled C-CPI-U Rate | X6: =X3*X5 -> 0.05406 | Y6: =IF(A6="","",IF(INPUTS!$C$17="Yes",MIN(Y5*(1+INPUTS!$C$15)+IF(INPUTS!$C$27="Yes",(Z6-Z5)*INPUTS!$C$31+IF(AND(INPUTS!$C$28="Not yet credentialed",A6=INPUTS!$C$33),INPUTS!$C$32,0)+IF(AND(INPUTS!$C$28<>"FSA / FCAS",A6=INPUTS!$C$35),INPUTS!$C$34,0),0),INPUTS!$C$18),Y5*(1+INPUTS!$C$15)+IF(INPUTS!$C$27="Yes",(Z6-Z5)*INPUTS!$C$31+IF(AND(INPUTS!$C$28="Not yet credentialed",A6=INPUTS!$C$33),INPUTS!$C$32,0)+IF(AND(INPUTS!$C$28<>"FSA / FCAS",A6=INPUTS!$C$35),INPUTS!$C$34,0),0))) -> 103198.78 | Z6: =IF(A6="","",IF(AND(INPUTS!$C$27="Yes",INPUTS!$C$28<>"FSA / FCAS",ISNUMBER(INPUTS!$C$37)),MIN(A6*INPUTS!$C$37,INPUTS!$C$30),0)) -> 3 | AA6: =IF(A6="","",AN6) -> 19850 | AB6: =IF(OR(A6="",AA6=""),"",MAX(0,Y6-AA6)) -> 83348.777 | AC6: =IF(A6="","",MIN(AB6,AP6)*'CONSTANTS & REFERENCES'!$A$5+MAX(MIN(AB6,AR6)-AP6,0)*'CONSTANTS & REFERENCES'!$A$6+MAX(MIN(AB6,AT6)-AR6,0)*'CONSTANTS & REFERENCES'!$A$7+MAX(MIN(AB6,AV6)-AT6,0)*'CONSTANTS & REFERENCES'!$A$8+MAX(MIN(AB6,AX6)-AV6,0)*'CONSTANTS & REFERENCES'!$A$9+MAX(MIN(AB6,AZ6)-AX6,0)*'CONSTANTS & REFERENCES'!$A$10+MAX(AB6-AZ6,0)*'CONSTANTS & REFERENCES'!$A$11) -> 11810.731 | AD6: =IF(AB6="","",IF(INPUTS!$C$20="Yes",AB6*INPUTS!$C$21,0)) -> 0 | AE6: =IF(Y6="","",MIN(Y6,BC6)*'CONSTANTS & REFERENCES'!$B$22) -> 6398.3242 | AF6: =IF(Y6="","",Y6*'CONSTANTS & REFERENCES'!$B$24+MAX(0,Y6-IF(AK6="Married Filing Jointly",'CONSTANTS & REFERENCES'!$C$26,IF(AK6="Married Filing Separately",'CONSTANTS & REFERENCES'!$C$27,IF(AK6="Head of Household",'CONSTANTS & REFERENCES'!$C$28,'CONSTANTS & REFERENCES'!$C$25))))*'CONSTANTS & REFERENCES'!$B$25) -> 1496.3823 | AG6: =IF(Y6="","",AE6+AF6) -> 7894.7065 | AH6: =IF(OR(AC6="",AG6=""),"",AC6+AD6+AG6) -> 19705.438 | AI6: =IF(AH6="","",Y6-AH6) -> 83493.34 | AJ6: =IF(AI6="","",Y6-AH6-AI6) -> 0 | AK6: =IF(A6="","",IF(AND(INPUTS!$C$43="Yes",A6>=INPUTS!$C$45),INPUTS!$C$44,INPUTS!$C$19)) -> Single | AL6: =IF(A6="","",(1+$X$6)^A6) -> 1.2344154 | AM6: =IF(A6="","",(IF(OR(AK6="Single",AK6="Married Filing Separately"),'CONSTANTS & REFERENCES'!$B$13,IF(AK6="Married Filing Jointly",'CONSTANTS & REFERENCES'!$G$13,IF(AK6="Head of Household",'CONSTANTS & REFERENCES'!$L$13,""))))*AL6) -> 19874.088 | AN6: =IF(AM6="","",IF(A6=0,IF(OR(AK6="Single",AK6="Married Filing Separately"),'CONSTANTS & REFERENCES'!$B$13,IF(AK6="Married Filing Jointly",'CONSTANTS & REFERENCES'!$G$13,IF(AK6="Head of Household",'CONSTANTS & REFERENCES'!$L$13,""))),_xlfn.FLOOR.MATH(AM6,IF(AK6="Married Filing Separately",Bracket_Round_MFS,Bracket_Round_Standard)))) -> 19850 | AO6: =IF(A6="","",(IF(OR(AK6="Single",AK6="Married Filing Separately"),'CONSTANTS & REFERENCES'!$C$5,IF(AK6="Married Filing Jointly",'CONSTANTS & REFERENCES'!$H$5,IF(AK6="Head of Household",'CONSTANTS & REFERENCES'!$M$5,""))))*AL6) -> 15306.751 | AP6: =IF(AO6="","",IF(A6=0,IF(OR(AK6="Single",AK6="Married Filing Separately"),'CONSTANTS & REFERENCES'!$C$5,IF(AK6="Married Filing Jointly",'CONSTANTS & REFERENCES'!$H$5,IF(AK6="Head of Household",'CONSTANTS & REFERENCES'!$M$5,""))),_xlfn.FLOOR.MATH(AO6,IF(AK6="Married Filing Separately",Bracket_Round_MFS,Bracket_Round_Standard)))) -> 15300 | AQ6: =IF(A6="","",(IF(OR(AK6="Single",AK6="Married Filing Separately"),'CONSTANTS & REFERENCES'!$C$6,IF(AK6="Married Filing Jointly",'CONSTANTS & REFERENCES'!$H$6,IF(AK6="Head of Household",'CONSTANTS & REFERENCES'!$M$6,""))))*AL6) -> 62214.536 | AR6: =IF(AQ6="","",IF(A6=0,IF(OR(AK6="Single",AK6="Married Filing Separately"),'CONSTANTS & REFERENCES'!$C$6,IF(AK6="Married Filing Jointly",'CONSTANTS & REFERENCES'!$H$6,IF(AK6="Head of Household",'CONSTANTS & REFERENCES'!$M$6,""))),_xlfn.FLOOR.MATH(AQ6,IF(AK6="Married Filing Separately",Bracket_Round_MFS,Bracket_Round_Standard)))) -> 62200 | AS6: =IF(A6="","",(IF(OR(AK6="Single",AK6="Married Filing Separately"),'CONSTANTS & REFERENCES'!$C$7,IF(AK6="Married Filing Jointly",'CONSTANTS & REFERENCES'!$H$7,IF(AK6="Head of Household",'CONSTANTS & REFERENCES'!$M$7,""))))*AL6) -> 130477.71 | AT6: =IF(AS6="","",IF(A6=0,IF(OR(AK6="Single",AK6="Married Filing Separately"),'CONSTANTS & REFERENCES'!$C$7,IF(AK6="Married Filing Jointly",'CONSTANTS & REFERENCES'!$H$7,IF(AK6="Head of Household",'CONSTANTS & REFERENCES'!$M$7,""))),_xlfn.FLOOR.MATH(AS6,IF(AK6="Married Filing Separately",Bracket_Round_MFS,Bracket_Round_Standard)))) -> 130450 | AU6: =IF(A6="","",(IF(OR(AK6="Single",AK6="Married Filing Separately"),'CONSTANTS & REFERENCES'!$C$8,IF(AK6="Married Filing Jointly",'CONSTANTS & REFERENCES'!$H$8,IF(AK6="Head of Household",'CONSTANTS & REFERENCES'!$M$8,""))))*AL6) -> 249074.17 | AV6: =IF(AU6="","",IF(A6=0,IF(OR(AK6="Single",AK6="Married Filing Separately"),'CONSTANTS & REFERENCES'!$C$8,IF(AK6="Married Filing Jointly",'CONSTANTS & REFERENCES'!$H$8,IF(AK6="Head of Household",'CONSTANTS & REFERENCES'!$M$8,""))),_xlfn.FLOOR.MATH(AU6,IF(AK6="Married Filing Separately",Bracket_Round_MFS,Bracket_Round_Standard)))) -> 249050 | AW6: =IF(A6="","",(IF(OR(AK6="Single",AK6="Married Filing Separately"),'CONSTANTS & REFERENCES'!$C$9,IF(AK6="Married Filing Jointly",'CONSTANTS & REFERENCES'!$H$9,IF(AK6="Head of Household",'CONSTANTS & REFERENCES'!$M$9,""))))*AL6) -> 316288.09 | AX6: =IF(AW6="","",IF(A6=0,IF(OR(AK6="Single",AK6="Married Filing Separately"),'CONSTANTS & REFERENCES'!$C$9,IF(AK6="Married Filing Jointly",'CONSTANTS & REFERENCES'!$H$9,IF(AK6="Head of Household",'CONSTANTS & REFERENCES'!$M$9,""))),_xlfn.FLOOR.MATH(AW6,IF(AK6="Married Filing Separately",Bracket_Round_MFS,Bracket_Round_Standard)))) -> 316250 | AY6: =IF(A6="","",(IF(OR(AK6="Single",AK6="Married Filing Separately"),'CONSTANTS & REFERENCES'!$C$10,IF(AK6="Married Filing Jointly",'CONSTANTS & REFERENCES'!$H$10,IF(AK6="Head of Household",'CONSTANTS & REFERENCES'!$M$10,""))))*AL6) -> 798173 | AZ6: =IF(AY6="","",IF(A6=0,IF(OR(AK6="Single",AK6="Married Filing Separately"),'CONSTANTS & REFERENCES'!$C$10,IF(AK6="Married Filing Jointly",'CONSTANTS & REFERENCES'!$H$10,IF(AK6="Head of Household",'CONSTANTS & REFERENCES'!$M$10,""))),_xlfn.FLOOR.MATH(AY6,IF(AK6="Married Filing Separately",Bracket_Round_MFS,Bracket_Round_Standard)))) -> 798150 | BA6: =IF(A6="","",IF(A6=0,"Official 2026 base values","Illustrative future tax assumptions under simplified C-CPI-U indexing; not an IRS forecast.")) -> Illustrative future tax assumptions under simplified C-CPI-U indexing; not an IRS forecast. | BB6: =IF(A6="","",'CONSTANTS & REFERENCES'!$C$22*AL6) -> 227749.64 | BC6: =IF(BB6="","",_xlfn.FLOOR.MATH(BB6,100)) -> 227700
A7: =IF(A6<INPUTS!$C$7-INPUTS!$C$6,A6+1,"") -> 5 | B7: =IF(A7="","",INPUTS!$C$6+A7) -> 27 | C7: =IF(A7="","",L6) -> 53892.575 | D7: =IF(A7="","",IF(A7<INPUTS!$C$13,0,J7)) -> 10000 | E7: =IF(A7="","",IF(D7=0,"—",IF(Y7<IF(AK7="Married Filing Jointly",'CONSTANTS & REFERENCES'!$B$44,IF(AK7="Married Filing Separately",'CONSTANTS & REFERENCES'!$B$45,'CONSTANTS & REFERENCES'!$B$43)),"Direct","Backdoor"))) -> Direct | F7: =IF(A7="","",$X$2*(1+$X$3)^A7) -> 10036.692 | G7: =IF(F7="","",_xlfn.FLOOR.MATH(F7,500)) -> 10000 | H7: =IF(A7="","",$X$4*(1+$X$3)^A7) -> 1472.0481 | I7: =IF(H7="","",_xlfn.FLOOR.MATH(H7,100)) -> 1400 | J7: =IF(A7="","",G7+IF(B7>=50,I7,0)) -> 10000 | K7: =IF(A7="","",IF(INPUTS!$C$12="Beginning",(C7+D7)*INPUTS!$C$10,C7*INPUTS!$C$10)) -> 6389.2575 | L7: =IF(A7="","",IF(INPUTS!$C$12="Beginning",(C7+D7)*(1+INPUTS!$C$10),C7*(1+INPUTS!$C$10)+D7)) -> 70281.833 | M7: =IF(A7="","",(1+INPUTS!$C$11)^A7) -> 1.3382256 | N7: =IF(A7="","",L7/M7) -> 52518.674 | O7: =IF(A7="","",O6+D7) -> 50500 | P7: =IF(A7="","",L7-INPUTS!$C$8-O7) -> 19781.833 | S7: =IF(B7="","",B7) -> 27 | T7: =IF(L7="","",L7) -> 70281.833 | U7: =IF(N7="","",N7) -> 52518.674 | V7: =IF(A7="","",FV(INPUTS!$C$10,INPUTS!$C$7-INPUTS!$C$6-A7+IF(INPUTS!$C$12="Beginning",1,0),0,-D7,0)) -> 411447.78 | W7: Future Tax Assumption | X7: Illustrative future tax assumptions under simplified C-CPI-U indexing; not an IRS forecast. | Y7: =IF(A7="","",IF(INPUTS!$C$17="Yes",MIN(Y6*(1+INPUTS!$C$15)+IF(INPUTS!$C$27="Yes",(Z7-Z6)*INPUTS!$C$31+IF(AND(INPUTS!$C$28="Not yet credentialed",A7=INPUTS!$C$33),INPUTS!$C$32,0)+IF(AND(INPUTS!$C$28<>"FSA / FCAS",A7=INPUTS!$C$35),INPUTS!$C$34,0),0),INPUTS!$C$18),Y6*(1+INPUTS!$C$15)+IF(INPUTS!$C$27="Yes",(Z7-Z6)*INPUTS!$C$31+IF(AND(INPUTS!$C$28="Not yet credentialed",A7=INPUTS!$C$33),INPUTS!$C$32,0)+IF(AND(INPUTS!$C$28<>"FSA / FCAS",A7=INPUTS!$C$35),INPUTS!$C$34,0),0))) -> 106294.74 | Z7: =IF(A7="","",IF(AND(INPUTS!$C$27="Yes",INPUTS!$C$28<>"FSA / FCAS",ISNUMBER(INPUTS!$C$37)),MIN(A7*INPUTS!$C$37,INPUTS!$C$30),0)) -> 3 | AA7: =IF(A7="","",AN7) -> 41850 | AB7: =IF(OR(A7="",AA7=""),"",MAX(0,Y7-AA7)) -> 64444.741 | AC7: =IF(A7="","",MIN(AB7,AP7)*'CONSTANTS & REFERENCES'!$A$5+MAX(MIN(AB7,AR7)-AP7,0)*'CONSTANTS & REFERENCES'!$A$6+MAX(MIN(AB7,AT7)-AR7,0)*'CONSTANTS & REFERENCES'!$A$7+MAX(MIN(AB7,AV7)-AT7,0)*'CONSTANTS & REFERENCES'!$A$8+MAX(MIN(AB7,AX7)-AV7,0)*'CONSTANTS & REFERENCES'!$A$9+MAX(MIN(AB7,AZ7)-AX7,0)*'CONSTANTS & REFERENCES'!$A$10+MAX(AB7-AZ7,0)*'CONSTANTS & REFERENCES'!$A$11) -> 7088.3689 | AD7: =IF(AB7="","",IF(INPUTS!$C$20="Yes",AB7*INPUTS!$C$21,0)) -> 0 | AE7: =IF(Y7="","",MIN(Y7,BC7)*'CONSTANTS & REFERENCES'!$B$22) -> 6590.2739 | AF7: =IF(Y7="","",Y7*'CONSTANTS & REFERENCES'!$B$24+MAX(0,Y7-IF(AK7="Married Filing Jointly",'CONSTANTS & REFERENCES'!$C$26,IF(AK7="Married Filing Separately",'CONSTANTS & REFERENCES'!$C$27,IF(AK7="Head of Household",'CONSTANTS & REFERENCES'!$C$28,'CONSTANTS & REFERENCES'!$C$25))))*'CONSTANTS & REFERENCES'!$B$25) -> 1541.2737 | AG7: =IF(Y7="","",AE7+AF7) -> 8131.5477 | AH7: =IF(OR(AC7="",AG7=""),"",AC7+AD7+AG7) -> 15219.917 | AI7: =IF(AH7="","",Y7-AH7) -> 91074.824 | AJ7: =IF(AI7="","",Y7-AH7-AI7) -> 0 | AK7: =IF(A7="","",IF(AND(INPUTS!$C$43="Yes",A7>=INPUTS!$C$45),INPUTS!$C$44,INPUTS!$C$19)) -> Married Filing Jointly | AL7: =IF(A7="","",(1+$X$6)^A7) -> 1.3011479 | AM7: =IF(A7="","",(IF(OR(AK7="Single",AK7="Married Filing Separately"),'CONSTANTS & REFERENCES'!$B$13,IF(AK7="Married Filing Jointly",'CONSTANTS & REFERENCES'!$G$13,IF(AK7="Head of Household",'CONSTANTS & REFERENCES'!$L$13,""))))*AL7) -> 41896.962 | AN7: =IF(AM7="","",IF(A7=0,IF(OR(AK7="Single",AK7="Married Filing Separately"),'CONSTANTS & REFERENCES'!$B$13,IF(AK7="Married Filing Jointly",'CONSTANTS & REFERENCES'!$G$13,IF(AK7="Head of Household",'CONSTANTS & REFERENCES'!$L$13,""))),_xlfn.FLOOR.MATH(AM7,IF(AK7="Married Filing Separately",Bracket_Round_MFS,Bracket_Round_Standard)))) -> 41850 | AO7: =IF(A7="","",(IF(OR(AK7="Single",AK7="Married Filing Separately"),'CONSTANTS & REFERENCES'!$C$5,IF(AK7="Married Filing Jointly",'CONSTANTS & REFERENCES'!$H$5,IF(AK7="Head of Household",'CONSTANTS & REFERENCES'!$M$5,""))))*AL7) -> 32268.468 | AP7: =IF(AO7="","",IF(A7=0,IF(OR(AK7="Single",AK7="Married Filing Separately"),'CONSTANTS & REFERENCES'!$C$5,IF(AK7="Married Filing Jointly",'CONSTANTS & REFERENCES'!$H$5,IF(AK7="Head of Household",'CONSTANTS & REFERENCES'!$M$5,""))),_xlfn.FLOOR.MATH(AO7,IF(AK7="Married Filing Separately",Bracket_Round_MFS,Bracket_Round_Standard)))) -> 32250 | AQ7: =IF(A7="","",(IF(OR(AK7="Single",AK7="Married Filing Separately"),'CONSTANTS & REFERENCES'!$C$6,IF(AK7="Married Filing Jointly",'CONSTANTS & REFERENCES'!$H$6,IF(AK7="Head of Household",'CONSTANTS & REFERENCES'!$M$6,""))))*AL7) -> 131155.71 | AR7: =IF(AQ7="","",IF(A7=0,IF(OR(AK7="Single",AK7="Married Filing Separately"),'CONSTANTS & REFERENCES'!$C$6,IF(AK7="Married Filing Jointly",'CONSTANTS & REFERENCES'!$H$6,IF(AK7="Head of Household",'CONSTANTS & REFERENCES'!$M$6,""))),_xlfn.FLOOR.MATH(AQ7,IF(AK7="Married Filing Separately",Bracket_Round_MFS,Bracket_Round_Standard)))) -> 131150 | AS7: =IF(A7="","",(IF(OR(AK7="Single",AK7="Married Filing Separately"),'CONSTANTS & REFERENCES'!$C$7,IF(AK7="Married Filing Jointly",'CONSTANTS & REFERENCES'!$H$7,IF(AK7="Head of Household",'CONSTANTS & REFERENCES'!$M$7,""))))*AL7) -> 275062.67 | AT7: =IF(AS7="","",IF(A7=0,IF(OR(AK7="Single",AK7="Married Filing Separately"),'CONSTANTS & REFERENCES'!$C$7,IF(AK7="Married Filing Jointly",'CONSTANTS & REFERENCES'!$H$7,IF(AK7="Head of Household",'CONSTANTS & REFERENCES'!$M$7,""))),_xlfn.FLOOR.MATH(AS7,IF(AK7="Married Filing Separately",Bracket_Round_MFS,Bracket_Round_Standard)))) -> 275050 | AU7: =IF(A7="","",(IF(OR(AK7="Single",AK7="Married Filing Separately"),'CONSTANTS & REFERENCES'!$C$8,IF(AK7="Married Filing Jointly",'CONSTANTS & REFERENCES'!$H$8,IF(AK7="Head of Household",'CONSTANTS & REFERENCES'!$M$8,""))))*AL7) -> 525078.23 | AV7: =IF(AU7="","",IF(A7=0,IF(OR(AK7="Single",AK7="Married Filing Separately"),'CONSTANTS & REFERENCES'!$C$8,IF(AK7="Married Filing Jointly",'CONSTANTS & REFERENCES'!$H$8,IF(AK7="Head of Household",'CONSTANTS & REFERENCES'!$M$8,""))),_xlfn.FLOOR.MATH(AU7,IF(AK7="Married Filing Separately",Bracket_Round_MFS,Bracket_Round_Standard)))) -> 525050 | AW7: =IF(A7="","",(IF(OR(AK7="Single",AK7="Married Filing Separately"),'CONSTANTS & REFERENCES'!$C$9,IF(AK7="Married Filing Jointly",'CONSTANTS & REFERENCES'!$H$9,IF(AK7="Head of Household",'CONSTANTS & REFERENCES'!$M$9,""))))*AL7) -> 666773.24 | AX7: =IF(AW7="","",IF(A7=0,IF(OR(AK7="Single",AK7="Married Filing Separately"),'CONSTANTS & REFERENCES'!$C$9,IF(AK7="Married Filing Jointly",'CONSTANTS & REFERENCES'!$H$9,IF(AK7="Head of Household",'CONSTANTS & REFERENCES'!$M$9,""))),_xlfn.FLOOR.MATH(AW7,IF(AK7="Married Filing Separately",Bracket_Round_MFS,Bracket_Round_Standard)))) -> 666750 | AY7: =IF(A7="","",(IF(OR(AK7="Single",AK7="Married Filing Separately"),'CONSTANTS & REFERENCES'!$C$10,IF(AK7="Married Filing Jointly",'CONSTANTS & REFERENCES'!$H$10,IF(AK7="Head of Household",'CONSTANTS & REFERENCES'!$M$10,""))))*AL7) -> 1000062.3 | AZ7: =IF(AY7="","",IF(A7=0,IF(OR(AK7="Single",AK7="Married Filing Separately"),'CONSTANTS & REFERENCES'!$C$10,IF(AK7="Married Filing Jointly",'CONSTANTS & REFERENCES'!$H$10,IF(AK7="Head of Household",'CONSTANTS & REFERENCES'!$M$10,""))),_xlfn.FLOOR.MATH(AY7,IF(AK7="Married Filing Separately",Bracket_Round_MFS,Bracket_Round_Standard)))) -> 1000050 | BA7: =IF(A7="","",IF(A7=0,"Official 2026 base values","Illustrative future tax assumptions under simplified C-CPI-U indexing; not an IRS forecast.")) -> Illustrative future tax assumptions under simplified C-CPI-U indexing; not an IRS forecast. | BB7: =IF(A7="","",'CONSTANTS & REFERENCES'!$C$22*AL7) -> 240061.79 | BC7: =IF(BB7="","",_xlfn.FLOOR.MATH(BB7,100)) -> 240000
A8: =IF(A7<INPUTS!$C$7-INPUTS!$C$6,A7+1,"") -> 6 | B8: =IF(A8="","",INPUTS!$C$6+A8) -> 28 | C8: =IF(A8="","",L7) -> 70281.833 | D8: =IF(A8="","",IF(A8<INPUTS!$C$13,0,J8)) -> 10500 | E8: =IF(A8="","",IF(D8=0,"—",IF(Y8<IF(AK8="Married Filing Jointly",'CONSTANTS & REFERENCES'!$B$44,IF(AK8="Married Filing Separately",'CONSTANTS & REFERENCES'!$B$45,'CONSTANTS & REFERENCES'!$B$43)),"Direct","Backdoor"))) -> Direct | F8: =IF(A8="","",$X$2*(1+$X$3)^A8) -> 10638.893 | G8: =IF(F8="","",_xlfn.FLOOR.MATH(F8,500)) -> 10500 | H8: =IF(A8="","",$X$4*(1+$X$3)^A8) -> 1560.371 | I8: =IF(H8="","",_xlfn.FLOOR.MATH(H8,100)) -> 1500 | J8: =IF(A8="","",G8+IF(B8>=50,I8,0)) -> 10500 | K8: =IF(A8="","",IF(INPUTS!$C$12="Beginning",(C8+D8)*INPUTS!$C$10,C8*INPUTS!$C$10)) -> 8078.1833 | L8: =IF(A8="","",IF(INPUTS!$C$12="Beginning",(C8+D8)*(1+INPUTS!$C$10),C8*(1+INPUTS!$C$10)+D8)) -> 88860.016 | M8: =IF(A8="","",(1+INPUTS!$C$11)^A8) -> 1.4185191 | N8: =IF(A8="","",L8/M8) -> 62642.805 | O8: =IF(A8="","",O7+D8) -> 61000 | P8: =IF(A8="","",L8-INPUTS!$C$8-O8) -> 27860.016 | S8: =IF(B8="","",B8) -> 28 | T8: =IF(L8="","",L8) -> 88860.016 | U8: =IF(N8="","",N8) -> 62642.805 | V8: =IF(A8="","",FV(INPUTS!$C$10,INPUTS!$C$7-INPUTS!$C$6-A8+IF(INPUTS!$C$12="Beginning",1,0),0,-D8,0)) -> 392745.61 | Y8: =IF(A8="","",IF(INPUTS!$C$17="Yes",MIN(Y7*(1+INPUTS!$C$15)+IF(INPUTS!$C$27="Yes",(Z8-Z7)*INPUTS!$C$31+IF(AND(INPUTS!$C$28="Not yet credentialed",A8=INPUTS!$C$33),INPUTS!$C$32,0)+IF(AND(INPUTS!$C$28<>"FSA / FCAS",A8=INPUTS!$C$35),INPUTS!$C$34,0),0),INPUTS!$C$18),Y7*(1+INPUTS!$C$15)+IF(INPUTS!$C$27="Yes",(Z8-Z7)*INPUTS!$C$31+IF(AND(INPUTS!$C$28="Not yet credentialed",A8=INPUTS!$C$33),INPUTS!$C$32,0)+IF(AND(INPUTS!$C$28<>"FSA / FCAS",A8=INPUTS!$C$35),INPUTS!$C$34,0),0))) -> 109483.58 | Z8: =IF(A8="","",IF(AND(INPUTS!$C$27="Yes",INPUTS!$C$28<>"FSA / FCAS",ISNUMBER(INPUTS!$C$37)),MIN(A8*INPUTS!$C$37,INPUTS!$C$30),0)) -> 3 | AA8: =IF(A8="","",AN8) -> 44150 | AB8: =IF(OR(A8="",AA8=""),"",MAX(0,Y8-AA8)) -> 65333.583 | AC8: =IF(A8="","",MIN(AB8,AP8)*'CONSTANTS & REFERENCES'!$A$5+MAX(MIN(AB8,AR8)-AP8,0)*'CONSTANTS & REFERENCES'!$A$6+MAX(MIN(AB8,AT8)-AR8,0)*'CONSTANTS & REFERENCES'!$A$7+MAX(MIN(AB8,AV8)-AT8,0)*'CONSTANTS & REFERENCES'!$A$8+MAX(MIN(AB8,AX8)-AV8,0)*'CONSTANTS & REFERENCES'!$A$9+MAX(MIN(AB8,AZ8)-AX8,0)*'CONSTANTS & REFERENCES'!$A$10+MAX(AB8-AZ8,0)*'CONSTANTS & REFERENCES'!$A$11) -> 7160.03 | AD8: =IF(AB8="","",IF(INPUTS!$C$20="Yes",AB8*INPUTS!$C$21,0)) -> 0 | AE8: =IF(Y8="","",MIN(Y8,BC8)*'CONSTANTS & REFERENCES'!$B$22) -> 6787.9821 | AF8: =IF(Y8="","",Y8*'CONSTANTS & REFERENCES'!$B$24+MAX(0,Y8-IF(AK8="Married Filing Jointly",'CONSTANTS & REFERENCES'!$C$26,IF(AK8="Married Filing Separately",'CONSTANTS & REFERENCES'!$C$27,IF(AK8="Head of Household",'CONSTANTS & REFERENCES'!$C$28,'CONSTANTS & REFERENCES'!$C$25))))*'CONSTANTS & REFERENCES'!$B$25) -> 1587.512 | AG8: =IF(Y8="","",AE8+AF8) -> 8375.4941 | AH8: =IF(OR(AC8="",AG8=""),"",AC8+AD8+AG8) -> 15535.524 | AI8: =IF(AH8="","",Y8-AH8) -> 93948.059 | AJ8: =IF(AI8="","",Y8-AH8-AI8) -> 0 | AK8: =IF(A8="","",IF(AND(INPUTS!$C$43="Yes",A8>=INPUTS!$C$45),INPUTS!$C$44,INPUTS!$C$19)) -> Married Filing Jointly | AL8: =IF(A8="","",(1+$X$6)^A8) -> 1.371488 | AM8: =IF(A8="","",(IF(OR(AK8="Single",AK8="Married Filing Separately"),'CONSTANTS & REFERENCES'!$B$13,IF(AK8="Married Filing Jointly",'CONSTANTS & REFERENCES'!$G$13,IF(AK8="Head of Household",'CONSTANTS & REFERENCES'!$L$13,""))))*AL8) -> 44161.912 | AN8: =IF(AM8="","",IF(A8=0,IF(OR(AK8="Single",AK8="Married Filing Separately"),'CONSTANTS & REFERENCES'!$B$13,IF(AK8="Married Filing Jointly",'CONSTANTS & REFERENCES'!$G$13,IF(AK8="Head of Household",'CONSTANTS & REFERENCES'!$L$13,""))),_xlfn.FLOOR.MATH(AM8,IF(AK8="Married Filing Separately",Bracket_Round_MFS,Bracket_Round_Standard)))) -> 44150 | AO8: =IF(A8="","",(IF(OR(AK8="Single",AK8="Married Filing Separately"),'CONSTANTS & REFERENCES'!$C$5,IF(AK8="Married Filing Jointly",'CONSTANTS & REFERENCES'!$H$5,IF(AK8="Head of Household",'CONSTANTS & REFERENCES'!$M$5,""))))*AL8) -> 34012.901 | AP8: =IF(AO8="","",IF(A8=0,IF(OR(AK8="Single",AK8="Married Filing Separately"),'CONSTANTS & REFERENCES'!$C$5,IF(AK8="Married Filing Jointly",'CONSTANTS & REFERENCES'!$H$5,IF(AK8="Head of Household",'CONSTANTS & REFERENCES'!$M$5,""))),_xlfn.FLOOR.MATH(AO8,IF(AK8="Married Filing Separately",Bracket_Round_MFS,Bracket_Round_Standard)))) -> 34000 | AQ8: =IF(A8="","",(IF(OR(AK8="Single",AK8="Married Filing Separately"),'CONSTANTS & REFERENCES'!$C$6,IF(AK8="Married Filing Jointly",'CONSTANTS & REFERENCES'!$H$6,IF(AK8="Head of Household",'CONSTANTS & REFERENCES'!$M$6,""))))*AL8) -> 138245.99 | AR8: =IF(AQ8="","",IF(A8=0,IF(OR(AK8="Single",AK8="Married Filing Separately"),'CONSTANTS & REFERENCES'!$C$6,IF(AK8="Married Filing Jointly",'CONSTANTS & REFERENCES'!$H$6,IF(AK8="Head of Household",'CONSTANTS & REFERENCES'!$M$6,""))),_xlfn.FLOOR.MATH(AQ8,IF(AK8="Married Filing Separately",Bracket_Round_MFS,Bracket_Round_Standard)))) -> 138200 | AS8: =IF(A8="","",(IF(OR(AK8="Single",AK8="Married Filing Separately"),'CONSTANTS & REFERENCES'!$C$7,IF(AK8="Married Filing Jointly",'CONSTANTS & REFERENCES'!$H$7,IF(AK8="Head of Household",'CONSTANTS & REFERENCES'!$M$7,""))))*AL8) -> 289932.55 | AT8: =IF(AS8="","",IF(A8=0,IF(OR(AK8="Single",AK8="Married Filing Separately"),'CONSTANTS & REFERENCES'!$C$7,IF(AK8="Married Filing Jointly",'CONSTANTS & REFERENCES'!$H$7,IF(AK8="Head of Household",'CONSTANTS & REFERENCES'!$M$7,""))),_xlfn.FLOOR.MATH(AS8,IF(AK8="Married Filing Separately",Bracket_Round_MFS,Bracket_Round_Standard)))) -> 289900 | AU8: =IF(A8="","",(IF(OR(AK8="Single",AK8="Married Filing Separately"),'CONSTANTS & REFERENCES'!$C$8,IF(AK8="Married Filing Jointly",'CONSTANTS & REFERENCES'!$H$8,IF(AK8="Head of Household",'CONSTANTS & REFERENCES'!$M$8,""))))*AL8) -> 553463.96 | AV8: =IF(AU8="","",IF(A8=0,IF(OR(AK8="Single",AK8="Married Filing Separately"),'CONSTANTS & REFERENCES'!$C$8,IF(AK8="Married Filing Jointly",'CONSTANTS & REFERENCES'!$H$8,IF(AK8="Head of Household",'CONSTANTS & REFERENCES'!$M$8,""))),_xlfn.FLOOR.MATH(AU8,IF(AK8="Married Filing Separately",Bracket_Round_MFS,Bracket_Round_Standard)))) -> 553450 | AW8: =IF(A8="","",(IF(OR(AK8="Single",AK8="Married Filing Separately"),'CONSTANTS & REFERENCES'!$C$9,IF(AK8="Married Filing Jointly",'CONSTANTS & REFERENCES'!$H$9,IF(AK8="Head of Household",'CONSTANTS & REFERENCES'!$M$9,""))))*AL8) -> 702819 | AX8: =IF(AW8="","",IF(A8=0,IF(OR(AK8="Single",AK8="Married Filing Separately"),'CONSTANTS & REFERENCES'!$C$9,IF(AK8="Married Filing Jointly",'CONSTANTS & REFERENCES'!$H$9,IF(AK8="Head of Household",'CONSTANTS & REFERENCES'!$M$9,""))),_xlfn.FLOOR.MATH(AW8,IF(AK8="Married Filing Separately",Bracket_Round_MFS,Bracket_Round_Standard)))) -> 702800 | AY8: =IF(A8="","",(IF(OR(AK8="Single",AK8="Married Filing Separately"),'CONSTANTS & REFERENCES'!$C$10,IF(AK8="Married Filing Jointly",'CONSTANTS & REFERENCES'!$H$10,IF(AK8="Head of Household",'CONSTANTS & REFERENCES'!$M$10,""))))*AL8) -> 1054125.6 | AZ8: =IF(AY8="","",IF(A8=0,IF(OR(AK8="Single",AK8="Married Filing Separately"),'CONSTANTS & REFERENCES'!$C$10,IF(AK8="Married Filing Jointly",'CONSTANTS & REFERENCES'!$H$10,IF(AK8="Head of Household",'CONSTANTS & REFERENCES'!$M$10,""))),_xlfn.FLOOR.MATH(AY8,IF(AK8="Married Filing Separately",Bracket_Round_MFS,Bracket_Round_Standard)))) -> 1054100 | BA8: =IF(A8="","",IF(A8=0,"Official 2026 base values","Illustrative future tax assumptions under simplified C-CPI-U indexing; not an IRS forecast.")) -> Illustrative future tax assumptions under simplified C-CPI-U indexing; not an IRS forecast. | BB8: =IF(A8="","",'CONSTANTS & REFERENCES'!$C$22*AL8) -> 253039.53 | BC8: =IF(BB8="","",_xlfn.FLOOR.MATH(BB8,100)) -> 253000
A9: =IF(A8<INPUTS!$C$7-INPUTS!$C$6,A8+1,"") -> 7 | B9: =IF(A9="","",INPUTS!$C$6+A9) -> 29 | C9: =IF(A9="","",L8) -> 88860.016 | D9: =IF(A9="","",IF(A9<INPUTS!$C$13,0,J9)) -> 11000 | E9: =IF(A9="","",IF(D9=0,"—",IF(Y9<IF(AK9="Married Filing Jointly",'CONSTANTS & REFERENCES'!$B$44,IF(AK9="Married Filing Separately",'CONSTANTS & REFERENCES'!$B$45,'CONSTANTS & REFERENCES'!$B$43)),"Direct","Backdoor"))) -> Direct | F9: =IF(A9="","",$X$2*(1+$X$3)^A9) -> 11277.227 | G9: =IF(F9="","",_xlfn.FLOOR.MATH(F9,500)) -> 11000 | H9: =IF(A9="","",$X$4*(1+$X$3)^A9) -> 1653.9933 | I9: =IF(H9="","",_xlfn.FLOOR.MATH(H9,100)) -> 1600 | J9: =IF(A9="","",G9+IF(B9>=50,I9,0)) -> 11000 | K9: =IF(A9="","",IF(INPUTS!$C$12="Beginning",(C9+D9)*INPUTS!$C$10,C9*INPUTS!$C$10)) -> 9986.0016 | L9: =IF(A9="","",IF(INPUTS!$C$12="Beginning",(C9+D9)*(1+INPUTS!$C$10),C9*(1+INPUTS!$C$10)+D9)) -> 109846.02 | M9: =IF(A9="","",(1+INPUTS!$C$11)^A9) -> 1.5036303 | N9: =IF(A9="","",L9/M9) -> 73053.875 | O9: =IF(A9="","",O8+D9) -> 72000 | P9: =IF(A9="","",L9-INPUTS!$C$8-O9) -> 37846.017 | S9: =IF(B9="","",B9) -> 29 | T9: =IF(L9="","",L9) -> 109846.02 | U9: =IF(N9="","",N9) -> 73053.875 | V9: =IF(A9="","",FV(INPUTS!$C$10,INPUTS!$C$7-INPUTS!$C$6-A9+IF(INPUTS!$C$12="Beginning",1,0),0,-D9,0)) -> 374043.43 | Y9: =IF(A9="","",IF(INPUTS!$C$17="Yes",MIN(Y8*(1+INPUTS!$C$15)+IF(INPUTS!$C$27="Yes",(Z9-Z8)*INPUTS!$C$31+IF(AND(INPUTS!$C$28="Not yet credentialed",A9=INPUTS!$C$33),INPUTS!$C$32,0)+IF(AND(INPUTS!$C$28<>"FSA / FCAS",A9=INPUTS!$C$35),INPUTS!$C$34,0),0),INPUTS!$C$18),Y8*(1+INPUTS!$C$15)+IF(INPUTS!$C$27="Yes",(Z9-Z8)*INPUTS!$C$31+IF(AND(INPUTS!$C$28="Not yet credentialed",A9=INPUTS!$C$33),INPUTS!$C$32,0)+IF(AND(INPUTS!$C$28<>"FSA / FCAS",A9=INPUTS!$C$35),INPUTS!$C$34,0),0))) -> 112768.09 | Z9: =IF(A9="","",IF(AND(INPUTS!$C$27="Yes",INPUTS!$C$28<>"FSA / FCAS",ISNUMBER(INPUTS!$C$37)),MIN(A9*INPUTS!$C$37,INPUTS!$C$30),0)) -> 3 | AA9: =IF(A9="","",AN9) -> 46500 | AB9: =IF(OR(A9="",AA9=""),"",MAX(0,Y9-AA9)) -> 66268.09 | AC9: =IF(A9="","",MIN(AB9,AP9)*'CONSTANTS & REFERENCES'!$A$5+MAX(MIN(AB9,AR9)-AP9,0)*'CONSTANTS & REFERENCES'!$A$6+MAX(MIN(AB9,AT9)-AR9,0)*'CONSTANTS & REFERENCES'!$A$7+MAX(MIN(AB9,AV9)-AT9,0)*'CONSTANTS & REFERENCES'!$A$8+MAX(MIN(AB9,AX9)-AV9,0)*'CONSTANTS & REFERENCES'!$A$9+MAX(MIN(AB9,AZ9)-AX9,0)*'CONSTANTS & REFERENCES'!$A$10+MAX(AB9-AZ9,0)*'CONSTANTS & REFERENCES'!$A$11) -> 7235.1709 | AD9: =IF(AB9="","",IF(INPUTS!$C$20="Yes",AB9*INPUTS!$C$21,0)) -> 0 | AE9: =IF(Y9="","",MIN(Y9,BC9)*'CONSTANTS & REFERENCES'!$B$22) -> 6991.6216 | AF9: =IF(Y9="","",Y9*'CONSTANTS & REFERENCES'!$B$24+MAX(0,Y9-IF(AK9="Married Filing Jointly",'CONSTANTS & REFERENCES'!$C$26,IF(AK9="Married Filing Separately",'CONSTANTS & REFERENCES'!$C$27,IF(AK9="Head of Household",'CONSTANTS & REFERENCES'!$C$28,'CONSTANTS & REFERENCES'!$C$25))))*'CONSTANTS & REFERENCES'!$B$25) -> 1635.1373 | AG9: =IF(Y9="","",AE9+AF9) -> 8626.7589 | AH9: =IF(OR(AC9="",AG9=""),"",AC9+AD9+AG9) -> 15861.93 | AI9: =IF(AH9="","",Y9-AH9) -> 96906.161 | AJ9: =IF(AI9="","",Y9-AH9-AI9) -> 0 | AK9: =IF(A9="","",IF(AND(INPUTS!$C$43="Yes",A9>=INPUTS!$C$45),INPUTS!$C$44,INPUTS!$C$19)) -> Married Filing Jointly | AL9: =IF(A9="","",(1+$X$6)^A9) -> 1.4456306 | AM9: =IF(A9="","",(IF(OR(AK9="Single",AK9="Married Filing Separately"),'CONSTANTS & REFERENCES'!$B$13,IF(AK9="Married Filing Jointly",'CONSTANTS & REFERENCES'!$G$13,IF(AK9="Head of Household",'CONSTANTS & REFERENCES'!$L$13,""))))*AL9) -> 46549.305 | AN9: =IF(AM9="","",IF(A9=0,IF(OR(AK9="Single",AK9="Married Filing Separately"),'CONSTANTS & REFERENCES'!$B$13,IF(AK9="Married Filing Jointly",'CONSTANTS & REFERENCES'!$G$13,IF(AK9="Head of Household",'CONSTANTS & REFERENCES'!$L$13,""))),_xlfn.FLOOR.MATH(AM9,IF(AK9="Married Filing Separately",Bracket_Round_MFS,Bracket_Round_Standard)))) -> 46500 | AO9: =IF(A9="","",(IF(OR(AK9="Single",AK9="Married Filing Separately"),'CONSTANTS & REFERENCES'!$C$5,IF(AK9="Married Filing Jointly",'CONSTANTS & REFERENCES'!$H$5,IF(AK9="Head of Household",'CONSTANTS & REFERENCES'!$M$5,""))))*AL9) -> 35851.639 | AP9: =IF(AO9="","",IF(A9=0,IF(OR(AK9="Single",AK9="Married Filing Separately"),'CONSTANTS & REFERENCES'!$C$5,IF(AK9="Married Filing Jointly",'CONSTANTS & REFERENCES'!$H$5,IF(AK9="Head of Household",'CONSTANTS & REFERENCES'!$M$5,""))),_xlfn.FLOOR.MATH(AO9,IF(AK9="Married Filing Separately",Bracket_Round_MFS,Bracket_Round_Standard)))) -> 35850 | AQ9: =IF(A9="","",(IF(OR(AK9="Single",AK9="Married Filing Separately"),'CONSTANTS & REFERENCES'!$C$6,IF(AK9="Married Filing Jointly",'CONSTANTS & REFERENCES'!$H$6,IF(AK9="Head of Household",'CONSTANTS & REFERENCES'!$M$6,""))))*AL9) -> 145719.56 | AR9: =IF(AQ9="","",IF(A9=0,IF(OR(AK9="Single",AK9="Married Filing Separately"),'CONSTANTS & REFERENCES'!$C$6,IF(AK9="Married Filing Jointly",'CONSTANTS & REFERENCES'!$H$6,IF(AK9="Head of Household",'CONSTANTS & REFERENCES'!$M$6,""))),_xlfn.FLOOR.MATH(AQ9,IF(AK9="Married Filing Separately",Bracket_Round_MFS,Bracket_Round_Standard)))) -> 145700 | AS9: =IF(A9="","",(IF(OR(AK9="Single",AK9="Married Filing Separately"),'CONSTANTS & REFERENCES'!$C$7,IF(AK9="Married Filing Jointly",'CONSTANTS & REFERENCES'!$H$7,IF(AK9="Head of Household",'CONSTANTS & REFERENCES'!$M$7,""))))*AL9) -> 305606.31 | AT9: =IF(AS9="","",IF(A9=0,IF(OR(AK9="Single",AK9="Married Filing Separately"),'CONSTANTS & REFERENCES'!$C$7,IF(AK9="Married Filing Jointly",'CONSTANTS & REFERENCES'!$H$7,IF(AK9="Head of Household",'CONSTANTS & REFERENCES'!$M$7,""))),_xlfn.FLOOR.MATH(AS9,IF(AK9="Married Filing Separately",Bracket_Round_MFS,Bracket_Round_Standard)))) -> 305600 | AU9: =IF(A9="","",(IF(OR(AK9="Single",AK9="Married Filing Separately"),'CONSTANTS & REFERENCES'!$C$8,IF(AK9="Married Filing Jointly",'CONSTANTS & REFERENCES'!$H$8,IF(AK9="Head of Household",'CONSTANTS & REFERENCES'!$M$8,""))))*AL9) -> 583384.22 | AV9: =IF(AU9="","",IF(A9=0,IF(OR(AK9="Single",AK9="Married Filing Separately"),'CONSTANTS & REFERENCES'!$C$8,IF(AK9="Married Filing Jointly",'CONSTANTS & REFERENCES'!$H$8,IF(AK9="Head of Household",'CONSTANTS & REFERENCES'!$M$8,""))),_xlfn.FLOOR.MATH(AU9,IF(AK9="Married Filing Separately",Bracket_Round_MFS,Bracket_Round_Standard)))) -> 583350 | AW9: =IF(A9="","",(IF(OR(AK9="Single",AK9="Married Filing Separately"),'CONSTANTS & REFERENCES'!$C$9,IF(AK9="Married Filing Jointly",'CONSTANTS & REFERENCES'!$H$9,IF(AK9="Head of Household",'CONSTANTS & REFERENCES'!$M$9,""))))*AL9) -> 740813.4 | AX9: =IF(AW9="","",IF(A9=0,IF(OR(AK9="Single",AK9="Married Filing Separately"),'CONSTANTS & REFERENCES'!$C$9,IF(AK9="Married Filing Jointly",'CONSTANTS & REFERENCES'!$H$9,IF(AK9="Head of Household",'CONSTANTS & REFERENCES'!$M$9,""))),_xlfn.FLOOR.MATH(AW9,IF(AK9="Married Filing Separately",Bracket_Round_MFS,Bracket_Round_Standard)))) -> 740800 | AY9: =IF(A9="","",(IF(OR(AK9="Single",AK9="Married Filing Separately"),'CONSTANTS & REFERENCES'!$C$10,IF(AK9="Married Filing Jointly",'CONSTANTS & REFERENCES'!$H$10,IF(AK9="Head of Household",'CONSTANTS & REFERENCES'!$M$10,""))))*AL9) -> 1111111.7 | AZ9: =IF(AY9="","",IF(A9=0,IF(OR(AK9="Single",AK9="Married Filing Separately"),'CONSTANTS & REFERENCES'!$C$10,IF(AK9="Married Filing Jointly",'CONSTANTS & REFERENCES'!$H$10,IF(AK9="Head of Household",'CONSTANTS & REFERENCES'!$M$10,""))),_xlfn.FLOOR.MATH(AY9,IF(AK9="Married Filing Separately",Bracket_Round_MFS,Bracket_Round_Standard)))) -> 1111100 | BA9: =IF(A9="","",IF(A9=0,"Official 2026 base values","Illustrative future tax assumptions under simplified C-CPI-U indexing; not an IRS forecast.")) -> Illustrative future tax assumptions under simplified C-CPI-U indexing; not an IRS forecast. | BB9: =IF(A9="","",'CONSTANTS & REFERENCES'!$C$22*AL9) -> 266718.84 | BC9: =IF(BB9="","",_xlfn.FLOOR.MATH(BB9,100)) -> 266700
A10: =IF(A9<INPUTS!$C$7-INPUTS!$C$6,A9+1,"") -> 8 | B10: =IF(A10="","",INPUTS!$C$6+A10) -> 30 | C10: =IF(A10="","",L9) -> 109846.02 | D10: =IF(A10="","",IF(A10<INPUTS!$C$13,0,J10)) -> 11500 | E10: =IF(A10="","",IF(D10=0,"—",IF(Y10<IF(AK10="Married Filing Jointly",'CONSTANTS & REFERENCES'!$B$44,IF(AK10="Married Filing Separately",'CONSTANTS & REFERENCES'!$B$45,'CONSTANTS & REFERENCES'!$B$43)),"Direct","Backdoor"))) -> Direct | F10: =IF(A10="","",$X$2*(1+$X$3)^A10) -> 11953.861 | G10: =IF(F10="","",_xlfn.FLOOR.MATH(F10,500)) -> 11500 | H10: =IF(A10="","",$X$4*(1+$X$3)^A10) -> 1753.2329 | I10: =IF(H10="","",_xlfn.FLOOR.MATH(H10,100)) -> 1700 | J10: =IF(A10="","",G10+IF(B10>=50,I10,0)) -> 11500 | K10: =IF(A10="","",IF(INPUTS!$C$12="Beginning",(C10+D10)*INPUTS!$C$10,C10*INPUTS!$C$10)) -> 12134.602 | L10: =IF(A10="","",IF(INPUTS!$C$12="Beginning",(C10+D10)*(1+INPUTS!$C$10),C10*(1+INPUTS!$C$10)+D10)) -> 133480.62 | M10: =IF(A10="","",(1+INPUTS!$C$11)^A10) -> 1.5938481 | N10: =IF(A10="","",L10/M10) -> 83747.392 | O10: =IF(A10="","",O9+D10) -> 83500 | P10: =IF(A10="","",L10-INPUTS!$C$8-O10) -> 49980.619 | S10: =IF(B10="","",B10) -> 30 | T10: =IF(L10="","",L10) -> 133480.62 | U10: =IF(N10="","",N10) -> 83747.392 | V10: =IF(A10="","",FV(INPUTS!$C$10,INPUTS!$C$7-INPUTS!$C$6-A10+IF(INPUTS!$C$12="Beginning",1,0),0,-D10,0)) -> 355495.83 | Y10: =IF(A10="","",IF(INPUTS!$C$17="Yes",MIN(Y9*(1+INPUTS!$C$15)+IF(INPUTS!$C$27="Yes",(Z10-Z9)*INPUTS!$C$31+IF(AND(INPUTS!$C$28="Not yet credentialed",A10=INPUTS!$C$33),INPUTS!$C$32,0)+IF(AND(INPUTS!$C$28<>"FSA / FCAS",A10=INPUTS!$C$35),INPUTS!$C$34,0),0),INPUTS!$C$18),Y9*(1+INPUTS!$C$15)+IF(INPUTS!$C$27="Yes",(Z10-Z9)*INPUTS!$C$31+IF(AND(INPUTS!$C$28="Not yet credentialed",A10=INPUTS!$C$33),INPUTS!$C$32,0)+IF(AND(INPUTS!$C$28<>"FSA / FCAS",A10=INPUTS!$C$35),INPUTS!$C$34,0),0))) -> 116151.13 | Z10: =IF(A10="","",IF(AND(INPUTS!$C$27="Yes",INPUTS!$C$28<>"FSA / FCAS",ISNUMBER(INPUTS!$C$37)),MIN(A10*INPUTS!$C$37,INPUTS!$C$30),0)) -> 3 | AA10: =IF(A10="","",AN10) -> 49050 | AB10: =IF(OR(A10="",AA10=""),"",MAX(0,Y10-AA10)) -> 67101.133 | AC10: =IF(A10="","",MIN(AB10,AP10)*'CONSTANTS & REFERENCES'!$A$5+MAX(MIN(AB10,AR10)-AP10,0)*'CONSTANTS & REFERENCES'!$A$6+MAX(MIN(AB10,AT10)-AR10,0)*'CONSTANTS & REFERENCES'!$A$7+MAX(MIN(AB10,AV10)-AT10,0)*'CONSTANTS & REFERENCES'!$A$8+MAX(MIN(AB10,AX10)-AV10,0)*'CONSTANTS & REFERENCES'!$A$9+MAX(MIN(AB10,AZ10)-AX10,0)*'CONSTANTS & REFERENCES'!$A$10+MAX(AB10-AZ10,0)*'CONSTANTS & REFERENCES'!$A$11) -> 7297.136 | AD10: =IF(AB10="","",IF(INPUTS!$C$20="Yes",AB10*INPUTS!$C$21,0)) -> 0 | AE10: =IF(Y10="","",MIN(Y10,BC10)*'CONSTANTS & REFERENCES'!$B$22) -> 7201.3703 | AF10: =IF(Y10="","",Y10*'CONSTANTS & REFERENCES'!$B$24+MAX(0,Y10-IF(AK10="Married Filing Jointly",'CONSTANTS & REFERENCES'!$C$26,IF(AK10="Married Filing Separately",'CONSTANTS & REFERENCES'!$C$27,IF(AK10="Head of Household",'CONSTANTS & REFERENCES'!$C$28,'CONSTANTS & REFERENCES'!$C$25))))*'CONSTANTS & REFERENCES'!$B$25) -> 1684.1914 | AG10: =IF(Y10="","",AE10+AF10) -> 8885.5617 | AH10: =IF(OR(AC10="",AG10=""),"",AC10+AD10+AG10) -> 16182.698 | AI10: =IF(AH10="","",Y10-AH10) -> 99968.436 | AJ10: =IF(AI10="","",Y10-AH10-AI10) -> 0 | AK10: =IF(A10="","",IF(AND(INPUTS!$C$43="Yes",A10>=INPUTS!$C$45),INPUTS!$C$44,INPUTS!$C$19)) -> Married Filing Jointly | AL10: =IF(A10="","",(1+$X$6)^A10) -> 1.5237814 | AM10: =IF(A10="","",(IF(OR(AK10="Single",AK10="Married Filing Separately"),'CONSTANTS & REFERENCES'!$B$13,IF(AK10="Married Filing Jointly",'CONSTANTS & REFERENCES'!$G$13,IF(AK10="Head of Household",'CONSTANTS & REFERENCES'!$L$13,""))))*AL10) -> 49065.76 | AN10: =IF(AM10="","",IF(A10=0,IF(OR(AK10="Single",AK10="Married Filing Separately"),'CONSTANTS & REFERENCES'!$B$13,IF(AK10="Married Filing Jointly",'CONSTANTS & REFERENCES'!$G$13,IF(AK10="Head of Household",'CONSTANTS & REFERENCES'!$L$13,""))),_xlfn.FLOOR.MATH(AM10,IF(AK10="Married Filing Separately",Bracket_Round_MFS,Bracket_Round_Standard)))) -> 49050 | AO10: =IF(A10="","",(IF(OR(AK10="Single",AK10="Married Filing Separately"),'CONSTANTS & REFERENCES'!$C$5,IF(AK10="Married Filing Jointly",'CONSTANTS & REFERENCES'!$H$5,IF(AK10="Head of Household",'CONSTANTS & REFERENCES'!$M$5,""))))*AL10) -> 37789.778 | AP10: =IF(AO10="","",IF(A10=0,IF(OR(AK10="Single",AK10="Married Filing Separately"),'CONSTANTS & REFERENCES'!$C$5,IF(AK10="Married Filing Jointly",'CONSTANTS & REFERENCES'!$H$5,IF(AK10="Head of Household",'CONSTANTS & REFERENCES'!$M$5,""))),_xlfn.FLOOR.MATH(AO10,IF(AK10="Married Filing Separately",Bracket_Round_MFS,Bracket_Round_Standard)))) -> 37750 | AQ10: =IF(A10="","",(IF(OR(AK10="Single",AK10="Married Filing Separately"),'CONSTANTS & REFERENCES'!$C$6,IF(AK10="Married Filing Jointly",'CONSTANTS & REFERENCES'!$H$6,IF(AK10="Head of Household",'CONSTANTS & REFERENCES'!$M$6,""))))*AL10) -> 153597.16 | AR10: =IF(AQ10="","",IF(A10=0,IF(OR(AK10="Single",AK10="Married Filing Separately"),'CONSTANTS & REFERENCES'!$C$6,IF(AK10="Married Filing Jointly",'CONSTANTS & REFERENCES'!$H$6,IF(AK10="Head of Household",'CONSTANTS & REFERENCES'!$M$6,""))),_xlfn.FLOOR.MATH(AQ10,IF(AK10="Married Filing Separately",Bracket_Round_MFS,Bracket_Round_Standard)))) -> 153550 | AS10: =IF(A10="","",(IF(OR(AK10="Single",AK10="Married Filing Separately"),'CONSTANTS & REFERENCES'!$C$7,IF(AK10="Married Filing Jointly",'CONSTANTS & REFERENCES'!$H$7,IF(AK10="Head of Household",'CONSTANTS & REFERENCES'!$M$7,""))))*AL10) -> 322127.38 | AT10: =IF(AS10="","",IF(A10=0,IF(OR(AK10="Single",AK10="Married Filing Separately"),'CONSTANTS & REFERENCES'!$C$7,IF(AK10="Married Filing Jointly",'CONSTANTS & REFERENCES'!$H$7,IF(AK10="Head of Household",'CONSTANTS & REFERENCES'!$M$7,""))),_xlfn.FLOOR.MATH(AS10,IF(AK10="Married Filing Separately",Bracket_Round_MFS,Bracket_Round_Standard)))) -> 322100 | AU10: =IF(A10="","",(IF(OR(AK10="Single",AK10="Married Filing Separately"),'CONSTANTS & REFERENCES'!$C$8,IF(AK10="Married Filing Jointly",'CONSTANTS & REFERENCES'!$H$8,IF(AK10="Head of Household",'CONSTANTS & REFERENCES'!$M$8,""))))*AL10) -> 614921.98 | AV10: =IF(AU10="","",IF(A10=0,IF(OR(AK10="Single",AK10="Married Filing Separately"),'CONSTANTS & REFERENCES'!$C$8,IF(AK10="Married Filing Jointly",'CONSTANTS & REFERENCES'!$H$8,IF(AK10="Head of Household",'CONSTANTS & REFERENCES'!$M$8,""))),_xlfn.FLOOR.MATH(AU10,IF(AK10="Married Filing Separately",Bracket_Round_MFS,Bracket_Round_Standard)))) -> 614900 | AW10: =IF(A10="","",(IF(OR(AK10="Single",AK10="Married Filing Separately"),'CONSTANTS & REFERENCES'!$C$9,IF(AK10="Married Filing Jointly",'CONSTANTS & REFERENCES'!$H$9,IF(AK10="Head of Household",'CONSTANTS & REFERENCES'!$M$9,""))))*AL10) -> 780861.77 | AX10: =IF(AW10="","",IF(A10=0,IF(OR(AK10="Single",AK10="Married Filing Separately"),'CONSTANTS & REFERENCES'!$C$9,IF(AK10="Married Filing Jointly",'CONSTANTS & REFERENCES'!$H$9,IF(AK10="Head of Household",'CONSTANTS & REFERENCES'!$M$9,""))),_xlfn.FLOOR.MATH(AW10,IF(AK10="Married Filing Separately",Bracket_Round_MFS,Bracket_Round_Standard)))) -> 780850 | AY10: =IF(A10="","",(IF(OR(AK10="Single",AK10="Married Filing Separately"),'CONSTANTS & REFERENCES'!$C$10,IF(AK10="Married Filing Jointly",'CONSTANTS & REFERENCES'!$H$10,IF(AK10="Head of Household",'CONSTANTS & REFERENCES'!$M$10,""))))*AL10) -> 1171178.4 | AZ10: =IF(AY10="","",IF(A10=0,IF(OR(AK10="Single",AK10="Married Filing Separately"),'CONSTANTS & REFERENCES'!$C$10,IF(AK10="Married Filing Jointly",'CONSTANTS & REFERENCES'!$H$10,IF(AK10="Head of Household",'CONSTANTS & REFERENCES'!$M$10,""))),_xlfn.FLOOR.MATH(AY10,IF(AK10="Married Filing Separately",Bracket_Round_MFS,Bracket_Round_Standard)))) -> 1171150 | BA10: =IF(A10="","",IF(A10=0,"Official 2026 base values","Illustrative future tax assumptions under simplified C-CPI-U indexing; not an IRS forecast.")) -> Illustrative future tax assumptions under simplified C-CPI-U indexing; not an IRS forecast. | BB10: =IF(A10="","",'CONSTANTS & REFERENCES'!$C$22*AL10) -> 281137.66 | BC10: =IF(BB10="","",_xlfn.FLOOR.MATH(BB10,100)) -> 281100
A11: =IF(A10<INPUTS!$C$7-INPUTS!$C$6,A10+1,"") -> 9 | B11: =IF(A11="","",INPUTS!$C$6+A11) -> 31 | C11: =IF(A11="","",L10) -> 133480.62 | D11: =IF(A11="","",IF(A11<INPUTS!$C$13,0,J11)) -> 12500 | E11: =IF(A11="","",IF(D11=0,"—",IF(Y11<IF(AK11="Married Filing Jointly",'CONSTANTS & REFERENCES'!$B$44,IF(AK11="Married Filing Separately",'CONSTANTS & REFERENCES'!$B$45,'CONSTANTS & REFERENCES'!$B$43)),"Direct","Backdoor"))) -> Direct | F11: =IF(A11="","",$X$2*(1+$X$3)^A11) -> 12671.092 | G11: =IF(F11="","",_xlfn.FLOOR.MATH(F11,500)) -> 12500 | H11: =IF(A11="","",$X$4*(1+$X$3)^A11) -> 1858.4269 | I11: =IF(H11="","",_xlfn.FLOOR.MATH(H11,100)) -> 1800 | J11: =IF(A11="","",G11+IF(B11>=50,I11,0)) -> 12500 | K11: =IF(A11="","",IF(INPUTS!$C$12="Beginning",(C11+D11)*INPUTS!$C$10,C11*INPUTS!$C$10)) -> 14598.062 | L11: =IF(A11="","",IF(INPUTS!$C$12="Beginning",(C11+D11)*(1+INPUTS!$C$10),C11*(1+INPUTS!$C$10)+D11)) -> 160578.68 | M11: =IF(A11="","",(1+INPUTS!$C$11)^A11) -> 1.689479 | N11: =IF(A11="","",L11/M11) -> 95046.275 | O11: =IF(A11="","",O10+D11) -> 96000 | P11: =IF(A11="","",L11-INPUTS!$C$8-O11) -> 64578.681 | S11: =IF(B11="","",B11) -> 31 | T11: =IF(L11="","",L11) -> 160578.68 | U11: =IF(N11="","",N11) -> 95046.275 | V11: =IF(A11="","",FV(INPUTS!$C$10,INPUTS!$C$7-INPUTS!$C$6-A11+IF(INPUTS!$C$12="Beginning",1,0),0,-D11,0)) -> 351280.46 | Y11: =IF(A11="","",IF(INPUTS!$C$17="Yes",MIN(Y10*(1+INPUTS!$C$15)+IF(INPUTS!$C$27="Yes",(Z11-Z10)*INPUTS!$C$31+IF(AND(INPUTS!$C$28="Not yet credentialed",A11=INPUTS!$C$33),INPUTS!$C$32,0)+IF(AND(INPUTS!$C$28<>"FSA / FCAS",A11=INPUTS!$C$35),INPUTS!$C$34,0),0),INPUTS!$C$18),Y10*(1+INPUTS!$C$15)+IF(INPUTS!$C$27="Yes",(Z11-Z10)*INPUTS!$C$31+IF(AND(INPUTS!$C$28="Not yet credentialed",A11=INPUTS!$C$33),INPUTS!$C$32,0)+IF(AND(INPUTS!$C$28<>"FSA / FCAS",A11=INPUTS!$C$35),INPUTS!$C$34,0),0))) -> 119635.67 | Z11: =IF(A11="","",IF(AND(INPUTS!$C$27="Yes",INPUTS!$C$28<>"FSA / FCAS",ISNUMBER(INPUTS!$C$37)),MIN(A11*INPUTS!$C$37,INPUTS!$C$30),0)) -> 3 | AA11: =IF(A11="","",AN11) -> 51700 | AB11: =IF(OR(A11="",AA11=""),"",MAX(0,Y11-AA11)) -> 67935.667 | AC11: =IF(A11="","",MIN(AB11,AP11)*'CONSTANTS & REFERENCES'!$A$5+MAX(MIN(AB11,AR11)-AP11,0)*'CONSTANTS & REFERENCES'!$A$6+MAX(MIN(AB11,AT11)-AR11,0)*'CONSTANTS & REFERENCES'!$A$7+MAX(MIN(AB11,AV11)-AT11,0)*'CONSTANTS & REFERENCES'!$A$8+MAX(MIN(AB11,AX11)-AV11,0)*'CONSTANTS & REFERENCES'!$A$9+MAX(MIN(AB11,AZ11)-AX11,0)*'CONSTANTS & REFERENCES'!$A$10+MAX(AB11-AZ11,0)*'CONSTANTS & REFERENCES'!$A$11) -> 7356.2801 | AD11: =IF(AB11="","",IF(INPUTS!$C$20="Yes",AB11*INPUTS!$C$21,0)) -> 0 | AE11: =IF(Y11="","",MIN(Y11,BC11)*'CONSTANTS & REFERENCES'!$B$22) -> 7417.4114 | AF11: =IF(Y11="","",Y11*'CONSTANTS & REFERENCES'!$B$24+MAX(0,Y11-IF(AK11="Married Filing Jointly",'CONSTANTS & REFERENCES'!$C$26,IF(AK11="Married Filing Separately",'CONSTANTS & REFERENCES'!$C$27,IF(AK11="Head of Household",'CONSTANTS & REFERENCES'!$C$28,'CONSTANTS & REFERENCES'!$C$25))))*'CONSTANTS & REFERENCES'!$B$25) -> 1734.7172 | AG11: =IF(Y11="","",AE11+AF11) -> 9152.1285 | AH11: =IF(OR(AC11="",AG11=""),"",AC11+AD11+AG11) -> 16508.409 | AI11: =IF(AH11="","",Y11-AH11) -> 103127.26 | AJ11: =IF(AI11="","",Y11-AH11-AI11) -> 0 | AK11: =IF(A11="","",IF(AND(INPUTS!$C$43="Yes",A11>=INPUTS!$C$45),INPUTS!$C$44,INPUTS!$C$19)) -> Married Filing Jointly | AL11: =IF(A11="","",(1+$X$6)^A11) -> 1.606157 | AM11: =IF(A11="","",(IF(OR(AK11="Single",AK11="Married Filing Separately"),'CONSTANTS & REFERENCES'!$B$13,IF(AK11="Married Filing Jointly",'CONSTANTS & REFERENCES'!$G$13,IF(AK11="Head of Household",'CONSTANTS & REFERENCES'!$L$13,""))))*AL11) -> 51718.255 | AN11: =IF(AM11="","",IF(A11=0,IF(OR(AK11="Single",AK11="Married Filing Separately"),'CONSTANTS & REFERENCES'!$B$13,IF(AK11="Married Filing Jointly",'CONSTANTS & REFERENCES'!$G$13,IF(AK11="Head of Household",'CONSTANTS & REFERENCES'!$L$13,""))),_xlfn.FLOOR.MATH(AM11,IF(AK11="Married Filing Separately",Bracket_Round_MFS,Bracket_Round_Standard)))) -> 51700 | AO11: =IF(A11="","",(IF(OR(AK11="Single",AK11="Married Filing Separately"),'CONSTANTS & REFERENCES'!$C$5,IF(AK11="Married Filing Jointly",'CONSTANTS & REFERENCES'!$H$5,IF(AK11="Head of Household",'CONSTANTS & REFERENCES'!$M$5,""))))*AL11) -> 39832.694 | AP11: =IF(AO11="","",IF(A11=0,IF(OR(AK11="Single",AK11="Married Filing Separately"),'CONSTANTS & REFERENCES'!$C$5,IF(AK11="Married Filing Jointly",'CONSTANTS & REFERENCES'!$H$5,IF(AK11="Head of Household",'CONSTANTS & REFERENCES'!$M$5,""))),_xlfn.FLOOR.MATH(AO11,IF(AK11="Married Filing Separately",Bracket_Round_MFS,Bracket_Round_Standard)))) -> 39800 | AQ11: =IF(A11="","",(IF(OR(AK11="Single",AK11="Married Filing Separately"),'CONSTANTS & REFERENCES'!$C$6,IF(AK11="Married Filing Jointly",'CONSTANTS & REFERENCES'!$H$6,IF(AK11="Head of Household",'CONSTANTS & REFERENCES'!$M$6,""))))*AL11) -> 161900.63 | AR11: =IF(AQ11="","",IF(A11=0,IF(OR(AK11="Single",AK11="Married Filing Separately"),'CONSTANTS & REFERENCES'!$C$6,IF(AK11="Married Filing Jointly",'CONSTANTS & REFERENCES'!$H$6,IF(AK11="Head of Household",'CONSTANTS & REFERENCES'!$M$6,""))),_xlfn.FLOOR.MATH(AQ11,IF(AK11="Married Filing Separately",Bracket_Round_MFS,Bracket_Round_Standard)))) -> 161900 | AS11: =IF(A11="","",(IF(OR(AK11="Single",AK11="Married Filing Separately"),'CONSTANTS & REFERENCES'!$C$7,IF(AK11="Married Filing Jointly",'CONSTANTS & REFERENCES'!$H$7,IF(AK11="Head of Household",'CONSTANTS & REFERENCES'!$M$7,""))))*AL11) -> 339541.59 | AT11: =IF(AS11="","",IF(A11=0,IF(OR(AK11="Single",AK11="Married Filing Separately"),'CONSTANTS & REFERENCES'!$C$7,IF(AK11="Married Filing Jointly",'CONSTANTS & REFERENCES'!$H$7,IF(AK11="Head of Household",'CONSTANTS & REFERENCES'!$M$7,""))),_xlfn.FLOOR.MATH(AS11,IF(AK11="Married Filing Separately",Bracket_Round_MFS,Bracket_Round_Standard)))) -> 339500 | AU11: =IF(A11="","",(IF(OR(AK11="Single",AK11="Married Filing Separately"),'CONSTANTS & REFERENCES'!$C$8,IF(AK11="Married Filing Jointly",'CONSTANTS & REFERENCES'!$H$8,IF(AK11="Head of Household",'CONSTANTS & REFERENCES'!$M$8,""))))*AL11) -> 648164.66 | AV11: =IF(AU11="","",IF(A11=0,IF(OR(AK11="Single",AK11="Married Filing Separately"),'CONSTANTS & REFERENCES'!$C$8,IF(AK11="Married Filing Jointly",'CONSTANTS & REFERENCES'!$H$8,IF(AK11="Head of Household",'CONSTANTS & REFERENCES'!$M$8,""))),_xlfn.FLOOR.MATH(AU11,IF(AK11="Married Filing Separately",Bracket_Round_MFS,Bracket_Round_Standard)))) -> 648150 | AW11: =IF(A11="","",(IF(OR(AK11="Single",AK11="Married Filing Separately"),'CONSTANTS & REFERENCES'!$C$9,IF(AK11="Married Filing Jointly",'CONSTANTS & REFERENCES'!$H$9,IF(AK11="Head of Household",'CONSTANTS & REFERENCES'!$M$9,""))))*AL11) -> 823075.16 | AX11: =IF(AW11="","",IF(A11=0,IF(OR(AK11="Single",AK11="Married Filing Separately"),'CONSTANTS & REFERENCES'!$C$9,IF(AK11="Married Filing Jointly",'CONSTANTS & REFERENCES'!$H$9,IF(AK11="Head of Household",'CONSTANTS & REFERENCES'!$M$9,""))),_xlfn.FLOOR.MATH(AW11,IF(AK11="Married Filing Separately",Bracket_Round_MFS,Bracket_Round_Standard)))) -> 823050 | AY11: =IF(A11="","",(IF(OR(AK11="Single",AK11="Married Filing Separately"),'CONSTANTS & REFERENCES'!$C$10,IF(AK11="Married Filing Jointly",'CONSTANTS & REFERENCES'!$H$10,IF(AK11="Head of Household",'CONSTANTS & REFERENCES'!$M$10,""))))*AL11) -> 1234492.3 | AZ11: =IF(AY11="","",IF(A11=0,IF(OR(AK11="Single",AK11="Married Filing Separately"),'CONSTANTS & REFERENCES'!$C$10,IF(AK11="Married Filing Jointly",'CONSTANTS & REFERENCES'!$H$10,IF(AK11="Head of Household",'CONSTANTS & REFERENCES'!$M$10,""))),_xlfn.FLOOR.MATH(AY11,IF(AK11="Married Filing Separately",Bracket_Round_MFS,Bracket_Round_Standard)))) -> 1234450 | BA11: =IF(A11="","",IF(A11=0,"Official 2026 base values","Illustrative future tax assumptions under simplified C-CPI-U indexing; not an IRS forecast.")) -> Illustrative future tax assumptions under simplified C-CPI-U indexing; not an IRS forecast. | BB11: =IF(A11="","",'CONSTANTS & REFERENCES'!$C$22*AL11) -> 296335.97 | BC11: =IF(BB11="","",_xlfn.FLOOR.MATH(BB11,100)) -> 296300
A12: =IF(A11<INPUTS!$C$7-INPUTS!$C$6,A11+1,"") -> 10 | B12: =IF(A12="","",INPUTS!$C$6+A12) -> 32 | C12: =IF(A12="","",L11) -> 160578.68 | D12: =IF(A12="","",IF(A12<INPUTS!$C$13,0,J12)) -> 13000 | E12: =IF(A12="","",IF(D12=0,"—",IF(Y12<IF(AK12="Married Filing Jointly",'CONSTANTS & REFERENCES'!$B$44,IF(AK12="Married Filing Separately",'CONSTANTS & REFERENCES'!$B$45,'CONSTANTS & REFERENCES'!$B$43)),"Direct","Backdoor"))) -> Direct | F12: =IF(A12="","",$X$2*(1+$X$3)^A12) -> 13431.358 | G12: =IF(F12="","",_xlfn.FLOOR.MATH(F12,500)) -> 13000 | H12: =IF(A12="","",$X$4*(1+$X$3)^A12) -> 1969.9325 | I12: =IF(H12="","",_xlfn.FLOOR.MATH(H12,100)) -> 1900 | J12: =IF(A12="","",G12+IF(B12>=50,I12,0)) -> 13000 | K12: =IF(A12="","",IF(INPUTS!$C$12="Beginning",(C12+D12)*INPUTS!$C$10,C12*INPUTS!$C$10)) -> 17357.868 | L12: =IF(A12="","",IF(INPUTS!$C$12="Beginning",(C12+D12)*(1+INPUTS!$C$10),C12*(1+INPUTS!$C$10)+D12)) -> 190936.55 | M12: =IF(A12="","",(1+INPUTS!$C$11)^A12) -> 1.7908477 | N12: =IF(A12="","",L12/M12) -> 106617.97 | O12: =IF(A12="","",O11+D12) -> 109000 | P12: =IF(A12="","",L12-INPUTS!$C$8-O12) -> 81936.549 | S12: =IF(B12="","",B12) -> 32 | T12: =IF(L12="","",L12) -> 190936.55 | U12: =IF(N12="","",N12) -> 106617.97 | V12: =IF(A12="","",FV(INPUTS!$C$10,INPUTS!$C$7-INPUTS!$C$6-A12+IF(INPUTS!$C$12="Beginning",1,0),0,-D12,0)) -> 332119.71 | Y12: =IF(A12="","",IF(INPUTS!$C$17="Yes",MIN(Y11*(1+INPUTS!$C$15)+IF(INPUTS!$C$27="Yes",(Z12-Z11)*INPUTS!$C$31+IF(AND(INPUTS!$C$28="Not yet credentialed",A12=INPUTS!$C$33),INPUTS!$C$32,0)+IF(AND(INPUTS!$C$28<>"FSA / FCAS",A12=INPUTS!$C$35),INPUTS!$C$34,0),0),INPUTS!$C$18),Y11*(1+INPUTS!$C$15)+IF(INPUTS!$C$27="Yes",(Z12-Z11)*INPUTS!$C$31+IF(AND(INPUTS!$C$28="Not yet credentialed",A12=INPUTS!$C$33),INPUTS!$C$32,0)+IF(AND(INPUTS!$C$28<>"FSA / FCAS",A12=INPUTS!$C$35),INPUTS!$C$34,0),0))) -> 123224.74 | Z12: =IF(A12="","",IF(AND(INPUTS!$C$27="Yes",INPUTS!$C$28<>"FSA / FCAS",ISNUMBER(INPUTS!$C$37)),MIN(A12*INPUTS!$C$37,INPUTS!$C$30),0)) -> 3 | AA12: =IF(A12="","",AN12) -> 54500 | AB12: =IF(OR(A12="",AA12=""),"",MAX(0,Y12-AA12)) -> 68724.737 | AC12: =IF(A12="","",MIN(AB12,AP12)*'CONSTANTS & REFERENCES'!$A$5+MAX(MIN(AB12,AR12)-AP12,0)*'CONSTANTS & REFERENCES'!$A$6+MAX(MIN(AB12,AT12)-AR12,0)*'CONSTANTS & REFERENCES'!$A$7+MAX(MIN(AB12,AV12)-AT12,0)*'CONSTANTS & REFERENCES'!$A$8+MAX(MIN(AB12,AX12)-AV12,0)*'CONSTANTS & REFERENCES'!$A$9+MAX(MIN(AB12,AZ12)-AX12,0)*'CONSTANTS & REFERENCES'!$A$10+MAX(AB12-AZ12,0)*'CONSTANTS & REFERENCES'!$A$11) -> 7407.9685 | AD12: =IF(AB12="","",IF(INPUTS!$C$20="Yes",AB12*INPUTS!$C$21,0)) -> 0 | AE12: =IF(Y12="","",MIN(Y12,BC12)*'CONSTANTS & REFERENCES'!$B$22) -> 7639.9337 | AF12: =IF(Y12="","",Y12*'CONSTANTS & REFERENCES'!$B$24+MAX(0,Y12-IF(AK12="Married Filing Jointly",'CONSTANTS & REFERENCES'!$C$26,IF(AK12="Married Filing Separately",'CONSTANTS & REFERENCES'!$C$27,IF(AK12="Head of Household",'CONSTANTS & REFERENCES'!$C$28,'CONSTANTS & REFERENCES'!$C$25))))*'CONSTANTS & REFERENCES'!$B$25) -> 1786.7587 | AG12: =IF(Y12="","",AE12+AF12) -> 9426.6924 | AH12: =IF(OR(AC12="",AG12=""),"",AC12+AD12+AG12) -> 16834.661 | AI12: =IF(AH12="","",Y12-AH12) -> 106390.08 | AJ12: =IF(AI12="","",Y12-AH12-AI12) -> 0 | AK12: =IF(A12="","",IF(AND(INPUTS!$C$43="Yes",A12>=INPUTS!$C$45),INPUTS!$C$44,INPUTS!$C$19)) -> Married Filing Jointly | AL12: =IF(A12="","",(1+$X$6)^A12) -> 1.6929858 | AM12: =IF(A12="","",(IF(OR(AK12="Single",AK12="Married Filing Separately"),'CONSTANTS & REFERENCES'!$B$13,IF(AK12="Married Filing Jointly",'CONSTANTS & REFERENCES'!$G$13,IF(AK12="Head of Household",'CONSTANTS & REFERENCES'!$L$13,""))))*AL12) -> 54514.144 | AN12: =IF(AM12="","",IF(A12=0,IF(OR(AK12="Single",AK12="Married Filing Separately"),'CONSTANTS & REFERENCES'!$B$13,IF(AK12="Married Filing Jointly",'CONSTANTS & REFERENCES'!$G$13,IF(AK12="Head of Household",'CONSTANTS & REFERENCES'!$L$13,""))),_xlfn.FLOOR.MATH(AM12,IF(AK12="Married Filing Separately",Bracket_Round_MFS,Bracket_Round_Standard)))) -> 54500 | AO12: =IF(A12="","",(IF(OR(AK12="Single",AK12="Married Filing Separately"),'CONSTANTS & REFERENCES'!$C$5,IF(AK12="Married Filing Jointly",'CONSTANTS & REFERENCES'!$H$5,IF(AK12="Head of Household",'CONSTANTS & REFERENCES'!$M$5,""))))*AL12) -> 41986.049 | AP12: =IF(AO12="","",IF(A12=0,IF(OR(AK12="Single",AK12="Married Filing Separately"),'CONSTANTS & REFERENCES'!$C$5,IF(AK12="Married Filing Jointly",'CONSTANTS & REFERENCES'!$H$5,IF(AK12="Head of Household",'CONSTANTS & REFERENCES'!$M$5,""))),_xlfn.FLOOR.MATH(AO12,IF(AK12="Married Filing Separately",Bracket_Round_MFS,Bracket_Round_Standard)))) -> 41950 | AQ12: =IF(A12="","",(IF(OR(AK12="Single",AK12="Married Filing Separately"),'CONSTANTS & REFERENCES'!$C$6,IF(AK12="Married Filing Jointly",'CONSTANTS & REFERENCES'!$H$6,IF(AK12="Head of Household",'CONSTANTS & REFERENCES'!$M$6,""))))*AL12) -> 170652.97 | AR12: =IF(AQ12="","",IF(A12=0,IF(OR(AK12="Single",AK12="Married Filing Separately"),'CONSTANTS & REFERENCES'!$C$6,IF(AK12="Married Filing Jointly",'CONSTANTS & REFERENCES'!$H$6,IF(AK12="Head of Household",'CONSTANTS & REFERENCES'!$M$6,""))),_xlfn.FLOOR.MATH(AQ12,IF(AK12="Married Filing Separately",Bracket_Round_MFS,Bracket_Round_Standard)))) -> 170650 | AS12: =IF(A12="","",(IF(OR(AK12="Single",AK12="Married Filing Separately"),'CONSTANTS & REFERENCES'!$C$7,IF(AK12="Married Filing Jointly",'CONSTANTS & REFERENCES'!$H$7,IF(AK12="Head of Household",'CONSTANTS & REFERENCES'!$M$7,""))))*AL12) -> 357897.21 | AT12: =IF(AS12="","",IF(A12=0,IF(OR(AK12="Single",AK12="Married Filing Separately"),'CONSTANTS & REFERENCES'!$C$7,IF(AK12="Married Filing Jointly",'CONSTANTS & REFERENCES'!$H$7,IF(AK12="Head of Household",'CONSTANTS & REFERENCES'!$M$7,""))),_xlfn.FLOOR.MATH(AS12,IF(AK12="Married Filing Separately",Bracket_Round_MFS,Bracket_Round_Standard)))) -> 357850 | AU12: =IF(A12="","",(IF(OR(AK12="Single",AK12="Married Filing Separately"),'CONSTANTS & REFERENCES'!$C$8,IF(AK12="Married Filing Jointly",'CONSTANTS & REFERENCES'!$H$8,IF(AK12="Head of Household",'CONSTANTS & REFERENCES'!$M$8,""))))*AL12) -> 683204.44 | AV12: =IF(AU12="","",IF(A12=0,IF(OR(AK12="Single",AK12="Married Filing Separately"),'CONSTANTS & REFERENCES'!$C$8,IF(AK12="Married Filing Jointly",'CONSTANTS & REFERENCES'!$H$8,IF(AK12="Head of Household",'CONSTANTS & REFERENCES'!$M$8,""))),_xlfn.FLOOR.MATH(AU12,IF(AK12="Married Filing Separately",Bracket_Round_MFS,Bracket_Round_Standard)))) -> 683200 | AW12: =IF(A12="","",(IF(OR(AK12="Single",AK12="Married Filing Separately"),'CONSTANTS & REFERENCES'!$C$9,IF(AK12="Married Filing Jointly",'CONSTANTS & REFERENCES'!$H$9,IF(AK12="Head of Household",'CONSTANTS & REFERENCES'!$M$9,""))))*AL12) -> 867570.6 | AX12: =IF(AW12="","",IF(A12=0,IF(OR(AK12="Single",AK12="Married Filing Separately"),'CONSTANTS & REFERENCES'!$C$9,IF(AK12="Married Filing Jointly",'CONSTANTS & REFERENCES'!$H$9,IF(AK12="Head of Household",'CONSTANTS & REFERENCES'!$M$9,""))),_xlfn.FLOOR.MATH(AW12,IF(AK12="Married Filing Separately",Bracket_Round_MFS,Bracket_Round_Standard)))) -> 867550 | AY12: =IF(A12="","",(IF(OR(AK12="Single",AK12="Married Filing Separately"),'CONSTANTS & REFERENCES'!$C$10,IF(AK12="Married Filing Jointly",'CONSTANTS & REFERENCES'!$H$10,IF(AK12="Head of Household",'CONSTANTS & REFERENCES'!$M$10,""))))*AL12) -> 1301228.9 | AZ12: =IF(AY12="","",IF(A12=0,IF(OR(AK12="Single",AK12="Married Filing Separately"),'CONSTANTS & REFERENCES'!$C$10,IF(AK12="Married Filing Jointly",'CONSTANTS & REFERENCES'!$H$10,IF(AK12="Head of Household",'CONSTANTS & REFERENCES'!$M$10,""))),_xlfn.FLOOR.MATH(AY12,IF(AK12="Married Filing Separately",Bracket_Round_MFS,Bracket_Round_Standard)))) -> 1301200 | BA12: =IF(A12="","",IF(A12=0,"Official 2026 base values","Illustrative future tax assumptions under simplified C-CPI-U indexing; not an IRS forecast.")) -> Illustrative future tax assumptions under simplified C-CPI-U indexing; not an IRS forecast. | BB12: =IF(A12="","",'CONSTANTS & REFERENCES'!$C$22*AL12) -> 312355.89 | BC12: =IF(BB12="","",_xlfn.FLOOR.MATH(BB12,100)) -> 312300
A13: =IF(A12<INPUTS!$C$7-INPUTS!$C$6,A12+1,"") -> 11 | B13: =IF(A13="","",INPUTS!$C$6+A13) -> 33 | C13: =IF(A13="","",L12) -> 190936.55 | D13: =IF(A13="","",IF(A13<INPUTS!$C$13,0,J13)) -> 14000 | E13: =IF(A13="","",IF(D13=0,"—",IF(Y13<IF(AK13="Married Filing Jointly",'CONSTANTS & REFERENCES'!$B$44,IF(AK13="Married Filing Separately",'CONSTANTS & REFERENCES'!$B$45,'CONSTANTS & REFERENCES'!$B$43)),"Direct","Backdoor"))) -> Direct | F13: =IF(A13="","",$X$2*(1+$X$3)^A13) -> 14237.239 | G13: =IF(F13="","",_xlfn.FLOOR.MATH(F13,500)) -> 14000 | H13: =IF(A13="","",$X$4*(1+$X$3)^A13) -> 2088.1284 | I13: =IF(H13="","",_xlfn.FLOOR.MATH(H13,100)) -> 2000 | J13: =IF(A13="","",G13+IF(B13>=50,I13,0)) -> 14000 | K13: =IF(A13="","",IF(INPUTS!$C$12="Beginning",(C13+D13)*INPUTS!$C$10,C13*INPUTS!$C$10)) -> 20493.655 | L13: =IF(A13="","",IF(INPUTS!$C$12="Beginning",(C13+D13)*(1+INPUTS!$C$10),C13*(1+INPUTS!$C$10)+D13)) -> 225430.2 | M13: =IF(A13="","",(1+INPUTS!$C$11)^A13) -> 1.8982986 | N13: =IF(A13="","",L13/M13) -> 118753.82 | O13: =IF(A13="","",O12+D13) -> 123000 | P13: =IF(A13="","",L13-INPUTS!$C$8-O13) -> 102430.2 | S13: =IF(B13="","",B13) -> 33 | T13: =IF(L13="","",L13) -> 225430.2 | U13: =IF(N13="","",N13) -> 118753.82 | V13: =IF(A13="","",FV(INPUTS!$C$10,INPUTS!$C$7-INPUTS!$C$6-A13+IF(INPUTS!$C$12="Beginning",1,0),0,-D13,0)) -> 325152.16 | Y13: =IF(A13="","",IF(INPUTS!$C$17="Yes",MIN(Y12*(1+INPUTS!$C$15)+IF(INPUTS!$C$27="Yes",(Z13-Z12)*INPUTS!$C$31+IF(AND(INPUTS!$C$28="Not yet credentialed",A13=INPUTS!$C$33),INPUTS!$C$32,0)+IF(AND(INPUTS!$C$28<>"FSA / FCAS",A13=INPUTS!$C$35),INPUTS!$C$34,0),0),INPUTS!$C$18),Y12*(1+INPUTS!$C$15)+IF(INPUTS!$C$27="Yes",(Z13-Z12)*INPUTS!$C$31+IF(AND(INPUTS!$C$28="Not yet credentialed",A13=INPUTS!$C$33),INPUTS!$C$32,0)+IF(AND(INPUTS!$C$28<>"FSA / FCAS",A13=INPUTS!$C$35),INPUTS!$C$34,0),0))) -> 126921.48 | Z13: =IF(A13="","",IF(AND(INPUTS!$C$27="Yes",INPUTS!$C$28<>"FSA / FCAS",ISNUMBER(INPUTS!$C$37)),MIN(A13*INPUTS!$C$37,INPUTS!$C$30),0)) -> 3 | AA13: =IF(A13="","",AN13) -> 57450 | AB13: =IF(OR(A13="",AA13=""),"",MAX(0,Y13-AA13)) -> 69471.479 | AC13: =IF(A13="","",MIN(AB13,AP13)*'CONSTANTS & REFERENCES'!$A$5+MAX(MIN(AB13,AR13)-AP13,0)*'CONSTANTS & REFERENCES'!$A$6+MAX(MIN(AB13,AT13)-AR13,0)*'CONSTANTS & REFERENCES'!$A$7+MAX(MIN(AB13,AV13)-AT13,0)*'CONSTANTS & REFERENCES'!$A$8+MAX(MIN(AB13,AX13)-AV13,0)*'CONSTANTS & REFERENCES'!$A$9+MAX(MIN(AB13,AZ13)-AX13,0)*'CONSTANTS & REFERENCES'!$A$10+MAX(AB13-AZ13,0)*'CONSTANTS & REFERENCES'!$A$11) -> 7451.5775 | AD13: =IF(AB13="","",IF(INPUTS!$C$20="Yes",AB13*INPUTS!$C$21,0)) -> 0 | AE13: =IF(Y13="","",MIN(Y13,BC13)*'CONSTANTS & REFERENCES'!$B$22) -> 7869.1317 | AF13: =IF(Y13="","",Y13*'CONSTANTS & REFERENCES'!$B$24+MAX(0,Y13-IF(AK13="Married Filing Jointly",'CONSTANTS & REFERENCES'!$C$26,IF(AK13="Married Filing Separately",'CONSTANTS & REFERENCES'!$C$27,IF(AK13="Head of Household",'CONSTANTS & REFERENCES'!$C$28,'CONSTANTS & REFERENCES'!$C$25))))*'CONSTANTS & REFERENCES'!$B$25) -> 1840.3615 | AG13: =IF(Y13="","",AE13+AF13) -> 9709.4932 | AH13: =IF(OR(AC13="",AG13=""),"",AC13+AD13+AG13) -> 17161.071 | AI13: =IF(AH13="","",Y13-AH13) -> 109760.41 | AJ13: =IF(AI13="","",Y13-AH13-AI13) -> 0 | AK13: =IF(A13="","",IF(AND(INPUTS!$C$43="Yes",A13>=INPUTS!$C$45),INPUTS!$C$44,INPUTS!$C$19)) -> Married Filing Jointly | AL13: =IF(A13="","",(1+$X$6)^A13) -> 1.7845087 | AM13: =IF(A13="","",(IF(OR(AK13="Single",AK13="Married Filing Separately"),'CONSTANTS & REFERENCES'!$B$13,IF(AK13="Married Filing Jointly",'CONSTANTS & REFERENCES'!$G$13,IF(AK13="Head of Household",'CONSTANTS & REFERENCES'!$L$13,""))))*AL13) -> 57461.179 | AN13: =IF(AM13="","",IF(A13=0,IF(OR(AK13="Single",AK13="Married Filing Separately"),'CONSTANTS & REFERENCES'!$B$13,IF(AK13="Married Filing Jointly",'CONSTANTS & REFERENCES'!$G$13,IF(AK13="Head of Household",'CONSTANTS & REFERENCES'!$L$13,""))),_xlfn.FLOOR.MATH(AM13,IF(AK13="Married Filing Separately",Bracket_Round_MFS,Bracket_Round_Standard)))) -> 57450 | AO13: =IF(A13="","",(IF(OR(AK13="Single",AK13="Married Filing Separately"),'CONSTANTS & REFERENCES'!$C$5,IF(AK13="Married Filing Jointly",'CONSTANTS & REFERENCES'!$H$5,IF(AK13="Head of Household",'CONSTANTS & REFERENCES'!$M$5,""))))*AL13) -> 44255.815 | AP13: =IF(AO13="","",IF(A13=0,IF(OR(AK13="Single",AK13="Married Filing Separately"),'CONSTANTS & REFERENCES'!$C$5,IF(AK13="Married Filing Jointly",'CONSTANTS & REFERENCES'!$H$5,IF(AK13="Head of Household",'CONSTANTS & REFERENCES'!$M$5,""))),_xlfn.FLOOR.MATH(AO13,IF(AK13="Married Filing Separately",Bracket_Round_MFS,Bracket_Round_Standard)))) -> 44250 | AQ13: =IF(A13="","",(IF(OR(AK13="Single",AK13="Married Filing Separately"),'CONSTANTS & REFERENCES'!$C$6,IF(AK13="Married Filing Jointly",'CONSTANTS & REFERENCES'!$H$6,IF(AK13="Head of Household",'CONSTANTS & REFERENCES'!$M$6,""))))*AL13) -> 179878.47 | AR13: =IF(AQ13="","",IF(A13=0,IF(OR(AK13="Single",AK13="Married Filing Separately"),'CONSTANTS & REFERENCES'!$C$6,IF(AK13="Married Filing Jointly",'CONSTANTS & REFERENCES'!$H$6,IF(AK13="Head of Household",'CONSTANTS & REFERENCES'!$M$6,""))),_xlfn.FLOOR.MATH(AQ13,IF(AK13="Married Filing Separately",Bracket_Round_MFS,Bracket_Round_Standard)))) -> 179850 | AS13: =IF(A13="","",(IF(OR(AK13="Single",AK13="Married Filing Separately"),'CONSTANTS & REFERENCES'!$C$7,IF(AK13="Married Filing Jointly",'CONSTANTS & REFERENCES'!$H$7,IF(AK13="Head of Household",'CONSTANTS & REFERENCES'!$M$7,""))))*AL13) -> 377245.13 | AT13: =IF(AS13="","",IF(A13=0,IF(OR(AK13="Single",AK13="Married Filing Separately"),'CONSTANTS & REFERENCES'!$C$7,IF(AK13="Married Filing Jointly",'CONSTANTS & REFERENCES'!$H$7,IF(AK13="Head of Household",'CONSTANTS & REFERENCES'!$M$7,""))),_xlfn.FLOOR.MATH(AS13,IF(AK13="Married Filing Separately",Bracket_Round_MFS,Bracket_Round_Standard)))) -> 377200 | AU13: =IF(A13="","",(IF(OR(AK13="Single",AK13="Married Filing Separately"),'CONSTANTS & REFERENCES'!$C$8,IF(AK13="Married Filing Jointly",'CONSTANTS & REFERENCES'!$H$8,IF(AK13="Head of Household",'CONSTANTS & REFERENCES'!$M$8,""))))*AL13) -> 720138.47 | AV13: =IF(AU13="","",IF(A13=0,IF(OR(AK13="Single",AK13="Married Filing Separately"),'CONSTANTS & REFERENCES'!$C$8,IF(AK13="Married Filing Jointly",'CONSTANTS & REFERENCES'!$H$8,IF(AK13="Head of Household",'CONSTANTS & REFERENCES'!$M$8,""))),_xlfn.FLOOR.MATH(AU13,IF(AK13="Married Filing Separately",Bracket_Round_MFS,Bracket_Round_Standard)))) -> 720100 | AW13: =IF(A13="","",(IF(OR(AK13="Single",AK13="Married Filing Separately"),'CONSTANTS & REFERENCES'!$C$9,IF(AK13="Married Filing Jointly",'CONSTANTS & REFERENCES'!$H$9,IF(AK13="Head of Household",'CONSTANTS & REFERENCES'!$M$9,""))))*AL13) -> 914471.47 | AX13: =IF(AW13="","",IF(A13=0,IF(OR(AK13="Single",AK13="Married Filing Separately"),'CONSTANTS & REFERENCES'!$C$9,IF(AK13="Married Filing Jointly",'CONSTANTS & REFERENCES'!$H$9,IF(AK13="Head of Household",'CONSTANTS & REFERENCES'!$M$9,""))),_xlfn.FLOOR.MATH(AW13,IF(AK13="Married Filing Separately",Bracket_Round_MFS,Bracket_Round_Standard)))) -> 914450 | AY13: =IF(A13="","",(IF(OR(AK13="Single",AK13="Married Filing Separately"),'CONSTANTS & REFERENCES'!$C$10,IF(AK13="Married Filing Jointly",'CONSTANTS & REFERENCES'!$H$10,IF(AK13="Head of Household",'CONSTANTS & REFERENCES'!$M$10,""))))*AL13) -> 1371573.4 | AZ13: =IF(AY13="","",IF(A13=0,IF(OR(AK13="Single",AK13="Married Filing Separately"),'CONSTANTS & REFERENCES'!$C$10,IF(AK13="Married Filing Jointly",'CONSTANTS & REFERENCES'!$H$10,IF(AK13="Head of Household",'CONSTANTS & REFERENCES'!$M$10,""))),_xlfn.FLOOR.MATH(AY13,IF(AK13="Married Filing Separately",Bracket_Round_MFS,Bracket_Round_Standard)))) -> 1371550 | BA13: =IF(A13="","",IF(A13=0,"Official 2026 base values","Illustrative future tax assumptions under simplified C-CPI-U indexing; not an IRS forecast.")) -> Illustrative future tax assumptions under simplified C-CPI-U indexing; not an IRS forecast. | BB13: =IF(A13="","",'CONSTANTS & REFERENCES'!$C$22*AL13) -> 329241.85 | BC13: =IF(BB13="","",_xlfn.FLOOR.MATH(BB13,100)) -> 329200
A14: =IF(A13<INPUTS!$C$7-INPUTS!$C$6,A13+1,"") -> 12 | B14: =IF(A14="","",INPUTS!$C$6+A14) -> 34 | C14: =IF(A14="","",L13) -> 225430.2 | D14: =IF(A14="","",IF(A14<INPUTS!$C$13,0,J14)) -> 15000 | E14: =IF(A14="","",IF(D14=0,"—",IF(Y14<IF(AK14="Married Filing Jointly",'CONSTANTS & REFERENCES'!$B$44,IF(AK14="Married Filing Separately",'CONSTANTS & REFERENCES'!$B$45,'CONSTANTS & REFERENCES'!$B$43)),"Direct","Backdoor"))) -> Direct | F14: =IF(A14="","",$X$2*(1+$X$3)^A14) -> 15091.474 | G14: =IF(F14="","",_xlfn.FLOOR.MATH(F14,500)) -> 15000 | H14: =IF(A14="","",$X$4*(1+$X$3)^A14) -> 2213.4161 | I14: =IF(H14="","",_xlfn.FLOOR.MATH(H14,100)) -> 2200 | J14: =IF(A14="","",G14+IF(B14>=50,I14,0)) -> 15000 | K14: =IF(A14="","",IF(INPUTS!$C$12="Beginning",(C14+D14)*INPUTS!$C$10,C14*INPUTS!$C$10)) -> 24043.02 | L14: =IF(A14="","",IF(INPUTS!$C$12="Beginning",(C14+D14)*(1+INPUTS!$C$10),C14*(1+INPUTS!$C$10)+D14)) -> 264473.22 | M14: =IF(A14="","",(1+INPUTS!$C$11)^A14) -> 2.0121965 | N14: =IF(A14="","",L14/M14) -> 131435.09 | O14: =IF(A14="","",O13+D14) -> 138000 | P14: =IF(A14="","",L14-INPUTS!$C$8-O14) -> 126473.22 | S14: =IF(B14="","",B14) -> 34 | T14: =IF(L14="","",L14) -> 264473.22 | U14: =IF(N14="","",N14) -> 131435.09 | V14: =IF(A14="","",FV(INPUTS!$C$10,INPUTS!$C$7-INPUTS!$C$6-A14+IF(INPUTS!$C$12="Beginning",1,0),0,-D14,0)) -> 316706.65 | Y14: =IF(A14="","",IF(INPUTS!$C$17="Yes",MIN(Y13*(1+INPUTS!$C$15)+IF(INPUTS!$C$27="Yes",(Z14-Z13)*INPUTS!$C$31+IF(AND(INPUTS!$C$28="Not yet credentialed",A14=INPUTS!$C$33),INPUTS!$C$32,0)+IF(AND(INPUTS!$C$28<>"FSA / FCAS",A14=INPUTS!$C$35),INPUTS!$C$34,0),0),INPUTS!$C$18),Y13*(1+INPUTS!$C$15)+IF(INPUTS!$C$27="Yes",(Z14-Z13)*INPUTS!$C$31+IF(AND(INPUTS!$C$28="Not yet credentialed",A14=INPUTS!$C$33),INPUTS!$C$32,0)+IF(AND(INPUTS!$C$28<>"FSA / FCAS",A14=INPUTS!$C$35),INPUTS!$C$34,0),0))) -> 130729.12 | Z14: =IF(A14="","",IF(AND(INPUTS!$C$27="Yes",INPUTS!$C$28<>"FSA / FCAS",ISNUMBER(INPUTS!$C$37)),MIN(A14*INPUTS!$C$37,INPUTS!$C$30),0)) -> 3 | AA14: =IF(A14="","",AN14) -> 60550 | AB14: =IF(OR(A14="",AA14=""),"",MAX(0,Y14-AA14)) -> 70179.124 | AC14: =IF(A14="","",MIN(AB14,AP14)*'CONSTANTS & REFERENCES'!$A$5+MAX(MIN(AB14,AR14)-AP14,0)*'CONSTANTS & REFERENCES'!$A$6+MAX(MIN(AB14,AT14)-AR14,0)*'CONSTANTS & REFERENCES'!$A$7+MAX(MIN(AB14,AV14)-AT14,0)*'CONSTANTS & REFERENCES'!$A$8+MAX(MIN(AB14,AX14)-AV14,0)*'CONSTANTS & REFERENCES'!$A$9+MAX(MIN(AB14,AZ14)-AX14,0)*'CONSTANTS & REFERENCES'!$A$10+MAX(AB14-AZ14,0)*'CONSTANTS & REFERENCES'!$A$11) -> 7489.4948 | AD14: =IF(AB14="","",IF(INPUTS!$C$20="Yes",AB14*INPUTS!$C$21,0)) -> 0 | AE14: =IF(Y14="","",MIN(Y14,BC14)*'CONSTANTS & REFERENCES'!$B$22) -> 8105.2057 | AF14: =IF(Y14="","",Y14*'CONSTANTS & REFERENCES'!$B$24+MAX(0,Y14-IF(AK14="Married Filing Jointly",'CONSTANTS & REFERENCES'!$C$26,IF(AK14="Married Filing Separately",'CONSTANTS & REFERENCES'!$C$27,IF(AK14="Head of Household",'CONSTANTS & REFERENCES'!$C$28,'CONSTANTS & REFERENCES'!$C$25))))*'CONSTANTS & REFERENCES'!$B$25) -> 1895.5723 | AG14: =IF(Y14="","",AE14+AF14) -> 10000.778 | AH14: =IF(OR(AC14="",AG14=""),"",AC14+AD14+AG14) -> 17490.273 | AI14: =IF(AH14="","",Y14-AH14) -> 113238.85 | AJ14: =IF(AI14="","",Y14-AH14-AI14) -> 0 | AK14: =IF(A14="","",IF(AND(INPUTS!$C$43="Yes",A14>=INPUTS!$C$45),INPUTS!$C$44,INPUTS!$C$19)) -> Married Filing Jointly | AL14: =IF(A14="","",(1+$X$6)^A14) -> 1.8809792 | AM14: =IF(A14="","",(IF(OR(AK14="Single",AK14="Married Filing Separately"),'CONSTANTS & REFERENCES'!$B$13,IF(AK14="Married Filing Jointly",'CONSTANTS & REFERENCES'!$G$13,IF(AK14="Head of Household",'CONSTANTS & REFERENCES'!$L$13,""))))*AL14) -> 60567.53 | AN14: =IF(AM14="","",IF(A14=0,IF(OR(AK14="Single",AK14="Married Filing Separately"),'CONSTANTS & REFERENCES'!$B$13,IF(AK14="Married Filing Jointly",'CONSTANTS & REFERENCES'!$G$13,IF(AK14="Head of Household",'CONSTANTS & REFERENCES'!$L$13,""))),_xlfn.FLOOR.MATH(AM14,IF(AK14="Married Filing Separately",Bracket_Round_MFS,Bracket_Round_Standard)))) -> 60550 | AO14: =IF(A14="","",(IF(OR(AK14="Single",AK14="Married Filing Separately"),'CONSTANTS & REFERENCES'!$C$5,IF(AK14="Married Filing Jointly",'CONSTANTS & REFERENCES'!$H$5,IF(AK14="Head of Household",'CONSTANTS & REFERENCES'!$M$5,""))))*AL14) -> 46648.284 | AP14: =IF(AO14="","",IF(A14=0,IF(OR(AK14="Single",AK14="Married Filing Separately"),'CONSTANTS & REFERENCES'!$C$5,IF(AK14="Married Filing Jointly",'CONSTANTS & REFERENCES'!$H$5,IF(AK14="Head of Household",'CONSTANTS & REFERENCES'!$M$5,""))),_xlfn.FLOOR.MATH(AO14,IF(AK14="Married Filing Separately",Bracket_Round_MFS,Bracket_Round_Standard)))) -> 46600 | AQ14: =IF(A14="","",(IF(OR(AK14="Single",AK14="Married Filing Separately"),'CONSTANTS & REFERENCES'!$C$6,IF(AK14="Married Filing Jointly",'CONSTANTS & REFERENCES'!$H$6,IF(AK14="Head of Household",'CONSTANTS & REFERENCES'!$M$6,""))))*AL14) -> 189602.7 | AR14: =IF(AQ14="","",IF(A14=0,IF(OR(AK14="Single",AK14="Married Filing Separately"),'CONSTANTS & REFERENCES'!$C$6,IF(AK14="Married Filing Jointly",'CONSTANTS & REFERENCES'!$H$6,IF(AK14="Head of Household",'CONSTANTS & REFERENCES'!$M$6,""))),_xlfn.FLOOR.MATH(AQ14,IF(AK14="Married Filing Separately",Bracket_Round_MFS,Bracket_Round_Standard)))) -> 189600 | AS14: =IF(A14="","",(IF(OR(AK14="Single",AK14="Married Filing Separately"),'CONSTANTS & REFERENCES'!$C$7,IF(AK14="Married Filing Jointly",'CONSTANTS & REFERENCES'!$H$7,IF(AK14="Head of Household",'CONSTANTS & REFERENCES'!$M$7,""))))*AL14) -> 397639 | AT14: =IF(AS14="","",IF(A14=0,IF(OR(AK14="Single",AK14="Married Filing Separately"),'CONSTANTS & REFERENCES'!$C$7,IF(AK14="Married Filing Jointly",'CONSTANTS & REFERENCES'!$H$7,IF(AK14="Head of Household",'CONSTANTS & REFERENCES'!$M$7,""))),_xlfn.FLOOR.MATH(AS14,IF(AK14="Married Filing Separately",Bracket_Round_MFS,Bracket_Round_Standard)))) -> 397600 | AU14: =IF(A14="","",(IF(OR(AK14="Single",AK14="Married Filing Separately"),'CONSTANTS & REFERENCES'!$C$8,IF(AK14="Married Filing Jointly",'CONSTANTS & REFERENCES'!$H$8,IF(AK14="Head of Household",'CONSTANTS & REFERENCES'!$M$8,""))))*AL14) -> 759069.16 | AV14: =IF(AU14="","",IF(A14=0,IF(OR(AK14="Single",AK14="Married Filing Separately"),'CONSTANTS & REFERENCES'!$C$8,IF(AK14="Married Filing Jointly",'CONSTANTS & REFERENCES'!$H$8,IF(AK14="Head of Household",'CONSTANTS & REFERENCES'!$M$8,""))),_xlfn.FLOOR.MATH(AU14,IF(AK14="Married Filing Separately",Bracket_Round_MFS,Bracket_Round_Standard)))) -> 759050 | AW14: =IF(A14="","",(IF(OR(AK14="Single",AK14="Married Filing Separately"),'CONSTANTS & REFERENCES'!$C$9,IF(AK14="Married Filing Jointly",'CONSTANTS & REFERENCES'!$H$9,IF(AK14="Head of Household",'CONSTANTS & REFERENCES'!$M$9,""))))*AL14) -> 963907.79 | AX14: =IF(AW14="","",IF(A14=0,IF(OR(AK14="Single",AK14="Married Filing Separately"),'CONSTANTS & REFERENCES'!$C$9,IF(AK14="Married Filing Jointly",'CONSTANTS & REFERENCES'!$H$9,IF(AK14="Head of Household",'CONSTANTS & REFERENCES'!$M$9,""))),_xlfn.FLOOR.MATH(AW14,IF(AK14="Married Filing Separately",Bracket_Round_MFS,Bracket_Round_Standard)))) -> 963900 | AY14: =IF(A14="","",(IF(OR(AK14="Single",AK14="Married Filing Separately"),'CONSTANTS & REFERENCES'!$C$10,IF(AK14="Married Filing Jointly",'CONSTANTS & REFERENCES'!$H$10,IF(AK14="Head of Household",'CONSTANTS & REFERENCES'!$M$10,""))))*AL14) -> 1445720.6 | AZ14: =IF(AY14="","",IF(A14=0,IF(OR(AK14="Single",AK14="Married Filing Separately"),'CONSTANTS & REFERENCES'!$C$10,IF(AK14="Married Filing Jointly",'CONSTANTS & REFERENCES'!$H$10,IF(AK14="Head of Household",'CONSTANTS & REFERENCES'!$M$10,""))),_xlfn.FLOOR.MATH(AY14,IF(AK14="Married Filing Separately",Bracket_Round_MFS,Bracket_Round_Standard)))) -> 1445700 | BA14: =IF(A14="","",IF(A14=0,"Official 2026 base values","Illustrative future tax assumptions under simplified C-CPI-U indexing; not an IRS forecast.")) -> Illustrative future tax assumptions under simplified C-CPI-U indexing; not an IRS forecast. | BB14: =IF(A14="","",'CONSTANTS & REFERENCES'!$C$22*AL14) -> 347040.66 | BC14: =IF(BB14="","",_xlfn.FLOOR.MATH(BB14,100)) -> 347000
A15: =IF(A14<INPUTS!$C$7-INPUTS!$C$6,A14+1,"") -> 13 | B15: =IF(A15="","",INPUTS!$C$6+A15) -> 35 | C15: =IF(A15="","",L14) -> 264473.22 | D15: =IF(A15="","",IF(A15<INPUTS!$C$13,0,J15)) -> 15500 | E15: =IF(A15="","",IF(D15=0,"—",IF(Y15<IF(AK15="Married Filing Jointly",'CONSTANTS & REFERENCES'!$B$44,IF(AK15="Married Filing Separately",'CONSTANTS & REFERENCES'!$B$45,'CONSTANTS & REFERENCES'!$B$43)),"Direct","Backdoor"))) -> Direct | F15: =IF(A15="","",$X$2*(1+$X$3)^A15) -> 15996.962 | G15: =IF(F15="","",_xlfn.FLOOR.MATH(F15,500)) -> 15500 | H15: =IF(A15="","",$X$4*(1+$X$3)^A15) -> 2346.2211 | I15: =IF(H15="","",_xlfn.FLOOR.MATH(H15,100)) -> 2300 | J15: =IF(A15="","",G15+IF(B15>=50,I15,0)) -> 15500 | K15: =IF(A15="","",IF(INPUTS!$C$12="Beginning",(C15+D15)*INPUTS!$C$10,C15*INPUTS!$C$10)) -> 27997.322 | L15: =IF(A15="","",IF(INPUTS!$C$12="Beginning",(C15+D15)*(1+INPUTS!$C$10),C15*(1+INPUTS!$C$10)+D15)) -> 307970.55 | M15: =IF(A15="","",(1+INPUTS!$C$11)^A15) -> 2.1329283 | N15: =IF(A15="","",L15/M15) -> 144388.61 | O15: =IF(A15="","",O14+D15) -> 153500 | P15: =IF(A15="","",L15-INPUTS!$C$8-O15) -> 154470.55 | S15: =IF(B15="","",B15) -> 35 | T15: =IF(L15="","",L15) -> 307970.55 | U15: =IF(N15="","",N15) -> 144388.61 | V15: =IF(A15="","",FV(INPUTS!$C$10,INPUTS!$C$7-INPUTS!$C$6-A15+IF(INPUTS!$C$12="Beginning",1,0),0,-D15,0)) -> 297512.31 | Y15: =IF(A15="","",IF(INPUTS!$C$17="Yes",MIN(Y14*(1+INPUTS!$C$15)+IF(INPUTS!$C$27="Yes",(Z15-Z14)*INPUTS!$C$31+IF(AND(INPUTS!$C$28="Not yet credentialed",A15=INPUTS!$C$33),INPUTS!$C$32,0)+IF(AND(INPUTS!$C$28<>"FSA / FCAS",A15=INPUTS!$C$35),INPUTS!$C$34,0),0),INPUTS!$C$18),Y14*(1+INPUTS!$C$15)+IF(INPUTS!$C$27="Yes",(Z15-Z14)*INPUTS!$C$31+IF(AND(INPUTS!$C$28="Not yet credentialed",A15=INPUTS!$C$33),INPUTS!$C$32,0)+IF(AND(INPUTS!$C$28<>"FSA / FCAS",A15=INPUTS!$C$35),INPUTS!$C$34,0),0))) -> 134651 | Z15: =IF(A15="","",IF(AND(INPUTS!$C$27="Yes",INPUTS!$C$28<>"FSA / FCAS",ISNUMBER(INPUTS!$C$37)),MIN(A15*INPUTS!$C$37,INPUTS!$C$30),0)) -> 3 | AA15: =IF(A15="","",AN15) -> 63800 | AB15: =IF(OR(A15="",AA15=""),"",MAX(0,Y15-AA15)) -> 70850.997 | AC15: =IF(A15="","",MIN(AB15,AP15)*'CONSTANTS & REFERENCES'!$A$5+MAX(MIN(AB15,AR15)-AP15,0)*'CONSTANTS & REFERENCES'!$A$6+MAX(MIN(AB15,AT15)-AR15,0)*'CONSTANTS & REFERENCES'!$A$7+MAX(MIN(AB15,AV15)-AT15,0)*'CONSTANTS & REFERENCES'!$A$8+MAX(MIN(AB15,AX15)-AV15,0)*'CONSTANTS & REFERENCES'!$A$9+MAX(MIN(AB15,AZ15)-AX15,0)*'CONSTANTS & REFERENCES'!$A$10+MAX(AB15-AZ15,0)*'CONSTANTS & REFERENCES'!$A$11) -> 7519.1197 | AD15: =IF(AB15="","",IF(INPUTS!$C$20="Yes",AB15*INPUTS!$C$21,0)) -> 0 | AE15: =IF(Y15="","",MIN(Y15,BC15)*'CONSTANTS & REFERENCES'!$B$22) -> 8348.3618 | AF15: =IF(Y15="","",Y15*'CONSTANTS & REFERENCES'!$B$24+MAX(0,Y15-IF(AK15="Married Filing Jointly",'CONSTANTS & REFERENCES'!$C$26,IF(AK15="Married Filing Separately",'CONSTANTS & REFERENCES'!$C$27,IF(AK15="Head of Household",'CONSTANTS & REFERENCES'!$C$28,'CONSTANTS & REFERENCES'!$C$25))))*'CONSTANTS & REFERENCES'!$B$25) -> 1952.4395 | AG15: =IF(Y15="","",AE15+AF15) -> 10300.801 | AH15: =IF(OR(AC15="",AG15=""),"",AC15+AD15+AG15) -> 17819.921 | AI15: =IF(AH15="","",Y15-AH15) -> 116831.08 | AJ15: =IF(AI15="","",Y15-AH15-AI15) -> 0 | AK15: =IF(A15="","",IF(AND(INPUTS!$C$43="Yes",A15>=INPUTS!$C$45),INPUTS!$C$44,INPUTS!$C$19)) -> Married Filing Jointly | AL15: =IF(A15="","",(1+$X$6)^A15) -> 1.9826649 | AM15: =IF(A15="","",(IF(OR(AK15="Single",AK15="Married Filing Separately"),'CONSTANTS & REFERENCES'!$B$13,IF(AK15="Married Filing Jointly",'CONSTANTS & REFERENCES'!$G$13,IF(AK15="Head of Household",'CONSTANTS & REFERENCES'!$L$13,""))))*AL15) -> 63841.811 | AN15: =IF(AM15="","",IF(A15=0,IF(OR(AK15="Single",AK15="Married Filing Separately"),'CONSTANTS & REFERENCES'!$B$13,IF(AK15="Married Filing Jointly",'CONSTANTS & REFERENCES'!$G$13,IF(AK15="Head of Household",'CONSTANTS & REFERENCES'!$L$13,""))),_xlfn.FLOOR.MATH(AM15,IF(AK15="Married Filing Separately",Bracket_Round_MFS,Bracket_Round_Standard)))) -> 63800 | AO15: =IF(A15="","",(IF(OR(AK15="Single",AK15="Married Filing Separately"),'CONSTANTS & REFERENCES'!$C$5,IF(AK15="Married Filing Jointly",'CONSTANTS & REFERENCES'!$H$5,IF(AK15="Head of Household",'CONSTANTS & REFERENCES'!$M$5,""))))*AL15) -> 49170.09 | AP15: =IF(AO15="","",IF(A15=0,IF(OR(AK15="Single",AK15="Married Filing Separately"),'CONSTANTS & REFERENCES'!$C$5,IF(AK15="Married Filing Jointly",'CONSTANTS & REFERENCES'!$H$5,IF(AK15="Head of Household",'CONSTANTS & REFERENCES'!$M$5,""))),_xlfn.FLOOR.MATH(AO15,IF(AK15="Married Filing Separately",Bracket_Round_MFS,Bracket_Round_Standard)))) -> 49150 | AQ15: =IF(A15="","",(IF(OR(AK15="Single",AK15="Married Filing Separately"),'CONSTANTS & REFERENCES'!$C$6,IF(AK15="Married Filing Jointly",'CONSTANTS & REFERENCES'!$H$6,IF(AK15="Head of Household",'CONSTANTS & REFERENCES'!$M$6,""))))*AL15) -> 199852.63 | AR15: =IF(AQ15="","",IF(A15=0,IF(OR(AK15="Single",AK15="Married Filing Separately"),'CONSTANTS & REFERENCES'!$C$6,IF(AK15="Married Filing Jointly",'CONSTANTS & REFERENCES'!$H$6,IF(AK15="Head of Household",'CONSTANTS & REFERENCES'!$M$6,""))),_xlfn.FLOOR.MATH(AQ15,IF(AK15="Married Filing Separately",Bracket_Round_MFS,Bracket_Round_Standard)))) -> 199850 | AS15: =IF(A15="","",(IF(OR(AK15="Single",AK15="Married Filing Separately"),'CONSTANTS & REFERENCES'!$C$7,IF(AK15="Married Filing Jointly",'CONSTANTS & REFERENCES'!$H$7,IF(AK15="Head of Household",'CONSTANTS & REFERENCES'!$M$7,""))))*AL15) -> 419135.37 | AT15: =IF(AS15="","",IF(A15=0,IF(OR(AK15="Single",AK15="Married Filing Separately"),'CONSTANTS & REFERENCES'!$C$7,IF(AK15="Married Filing Jointly",'CONSTANTS & REFERENCES'!$H$7,IF(AK15="Head of Household",'CONSTANTS & REFERENCES'!$M$7,""))),_xlfn.FLOOR.MATH(AS15,IF(AK15="Married Filing Separately",Bracket_Round_MFS,Bracket_Round_Standard)))) -> 419100 | AU15: =IF(A15="","",(IF(OR(AK15="Single",AK15="Married Filing Separately"),'CONSTANTS & REFERENCES'!$C$8,IF(AK15="Married Filing Jointly",'CONSTANTS & REFERENCES'!$H$8,IF(AK15="Head of Household",'CONSTANTS & REFERENCES'!$M$8,""))))*AL15) -> 800104.44 | AV15: =IF(AU15="","",IF(A15=0,IF(OR(AK15="Single",AK15="Married Filing Separately"),'CONSTANTS & REFERENCES'!$C$8,IF(AK15="Married Filing Jointly",'CONSTANTS & REFERENCES'!$H$8,IF(AK15="Head of Household",'CONSTANTS & REFERENCES'!$M$8,""))),_xlfn.FLOOR.MATH(AU15,IF(AK15="Married Filing Separately",Bracket_Round_MFS,Bracket_Round_Standard)))) -> 800100 | AW15: =IF(A15="","",(IF(OR(AK15="Single",AK15="Married Filing Separately"),'CONSTANTS & REFERENCES'!$C$9,IF(AK15="Married Filing Jointly",'CONSTANTS & REFERENCES'!$H$9,IF(AK15="Head of Household",'CONSTANTS & REFERENCES'!$M$9,""))))*AL15) -> 1016016.6 | AX15: =IF(AW15="","",IF(A15=0,IF(OR(AK15="Single",AK15="Married Filing Separately"),'CONSTANTS & REFERENCES'!$C$9,IF(AK15="Married Filing Jointly",'CONSTANTS & REFERENCES'!$H$9,IF(AK15="Head of Household",'CONSTANTS & REFERENCES'!$M$9,""))),_xlfn.FLOOR.MATH(AW15,IF(AK15="Married Filing Separately",Bracket_Round_MFS,Bracket_Round_Standard)))) -> 1016000 | AY15: =IF(A15="","",(IF(OR(AK15="Single",AK15="Married Filing Separately"),'CONSTANTS & REFERENCES'!$C$10,IF(AK15="Married Filing Jointly",'CONSTANTS & REFERENCES'!$H$10,IF(AK15="Head of Household",'CONSTANTS & REFERENCES'!$M$10,""))))*AL15) -> 1523876.3 | AZ15: =IF(AY15="","",IF(A15=0,IF(OR(AK15="Single",AK15="Married Filing Separately"),'CONSTANTS & REFERENCES'!$C$10,IF(AK15="Married Filing Jointly",'CONSTANTS & REFERENCES'!$H$10,IF(AK15="Head of Household",'CONSTANTS & REFERENCES'!$M$10,""))),_xlfn.FLOOR.MATH(AY15,IF(AK15="Married Filing Separately",Bracket_Round_MFS,Bracket_Round_Standard)))) -> 1523850 | BA15: =IF(A15="","",IF(A15=0,"Official 2026 base values","Illustrative future tax assumptions under simplified C-CPI-U indexing; not an IRS forecast.")) -> Illustrative future tax assumptions under simplified C-CPI-U indexing; not an IRS forecast. | BB15: =IF(A15="","",'CONSTANTS & REFERENCES'!$C$22*AL15) -> 365801.68 | BC15: =IF(BB15="","",_xlfn.FLOOR.MATH(BB15,100)) -> 365800
A16: =IF(A15<INPUTS!$C$7-INPUTS!$C$6,A15+1,"") -> 14 | B16: =IF(A16="","",INPUTS!$C$6+A16) -> 36 | C16: =IF(A16="","",L15) -> 307970.55 | D16: =IF(A16="","",IF(A16<INPUTS!$C$13,0,J16)) -> 16500 | E16: =IF(A16="","",IF(D16=0,"—",IF(Y16<IF(AK16="Married Filing Jointly",'CONSTANTS & REFERENCES'!$B$44,IF(AK16="Married Filing Separately",'CONSTANTS & REFERENCES'!$B$45,'CONSTANTS & REFERENCES'!$B$43)),"Direct","Backdoor"))) -> Direct | F16: =IF(A16="","",$X$2*(1+$X$3)^A16) -> 16956.78 | G16: =IF(F16="","",_xlfn.FLOOR.MATH(F16,500)) -> 16500 | H16: =IF(A16="","",$X$4*(1+$X$3)^A16) -> 2486.9944 | I16: =IF(H16="","",_xlfn.FLOOR.MATH(H16,100)) -> 2400 | J16: =IF(A16="","",G16+IF(B16>=50,I16,0)) -> 16500 | K16: =IF(A16="","",IF(INPUTS!$C$12="Beginning",(C16+D16)*INPUTS!$C$10,C16*INPUTS!$C$10)) -> 32447.055 | L16: =IF(A16="","",IF(INPUTS!$C$12="Beginning",(C16+D16)*(1+INPUTS!$C$10),C16*(1+INPUTS!$C$10)+D16)) -> 356917.6 | M16: =IF(A16="","",(1+INPUTS!$C$11)^A16) -> 2.260904 | N16: =IF(A16="","",L16/M16) -> 157865 | O16: =IF(A16="","",O15+D16) -> 170000 | P16: =IF(A16="","",L16-INPUTS!$C$8-O16) -> 186917.6 | S16: =IF(B16="","",B16) -> 36 | T16: =IF(L16="","",L16) -> 356917.6 | U16: =IF(N16="","",N16) -> 157865 | V16: =IF(A16="","",FV(INPUTS!$C$10,INPUTS!$C$7-INPUTS!$C$6-A16+IF(INPUTS!$C$12="Beginning",1,0),0,-D16,0)) -> 287915.14 | Y16: =IF(A16="","",IF(INPUTS!$C$17="Yes",MIN(Y15*(1+INPUTS!$C$15)+IF(INPUTS!$C$27="Yes",(Z16-Z15)*INPUTS!$C$31+IF(AND(INPUTS!$C$28="Not yet credentialed",A16=INPUTS!$C$33),INPUTS!$C$32,0)+IF(AND(INPUTS!$C$28<>"FSA / FCAS",A16=INPUTS!$C$35),INPUTS!$C$34,0),0),INPUTS!$C$18),Y15*(1+INPUTS!$C$15)+IF(INPUTS!$C$27="Yes",(Z16-Z15)*INPUTS!$C$31+IF(AND(INPUTS!$C$28="Not yet credentialed",A16=INPUTS!$C$33),INPUTS!$C$32,0)+IF(AND(INPUTS!$C$28<>"FSA / FCAS",A16=INPUTS!$C$35),INPUTS!$C$34,0),0))) -> 138690.53 | Z16: =IF(A16="","",IF(AND(INPUTS!$C$27="Yes",INPUTS!$C$28<>"FSA / FCAS",ISNUMBER(INPUTS!$C$37)),MIN(A16*INPUTS!$C$37,INPUTS!$C$30),0)) -> 3 | AA16: =IF(A16="","",AN16) -> 67250 | AB16: =IF(OR(A16="",AA16=""),"",MAX(0,Y16-AA16)) -> 71440.527 | AC16: =IF(A16="","",MIN(AB16,AP16)*'CONSTANTS & REFERENCES'!$A$5+MAX(MIN(AB16,AR16)-AP16,0)*'CONSTANTS & REFERENCES'!$A$6+MAX(MIN(AB16,AT16)-AR16,0)*'CONSTANTS & REFERENCES'!$A$7+MAX(MIN(AB16,AV16)-AT16,0)*'CONSTANTS & REFERENCES'!$A$8+MAX(MIN(AB16,AX16)-AV16,0)*'CONSTANTS & REFERENCES'!$A$9+MAX(MIN(AB16,AZ16)-AX16,0)*'CONSTANTS & REFERENCES'!$A$10+MAX(AB16-AZ16,0)*'CONSTANTS & REFERENCES'!$A$11) -> 7536.8633 | AD16: =IF(AB16="","",IF(INPUTS!$C$20="Yes",AB16*INPUTS!$C$21,0)) -> 0 | AE16: =IF(Y16="","",MIN(Y16,BC16)*'CONSTANTS & REFERENCES'!$B$22) -> 8598.8127 | AF16: =IF(Y16="","",Y16*'CONSTANTS & REFERENCES'!$B$24+MAX(0,Y16-IF(AK16="Married Filing Jointly",'CONSTANTS & REFERENCES'!$C$26,IF(AK16="Married Filing Separately",'CONSTANTS & REFERENCES'!$C$27,IF(AK16="Head of Household",'CONSTANTS & REFERENCES'!$C$28,'CONSTANTS & REFERENCES'!$C$25))))*'CONSTANTS & REFERENCES'!$B$25) -> 2011.0126 | AG16: =IF(Y16="","",AE16+AF16) -> 10609.825 | AH16: =IF(OR(AC16="",AG16=""),"",AC16+AD16+AG16) -> 18146.689 | AI16: =IF(AH16="","",Y16-AH16) -> 120543.84 | AJ16: =IF(AI16="","",Y16-AH16-AI16) -> 0 | AK16: =IF(A16="","",IF(AND(INPUTS!$C$43="Yes",A16>=INPUTS!$C$45),INPUTS!$C$44,INPUTS!$C$19)) -> Married Filing Jointly | AL16: =IF(A16="","",(1+$X$6)^A16) -> 2.0898478 | AM16: =IF(A16="","",(IF(OR(AK16="Single",AK16="Married Filing Separately"),'CONSTANTS & REFERENCES'!$B$13,IF(AK16="Married Filing Jointly",'CONSTANTS & REFERENCES'!$G$13,IF(AK16="Head of Household",'CONSTANTS & REFERENCES'!$L$13,""))))*AL16) -> 67293.099 | AN16: =IF(AM16="","",IF(A16=0,IF(OR(AK16="Single",AK16="Married Filing Separately"),'CONSTANTS & REFERENCES'!$B$13,IF(AK16="Married Filing Jointly",'CONSTANTS & REFERENCES'!$G$13,IF(AK16="Head of Household",'CONSTANTS & REFERENCES'!$L$13,""))),_xlfn.FLOOR.MATH(AM16,IF(AK16="Married Filing Separately",Bracket_Round_MFS,Bracket_Round_Standard)))) -> 67250 | AO16: =IF(A16="","",(IF(OR(AK16="Single",AK16="Married Filing Separately"),'CONSTANTS & REFERENCES'!$C$5,IF(AK16="Married Filing Jointly",'CONSTANTS & REFERENCES'!$H$5,IF(AK16="Head of Household",'CONSTANTS & REFERENCES'!$M$5,""))))*AL16) -> 51828.226 | AP16: =IF(AO16="","",IF(A16=0,IF(OR(AK16="Single",AK16="Married Filing Separately"),'CONSTANTS & REFERENCES'!$C$5,IF(AK16="Married Filing Jointly",'CONSTANTS & REFERENCES'!$H$5,IF(AK16="Head of Household",'CONSTANTS & REFERENCES'!$M$5,""))),_xlfn.FLOOR.MATH(AO16,IF(AK16="Married Filing Separately",Bracket_Round_MFS,Bracket_Round_Standard)))) -> 51800 | AQ16: =IF(A16="","",(IF(OR(AK16="Single",AK16="Married Filing Separately"),'CONSTANTS & REFERENCES'!$C$6,IF(AK16="Married Filing Jointly",'CONSTANTS & REFERENCES'!$H$6,IF(AK16="Head of Household",'CONSTANTS & REFERENCES'!$M$6,""))))*AL16) -> 210656.66 | AR16: =IF(AQ16="","",IF(A16=0,IF(OR(AK16="Single",AK16="Married Filing Separately"),'CONSTANTS & REFERENCES'!$C$6,IF(AK16="Married Filing Jointly",'CONSTANTS & REFERENCES'!$H$6,IF(AK16="Head of Household",'CONSTANTS & REFERENCES'!$M$6,""))),_xlfn.FLOOR.MATH(AQ16,IF(AK16="Married Filing Separately",Bracket_Round_MFS,Bracket_Round_Standard)))) -> 210650 | AS16: =IF(A16="","",(IF(OR(AK16="Single",AK16="Married Filing Separately"),'CONSTANTS & REFERENCES'!$C$7,IF(AK16="Married Filing Jointly",'CONSTANTS & REFERENCES'!$H$7,IF(AK16="Head of Household",'CONSTANTS & REFERENCES'!$M$7,""))))*AL16) -> 441793.83 | AT16: =IF(AS16="","",IF(A16=0,IF(OR(AK16="Single",AK16="Married Filing Separately"),'CONSTANTS & REFERENCES'!$C$7,IF(AK16="Married Filing Jointly",'CONSTANTS & REFERENCES'!$H$7,IF(AK16="Head of Household",'CONSTANTS & REFERENCES'!$M$7,""))),_xlfn.FLOOR.MATH(AS16,IF(AK16="Married Filing Separately",Bracket_Round_MFS,Bracket_Round_Standard)))) -> 441750 | AU16: =IF(A16="","",(IF(OR(AK16="Single",AK16="Married Filing Separately"),'CONSTANTS & REFERENCES'!$C$8,IF(AK16="Married Filing Jointly",'CONSTANTS & REFERENCES'!$H$8,IF(AK16="Head of Household",'CONSTANTS & REFERENCES'!$M$8,""))))*AL16) -> 843358.08 | AV16: =IF(AU16="","",IF(A16=0,IF(OR(AK16="Single",AK16="Married Filing Separately"),'CONSTANTS & REFERENCES'!$C$8,IF(AK16="Married Filing Jointly",'CONSTANTS & REFERENCES'!$H$8,IF(AK16="Head of Household",'CONSTANTS & REFERENCES'!$M$8,""))),_xlfn.FLOOR.MATH(AU16,IF(AK16="Married Filing Separately",Bracket_Round_MFS,Bracket_Round_Standard)))) -> 843350 | AW16: =IF(A16="","",(IF(OR(AK16="Single",AK16="Married Filing Separately"),'CONSTANTS & REFERENCES'!$C$9,IF(AK16="Married Filing Jointly",'CONSTANTS & REFERENCES'!$H$9,IF(AK16="Head of Household",'CONSTANTS & REFERENCES'!$M$9,""))))*AL16) -> 1070942.5 | AX16: =IF(AW16="","",IF(A16=0,IF(OR(AK16="Single",AK16="Married Filing Separately"),'CONSTANTS & REFERENCES'!$C$9,IF(AK16="Married Filing Jointly",'CONSTANTS & REFERENCES'!$H$9,IF(AK16="Head of Household",'CONSTANTS & REFERENCES'!$M$9,""))),_xlfn.FLOOR.MATH(AW16,IF(AK16="Married Filing Separately",Bracket_Round_MFS,Bracket_Round_Standard)))) -> 1070900 | AY16: =IF(A16="","",(IF(OR(AK16="Single",AK16="Married Filing Separately"),'CONSTANTS & REFERENCES'!$C$10,IF(AK16="Married Filing Jointly",'CONSTANTS & REFERENCES'!$H$10,IF(AK16="Head of Household",'CONSTANTS & REFERENCES'!$M$10,""))))*AL16) -> 1606257 | AZ16: =IF(AY16="","",IF(A16=0,IF(OR(AK16="Single",AK16="Married Filing Separately"),'CONSTANTS & REFERENCES'!$C$10,IF(AK16="Married Filing Jointly",'CONSTANTS & REFERENCES'!$H$10,IF(AK16="Head of Household",'CONSTANTS & REFERENCES'!$M$10,""))),_xlfn.FLOOR.MATH(AY16,IF(AK16="Married Filing Separately",Bracket_Round_MFS,Bracket_Round_Standard)))) -> 1606250 | BA16: =IF(A16="","",IF(A16=0,"Official 2026 base values","Illustrative future tax assumptions under simplified C-CPI-U indexing; not an IRS forecast.")) -> Illustrative future tax assumptions under simplified C-CPI-U indexing; not an IRS forecast. | BB16: =IF(A16="","",'CONSTANTS & REFERENCES'!$C$22*AL16) -> 385576.92 | BC16: =IF(BB16="","",_xlfn.FLOOR.MATH(BB16,100)) -> 385500
A17: =IF(A16<INPUTS!$C$7-INPUTS!$C$6,A16+1,"") -> 15 | B17: =IF(A17="","",INPUTS!$C$6+A17) -> 37 | C17: =IF(A17="","",L16) -> 356917.6 | D17: =IF(A17="","",IF(A17<INPUTS!$C$13,0,J17)) -> 17500 | E17: =IF(A17="","",IF(D17=0,"—",IF(Y17<IF(AK17="Married Filing Jointly",'CONSTANTS & REFERENCES'!$B$44,IF(AK17="Married Filing Separately",'CONSTANTS & REFERENCES'!$B$45,'CONSTANTS & REFERENCES'!$B$43)),"Direct","Backdoor"))) -> Direct | F17: =IF(A17="","",$X$2*(1+$X$3)^A17) -> 17974.186 | G17: =IF(F17="","",_xlfn.FLOOR.MATH(F17,500)) -> 17500 | H17: =IF(A17="","",$X$4*(1+$X$3)^A17) -> 2636.214 | I17: =IF(H17="","",_xlfn.FLOOR.MATH(H17,100)) -> 2600 | J17: =IF(A17="","",G17+IF(B17>=50,I17,0)) -> 17500 | K17: =IF(A17="","",IF(INPUTS!$C$12="Beginning",(C17+D17)*INPUTS!$C$10,C17*INPUTS!$C$10)) -> 37441.76 | L17: =IF(A17="","",IF(INPUTS!$C$12="Beginning",(C17+D17)*(1+INPUTS!$C$10),C17*(1+INPUTS!$C$10)+D17)) -> 411859.36 | M17: =IF(A17="","",(1+INPUTS!$C$11)^A17) -> 2.3965582 | N17: =IF(A17="","",L17/M17) -> 171854.52 | O17: =IF(A17="","",O16+D17) -> 187500 | P17: =IF(A17="","",L17-INPUTS!$C$8-O17) -> 224359.36 | S17: =IF(B17="","",B17) -> 37 | T17: =IF(L17="","",L17) -> 411859.36 | U17: =IF(N17="","",N17) -> 171854.52 | V17: =IF(A17="","",FV(INPUTS!$C$10,INPUTS!$C$7-INPUTS!$C$6-A17+IF(INPUTS!$C$12="Beginning",1,0),0,-D17,0)) -> 277604.13 | Y17: =IF(A17="","",IF(INPUTS!$C$17="Yes",MIN(Y16*(1+INPUTS!$C$15)+IF(INPUTS!$C$27="Yes",(Z17-Z16)*INPUTS!$C$31+IF(AND(INPUTS!$C$28="Not yet credentialed",A17=INPUTS!$C$33),INPUTS!$C$32,0)+IF(AND(INPUTS!$C$28<>"FSA / FCAS",A17=INPUTS!$C$35),INPUTS!$C$34,0),0),INPUTS!$C$18),Y16*(1+INPUTS!$C$15)+IF(INPUTS!$C$27="Yes",(Z17-Z16)*INPUTS!$C$31+IF(AND(INPUTS!$C$28="Not yet credentialed",A17=INPUTS!$C$33),INPUTS!$C$32,0)+IF(AND(INPUTS!$C$28<>"FSA / FCAS",A17=INPUTS!$C$35),INPUTS!$C$34,0),0))) -> 142851.24 | Z17: =IF(A17="","",IF(AND(INPUTS!$C$27="Yes",INPUTS!$C$28<>"FSA / FCAS",ISNUMBER(INPUTS!$C$37)),MIN(A17*INPUTS!$C$37,INPUTS!$C$30),0)) -> 3 | AA17: =IF(A17="","",AN17) -> 70900 | AB17: =IF(OR(A17="",AA17=""),"",MAX(0,Y17-AA17)) -> 71951.243 | AC17: =IF(A17="","",MIN(AB17,AP17)*'CONSTANTS & REFERENCES'!$A$5+MAX(MIN(AB17,AR17)-AP17,0)*'CONSTANTS & REFERENCES'!$A$6+MAX(MIN(AB17,AT17)-AR17,0)*'CONSTANTS & REFERENCES'!$A$7+MAX(MIN(AB17,AV17)-AT17,0)*'CONSTANTS & REFERENCES'!$A$8+MAX(MIN(AB17,AX17)-AV17,0)*'CONSTANTS & REFERENCES'!$A$9+MAX(MIN(AB17,AZ17)-AX17,0)*'CONSTANTS & REFERENCES'!$A$10+MAX(AB17-AZ17,0)*'CONSTANTS & REFERENCES'!$A$11) -> 7542.1492 | AD17: =IF(AB17="","",IF(INPUTS!$C$20="Yes",AB17*INPUTS!$C$21,0)) -> 0 | AE17: =IF(Y17="","",MIN(Y17,BC17)*'CONSTANTS & REFERENCES'!$B$22) -> 8856.7771 | AF17: =IF(Y17="","",Y17*'CONSTANTS & REFERENCES'!$B$24+MAX(0,Y17-IF(AK17="Married Filing Jointly",'CONSTANTS & REFERENCES'!$C$26,IF(AK17="Married Filing Separately",'CONSTANTS & REFERENCES'!$C$27,IF(AK17="Head of Household",'CONSTANTS & REFERENCES'!$C$28,'CONSTANTS & REFERENCES'!$C$25))))*'CONSTANTS & REFERENCES'!$B$25) -> 2071.343 | AG17: =IF(Y17="","",AE17+AF17) -> 10928.12 | AH17: =IF(OR(AC17="",AG17=""),"",AC17+AD17+AG17) -> 18470.269 | AI17: =IF(AH17="","",Y17-AH17) -> 124380.97 | AJ17: =IF(AI17="","",Y17-AH17-AI17) -> 0 | AK17: =IF(A17="","",IF(AND(INPUTS!$C$43="Yes",A17>=INPUTS!$C$45),INPUTS!$C$44,INPUTS!$C$19)) -> Married Filing Jointly | AL17: =IF(A17="","",(1+$X$6)^A17) -> 2.202825 | AM17: =IF(A17="","",(IF(OR(AK17="Single",AK17="Married Filing Separately"),'CONSTANTS & REFERENCES'!$B$13,IF(AK17="Married Filing Jointly",'CONSTANTS & REFERENCES'!$G$13,IF(AK17="Head of Household",'CONSTANTS & REFERENCES'!$L$13,""))))*AL17) -> 70930.964 | AN17: =IF(AM17="","",IF(A17=0,IF(OR(AK17="Single",AK17="Married Filing Separately"),'CONSTANTS & REFERENCES'!$B$13,IF(AK17="Married Filing Jointly",'CONSTANTS & REFERENCES'!$G$13,IF(AK17="Head of Household",'CONSTANTS & REFERENCES'!$L$13,""))),_xlfn.FLOOR.MATH(AM17,IF(AK17="Married Filing Separately",Bracket_Round_MFS,Bracket_Round_Standard)))) -> 70900 | AO17: =IF(A17="","",(IF(OR(AK17="Single",AK17="Married Filing Separately"),'CONSTANTS & REFERENCES'!$C$5,IF(AK17="Married Filing Jointly",'CONSTANTS & REFERENCES'!$H$5,IF(AK17="Head of Household",'CONSTANTS & REFERENCES'!$M$5,""))))*AL17) -> 54630.059 | AP17: =IF(AO17="","",IF(A17=0,IF(OR(AK17="Single",AK17="Married Filing Separately"),'CONSTANTS & REFERENCES'!$C$5,IF(AK17="Married Filing Jointly",'CONSTANTS & REFERENCES'!$H$5,IF(AK17="Head of Household",'CONSTANTS & REFERENCES'!$M$5,""))),_xlfn.FLOOR.MATH(AO17,IF(AK17="Married Filing Separately",Bracket_Round_MFS,Bracket_Round_Standard)))) -> 54600 | AQ17: =IF(A17="","",(IF(OR(AK17="Single",AK17="Married Filing Separately"),'CONSTANTS & REFERENCES'!$C$6,IF(AK17="Married Filing Jointly",'CONSTANTS & REFERENCES'!$H$6,IF(AK17="Head of Household",'CONSTANTS & REFERENCES'!$M$6,""))))*AL17) -> 222044.76 | AR17: =IF(AQ17="","",IF(A17=0,IF(OR(AK17="Single",AK17="Married Filing Separately"),'CONSTANTS & REFERENCES'!$C$6,IF(AK17="Married Filing Jointly",'CONSTANTS & REFERENCES'!$H$6,IF(AK17="Head of Household",'CONSTANTS & REFERENCES'!$M$6,""))),_xlfn.FLOOR.MATH(AQ17,IF(AK17="Married Filing Separately",Bracket_Round_MFS,Bracket_Round_Standard)))) -> 222000 | AS17: =IF(A17="","",(IF(OR(AK17="Single",AK17="Married Filing Separately"),'CONSTANTS & REFERENCES'!$C$7,IF(AK17="Married Filing Jointly",'CONSTANTS & REFERENCES'!$H$7,IF(AK17="Head of Household",'CONSTANTS & REFERENCES'!$M$7,""))))*AL17) -> 465677.2 | AT17: =IF(AS17="","",IF(A17=0,IF(OR(AK17="Single",AK17="Married Filing Separately"),'CONSTANTS & REFERENCES'!$C$7,IF(AK17="Married Filing Jointly",'CONSTANTS & REFERENCES'!$H$7,IF(AK17="Head of Household",'CONSTANTS & REFERENCES'!$M$7,""))),_xlfn.FLOOR.MATH(AS17,IF(AK17="Married Filing Separately",Bracket_Round_MFS,Bracket_Round_Standard)))) -> 465650 | AU17: =IF(A17="","",(IF(OR(AK17="Single",AK17="Married Filing Separately"),'CONSTANTS & REFERENCES'!$C$8,IF(AK17="Married Filing Jointly",'CONSTANTS & REFERENCES'!$H$8,IF(AK17="Head of Household",'CONSTANTS & REFERENCES'!$M$8,""))))*AL17) -> 888950.02 | AV17: =IF(AU17="","",IF(A17=0,IF(OR(AK17="Single",AK17="Married Filing Separately"),'CONSTANTS & REFERENCES'!$C$8,IF(AK17="Married Filing Jointly",'CONSTANTS & REFERENCES'!$H$8,IF(AK17="Head of Household",'CONSTANTS & REFERENCES'!$M$8,""))),_xlfn.FLOOR.MATH(AU17,IF(AK17="Married Filing Separately",Bracket_Round_MFS,Bracket_Round_Standard)))) -> 888950 | AW17: =IF(A17="","",(IF(OR(AK17="Single",AK17="Married Filing Separately"),'CONSTANTS & REFERENCES'!$C$9,IF(AK17="Married Filing Jointly",'CONSTANTS & REFERENCES'!$H$9,IF(AK17="Head of Household",'CONSTANTS & REFERENCES'!$M$9,""))))*AL17) -> 1128837.7 | AX17: =IF(AW17="","",IF(A17=0,IF(OR(AK17="Single",AK17="Married Filing Separately"),'CONSTANTS & REFERENCES'!$C$9,IF(AK17="Married Filing Jointly",'CONSTANTS & REFERENCES'!$H$9,IF(AK17="Head of Household",'CONSTANTS & REFERENCES'!$M$9,""))),_xlfn.FLOOR.MATH(AW17,IF(AK17="Married Filing Separately",Bracket_Round_MFS,Bracket_Round_Standard)))) -> 1128800 | AY17: =IF(A17="","",(IF(OR(AK17="Single",AK17="Married Filing Separately"),'CONSTANTS & REFERENCES'!$C$10,IF(AK17="Married Filing Jointly",'CONSTANTS & REFERENCES'!$H$10,IF(AK17="Head of Household",'CONSTANTS & REFERENCES'!$M$10,""))))*AL17) -> 1693091.3 | AZ17: =IF(AY17="","",IF(A17=0,IF(OR(AK17="Single",AK17="Married Filing Separately"),'CONSTANTS & REFERENCES'!$C$10,IF(AK17="Married Filing Jointly",'CONSTANTS & REFERENCES'!$H$10,IF(AK17="Head of Household",'CONSTANTS & REFERENCES'!$M$10,""))),_xlfn.FLOOR.MATH(AY17,IF(AK17="Married Filing Separately",Bracket_Round_MFS,Bracket_Round_Standard)))) -> 1693050 | BA17: =IF(A17="","",IF(A17=0,"Official 2026 base values","Illustrative future tax assumptions under simplified C-CPI-U indexing; not an IRS forecast.")) -> Illustrative future tax assumptions under simplified C-CPI-U indexing; not an IRS forecast. | BB17: =IF(A17="","",'CONSTANTS & REFERENCES'!$C$22*AL17) -> 406421.21 | BC17: =IF(BB17="","",_xlfn.FLOOR.MATH(BB17,100)) -> 406400
A18: =IF(A17<INPUTS!$C$7-INPUTS!$C$6,A17+1,"") -> 16 | B18: =IF(A18="","",INPUTS!$C$6+A18) -> 38 | C18: =IF(A18="","",L17) -> 411859.36 | D18: =IF(A18="","",IF(A18<INPUTS!$C$13,0,J18)) -> 19000 | E18: =IF(A18="","",IF(D18=0,"—",IF(Y18<IF(AK18="Married Filing Jointly",'CONSTANTS & REFERENCES'!$B$44,IF(AK18="Married Filing Separately",'CONSTANTS & REFERENCES'!$B$45,'CONSTANTS & REFERENCES'!$B$43)),"Direct","Backdoor"))) -> Direct | F18: =IF(A18="","",$X$2*(1+$X$3)^A18) -> 19052.638 | G18: =IF(F18="","",_xlfn.FLOOR.MATH(F18,500)) -> 19000 | H18: =IF(A18="","",$X$4*(1+$X$3)^A18) -> 2794.3869 | I18: =IF(H18="","",_xlfn.FLOOR.MATH(H18,100)) -> 2700 | J18: =IF(A18="","",G18+IF(B18>=50,I18,0)) -> 19000 | K18: =IF(A18="","",IF(INPUTS!$C$12="Beginning",(C18+D18)*INPUTS!$C$10,C18*INPUTS!$C$10)) -> 43085.936 | L18: =IF(A18="","",IF(INPUTS!$C$12="Beginning",(C18+D18)*(1+INPUTS!$C$10),C18*(1+INPUTS!$C$10)+D18)) -> 473945.3 | M18: =IF(A18="","",(1+INPUTS!$C$11)^A18) -> 2.5403517 | N18: =IF(A18="","",L18/M18) -> 186566.81 | O18: =IF(A18="","",O17+D18) -> 206500 | P18: =IF(A18="","",L18-INPUTS!$C$8-O18) -> 267445.3 | S18: =IF(B18="","",B18) -> 38 | T18: =IF(L18="","",L18) -> 473945.3 | U18: =IF(N18="","",N18) -> 186566.81 | V18: =IF(A18="","",FV(INPUTS!$C$10,INPUTS!$C$7-INPUTS!$C$6-A18+IF(INPUTS!$C$12="Beginning",1,0),0,-D18,0)) -> 273998.88 | Y18: =IF(A18="","",IF(INPUTS!$C$17="Yes",MIN(Y17*(1+INPUTS!$C$15)+IF(INPUTS!$C$27="Yes",(Z18-Z17)*INPUTS!$C$31+IF(AND(INPUTS!$C$28="Not yet credentialed",A18=INPUTS!$C$33),INPUTS!$C$32,0)+IF(AND(INPUTS!$C$28<>"FSA / FCAS",A18=INPUTS!$C$35),INPUTS!$C$34,0),0),INPUTS!$C$18),Y17*(1+INPUTS!$C$15)+IF(INPUTS!$C$27="Yes",(Z18-Z17)*INPUTS!$C$31+IF(AND(INPUTS!$C$28="Not yet credentialed",A18=INPUTS!$C$33),INPUTS!$C$32,0)+IF(AND(INPUTS!$C$28<>"FSA / FCAS",A18=INPUTS!$C$35),INPUTS!$C$34,0),0))) -> 147136.78 | Z18: =IF(A18="","",IF(AND(INPUTS!$C$27="Yes",INPUTS!$C$28<>"FSA / FCAS",ISNUMBER(INPUTS!$C$37)),MIN(A18*INPUTS!$C$37,INPUTS!$C$30),0)) -> 3 | AA18: =IF(A18="","",AN18) -> 74750 | AB18: =IF(OR(A18="",AA18=""),"",MAX(0,Y18-AA18)) -> 72386.78 | AC18: =IF(A18="","",MIN(AB18,AP18)*'CONSTANTS & REFERENCES'!$A$5+MAX(MIN(AB18,AR18)-AP18,0)*'CONSTANTS & REFERENCES'!$A$6+MAX(MIN(AB18,AT18)-AR18,0)*'CONSTANTS & REFERENCES'!$A$7+MAX(MIN(AB18,AV18)-AT18,0)*'CONSTANTS & REFERENCES'!$A$8+MAX(MIN(AB18,AX18)-AV18,0)*'CONSTANTS & REFERENCES'!$A$9+MAX(MIN(AB18,AZ18)-AX18,0)*'CONSTANTS & REFERENCES'!$A$10+MAX(AB18-AZ18,0)*'CONSTANTS & REFERENCES'!$A$11) -> 7535.4137 | AD18: =IF(AB18="","",IF(INPUTS!$C$20="Yes",AB18*INPUTS!$C$21,0)) -> 0 | AE18: =IF(Y18="","",MIN(Y18,BC18)*'CONSTANTS & REFERENCES'!$B$22) -> 9122.4804 | AF18: =IF(Y18="","",Y18*'CONSTANTS & REFERENCES'!$B$24+MAX(0,Y18-IF(AK18="Married Filing Jointly",'CONSTANTS & REFERENCES'!$C$26,IF(AK18="Married Filing Separately",'CONSTANTS & REFERENCES'!$C$27,IF(AK18="Head of Household",'CONSTANTS & REFERENCES'!$C$28,'CONSTANTS & REFERENCES'!$C$25))))*'CONSTANTS & REFERENCES'!$B$25) -> 2133.4833 | AG18: =IF(Y18="","",AE18+AF18) -> 11255.964 | AH18: =IF(OR(AC18="",AG18=""),"",AC18+AD18+AG18) -> 18791.377 | AI18: =IF(AH18="","",Y18-AH18) -> 128345.4 | AJ18: =IF(AI18="","",Y18-AH18-AI18) -> 0 | AK18: =IF(A18="","",IF(AND(INPUTS!$C$43="Yes",A18>=INPUTS!$C$45),INPUTS!$C$44,INPUTS!$C$19)) -> Married Filing Jointly | AL18: =IF(A18="","",(1+$X$6)^A18) -> 2.3219097 | AM18: =IF(A18="","",(IF(OR(AK18="Single",AK18="Married Filing Separately"),'CONSTANTS & REFERENCES'!$B$13,IF(AK18="Married Filing Jointly",'CONSTANTS & REFERENCES'!$G$13,IF(AK18="Head of Household",'CONSTANTS & REFERENCES'!$L$13,""))))*AL18) -> 74765.492 | AN18: =IF(AM18="","",IF(A18=0,IF(OR(AK18="Single",AK18="Married Filing Separately"),'CONSTANTS & REFERENCES'!$B$13,IF(AK18="Married Filing Jointly",'CONSTANTS & REFERENCES'!$G$13,IF(AK18="Head of Household",'CONSTANTS & REFERENCES'!$L$13,""))),_xlfn.FLOOR.MATH(AM18,IF(AK18="Married Filing Separately",Bracket_Round_MFS,Bracket_Round_Standard)))) -> 74750 | AO18: =IF(A18="","",(IF(OR(AK18="Single",AK18="Married Filing Separately"),'CONSTANTS & REFERENCES'!$C$5,IF(AK18="Married Filing Jointly",'CONSTANTS & REFERENCES'!$H$5,IF(AK18="Head of Household",'CONSTANTS & REFERENCES'!$M$5,""))))*AL18) -> 57583.36 | AP18: =IF(AO18="","",IF(A18=0,IF(OR(AK18="Single",AK18="Married Filing Separately"),'CONSTANTS & REFERENCES'!$C$5,IF(AK18="Married Filing Jointly",'CONSTANTS & REFERENCES'!$H$5,IF(AK18="Head of Household",'CONSTANTS & REFERENCES'!$M$5,""))),_xlfn.FLOOR.MATH(AO18,IF(AK18="Married Filing Separately",Bracket_Round_MFS,Bracket_Round_Standard)))) -> 57550 | AQ18: =IF(A18="","",(IF(OR(AK18="Single",AK18="Married Filing Separately"),'CONSTANTS & REFERENCES'!$C$6,IF(AK18="Married Filing Jointly",'CONSTANTS & REFERENCES'!$H$6,IF(AK18="Head of Household",'CONSTANTS & REFERENCES'!$M$6,""))))*AL18) -> 234048.5 | AR18: =IF(AQ18="","",IF(A18=0,IF(OR(AK18="Single",AK18="Married Filing Separately"),'CONSTANTS & REFERENCES'!$C$6,IF(AK18="Married Filing Jointly",'CONSTANTS & REFERENCES'!$H$6,IF(AK18="Head of Household",'CONSTANTS & REFERENCES'!$M$6,""))),_xlfn.FLOOR.MATH(AQ18,IF(AK18="Married Filing Separately",Bracket_Round_MFS,Bracket_Round_Standard)))) -> 234000 | AS18: =IF(A18="","",(IF(OR(AK18="Single",AK18="Married Filing Separately"),'CONSTANTS & REFERENCES'!$C$7,IF(AK18="Married Filing Jointly",'CONSTANTS & REFERENCES'!$H$7,IF(AK18="Head of Household",'CONSTANTS & REFERENCES'!$M$7,""))))*AL18) -> 490851.71 | AT18: =IF(AS18="","",IF(A18=0,IF(OR(AK18="Single",AK18="Married Filing Separately"),'CONSTANTS & REFERENCES'!$C$7,IF(AK18="Married Filing Jointly",'CONSTANTS & REFERENCES'!$H$7,IF(AK18="Head of Household",'CONSTANTS & REFERENCES'!$M$7,""))),_xlfn.FLOOR.MATH(AS18,IF(AK18="Married Filing Separately",Bracket_Round_MFS,Bracket_Round_Standard)))) -> 490850 | AU18: =IF(A18="","",(IF(OR(AK18="Single",AK18="Married Filing Separately"),'CONSTANTS & REFERENCES'!$C$8,IF(AK18="Married Filing Jointly",'CONSTANTS & REFERENCES'!$H$8,IF(AK18="Head of Household",'CONSTANTS & REFERENCES'!$M$8,""))))*AL18) -> 937006.66 | AV18: =IF(AU18="","",IF(A18=0,IF(OR(AK18="Single",AK18="Married Filing Separately"),'CONSTANTS & REFERENCES'!$C$8,IF(AK18="Married Filing Jointly",'CONSTANTS & REFERENCES'!$H$8,IF(AK18="Head of Household",'CONSTANTS & REFERENCES'!$M$8,""))),_xlfn.FLOOR.MATH(AU18,IF(AK18="Married Filing Separately",Bracket_Round_MFS,Bracket_Round_Standard)))) -> 937000 | AW18: =IF(A18="","",(IF(OR(AK18="Single",AK18="Married Filing Separately"),'CONSTANTS & REFERENCES'!$C$9,IF(AK18="Married Filing Jointly",'CONSTANTS & REFERENCES'!$H$9,IF(AK18="Head of Household",'CONSTANTS & REFERENCES'!$M$9,""))))*AL18) -> 1189862.6 | AX18: =IF(AW18="","",IF(A18=0,IF(OR(AK18="Single",AK18="Married Filing Separately"),'CONSTANTS & REFERENCES'!$C$9,IF(AK18="Married Filing Jointly",'CONSTANTS & REFERENCES'!$H$9,IF(AK18="Head of Household",'CONSTANTS & REFERENCES'!$M$9,""))),_xlfn.FLOOR.MATH(AW18,IF(AK18="Married Filing Separately",Bracket_Round_MFS,Bracket_Round_Standard)))) -> 1189850 | AY18: =IF(A18="","",(IF(OR(AK18="Single",AK18="Married Filing Separately"),'CONSTANTS & REFERENCES'!$C$10,IF(AK18="Married Filing Jointly",'CONSTANTS & REFERENCES'!$H$10,IF(AK18="Head of Household",'CONSTANTS & REFERENCES'!$M$10,""))))*AL18) -> 1784619.8 | AZ18: =IF(AY18="","",IF(A18=0,IF(OR(AK18="Single",AK18="Married Filing Separately"),'CONSTANTS & REFERENCES'!$C$10,IF(AK18="Married Filing Jointly",'CONSTANTS & REFERENCES'!$H$10,IF(AK18="Head of Household",'CONSTANTS & REFERENCES'!$M$10,""))),_xlfn.FLOOR.MATH(AY18,IF(AK18="Married Filing Separately",Bracket_Round_MFS,Bracket_Round_Standard)))) -> 1784600 | BA18: =IF(A18="","",IF(A18=0,"Official 2026 base values","Illustrative future tax assumptions under simplified C-CPI-U indexing; not an IRS forecast.")) -> Illustrative future tax assumptions under simplified C-CPI-U indexing; not an IRS forecast. | BB18: =IF(A18="","",'CONSTANTS & REFERENCES'!$C$22*AL18) -> 428392.34 | BC18: =IF(BB18="","",_xlfn.FLOOR.MATH(BB18,100)) -> 428300
